Workbook

Sheet CA07-本月-盘点结果
A1: 行号 | B1: 物料编码 | C1: 物料名称 | D1: 库存数量 | E1: 盘点数量 | F1: 单位 | G1: 单位编码 | H1: 单位描述 | I1: 使用数量 | J1: 单价 | K1: 本月使用金额 | L1: 上月使用金额 | M1: 对比 | N1: 备注（每月刷新） | O1: 回复 | P1: 分类
A2: 1 | B2: 4509073 | C2: "猪骨膏（SOMI，2.2LB*10包/箱）" | D2: 737 | E2: 330 | F2: 磅（美国） | G2: LB | H2: 磅（美国） | I2: =D2-E2 -> 407 | J2: =VLOOKUP(B2,本月系统单价mb5b!$B:$P,15,0) -> 9.6444776 | K2: =I2*J2 -> 3925.3024 | L2: =IFERROR(VLOOKUP(B2,上月数量需更新!A:C,3,0),0) -> 1540.02 | M2: =K2-L2 -> 2385.2824 | P2: =VLOOKUP(B2,物料分类!B:F,5,0) -> 成本-锅底类
A3: 201 | B3: 8011286 | C3: 易拉罐PET瓶（小口盖，100个/箱） | D3: 6400 | E3: 1900 | F3: 个 | G3: Z05 | H3: 个 | I3: =D3-E3 -> 4500 | J3: =VLOOKUP(B3,本月系统单价mb5b!$B:$P,15,0) -> 0.54213437 | K3: =I3*J3 -> 2439.6047 | L3: =IFERROR(VLOOKUP(B3,上月数量需更新!A:C,3,0),0) -> 2607.27 | M3: =K3-L3 -> -167.66531 | P3: =VLOOKUP(B3,物料分类!B:F,5,0) -> 物料消耗
A4: 3 | B4: 8014686 | C4: 320咖啡杯（30个/箱） | D4: 30 | E4: 30 | F4: 个 | G4: Z05 | H4: 个 | I4: =D4-E4 -> 0 | J4: =VLOOKUP(B4,本月系统单价mb5b!$B:$P,15,0) -> 8.3946667 | K4: =I4*J4 -> 0 | L4: =IFERROR(VLOOKUP(B4,上月数量需更新!A:C,3,0),0) -> 251.84 | M4: =K4-L4 -> -251.84 | P4: =VLOOKUP(B4,物料分类!B:F,5,0) -> 服务费
A5: 4 | B5: 8014689 | C5: 320折叠椅（30个/箱） | D5: 50 | E5: 50 | F5: 个 | G5: Z05 | H5: 个 | I5: =D5-E5 -> 0 | J5: =VLOOKUP(B5,本月系统单价mb5b!$B:$P,15,0) -> 12.5544 | K5: =I5*J5 -> 0 | L5: =IFERROR(VLOOKUP(B5,上月数量需更新!A:C,3,0),0) -> 125.55 | M5: =K5-L5 -> -125.55 | P5: =VLOOKUP(B5,物料分类!B:F,5,0) -> 服务费
A6: 5 | B6: 8014621 | C6: 320毛绒骰子（配套地贴使用，4个/套） | D6: 19 | E6: 19 | F6: 套 | G6: Z16 | H6: 套 | I6: =D6-E6 -> 0 | J6: =VLOOKUP(B6,本月系统单价mb5b!$B:$P,15,0) -> 62.245789 | K6: =I6*J6 -> 0 | L6: =IFERROR(VLOOKUP(B6,上月数量需更新!A:C,3,0),0) -> 0 | M6: =K6-L6 -> 0 | P6: =VLOOKUP(B6,物料分类!B:F,5,0) -> 服务费
A7: 197 | B7: 8011401 | C7: 无纺布打包袋（27.5*17*24CM） | D7: 11000 | E7: 3000 | F7: 个 | G7: Z05 | H7: 个 | I7: =D7-E7 -> 8000 | J7: =VLOOKUP(B7,本月系统单价mb5b!$B:$P,15,0) -> 0.24741273 | K7: =I7*J7 -> 1979.3018 | L7: =IFERROR(VLOOKUP(B7,上月数量需更新!A:C,3,0),0) -> 378.13 | M7: =K7-L7 -> 1601.1718 | P7: =VLOOKUP(B7,物料分类!B:F,5,0) -> 物料消耗
A8: 450 | B8: 8704096 | C8: 酒精湿巾（海底捞，独立包装，100片*14包/箱） | D8: 490 | E8: 84 | F8: 包 | G8: Z07 | H8: 包 | I8: =D8-E8 -> 406 | J8: =VLOOKUP(B8,本月系统单价mb5b!$B:$P,15,0) -> 4.0438367 | K8: =I8*J8 -> 1641.7977 | L8: =IFERROR(VLOOKUP(B8,上月数量需更新!A:C,3,0),0) -> 1687.01 | M8: =K8-L8 -> -45.212286 | P8: =VLOOKUP(B8,物料分类!B:F,5,0) -> 物料消耗
A9: 8 | B9: 1500911 | C9: ASAKI啤酒（330ML*24瓶/箱） | D9: 3217 | E9: 3070 | F9: 瓶 | G9: BOT | H9: 瓶 | I9: =D9-E9 -> 147 | J9: =VLOOKUP(B9,本月系统单价mb5b!$B:$P,15,0) -> 2.1549829 | K9: =I9*J9 -> 316.78249 | L9: =IFERROR(VLOOKUP(B9,上月数量需更新!A:C,3,0),0) -> 249.98 | M9: =K9-L9 -> 66.802487 | N9: =VLOOKUP(B9,计算!R:X,7,0) -> 多使用1瓶 | O9: 盤點无誤 | P9: =VLOOKUP(B9,物料分类!B:F,5,0) -> 成本-酒水类
A10: 9 | B10: 1501193 | C10: BC肉蟹（LB） | D10: 10.84 | E10: 2.288 | F10: 磅 | G10: CL5 | H10: 美 | I10: =D10-E10 -> 8.552 | J10: =VLOOKUP(B10,本月系统单价mb5b!$B:$P,15,0) -> 19.607011 | K10: =I10*J10 -> 167.67916 | L10: =IFERROR(VLOOKUP(B10,上月数量需更新!A:C,3,0),0) -> 74.34 | M10: =K10-L10 -> 93.339159 | P10: =VLOOKUP(B10,物料分类!B:F,5,0) -> 成本-荤菜类
A11: 26 | B11: 8011001 | C11: 一次性无纺布围裙（成人款，50条*20袋/箱） | D11: 11000 | E11: 5000 | F11: 条 | G11: Z19 | H11: 条 | I11: =D11-E11 -> 6000 | J11: =VLOOKUP(B11,本月系统单价mb5b!$B:$P,15,0) -> 0.19297545 | K11: =I11*J11 -> 1157.8527 | L11: =IFERROR(VLOOKUP(B11,上月数量需更新!A:C,3,0),0) -> 1929.76 | M11: =K11-L11 -> -771.90727 | P11: =VLOOKUP(B11,物料分类!B:F,5,0) -> 物料消耗
A12: 49 | B12: 8703542 | C12: 儿童餐盘（硅胶，40个/件） | D12: 200 | E12: 100 | F12: 个 | G12: Z05 | H12: 个 | I12: =D12-E12 -> 100 | J12: =VLOOKUP(B12,本月系统单价mb5b!$B:$P,15,0) -> 9.12505 | K12: =I12*J12 -> 912.505 | L12: =IFERROR(VLOOKUP(B12,上月数量需更新!A:C,3,0),0) -> 0 | M12: =K12-L12 -> 912.505 | P12: =VLOOKUP(B12,物料分类!B:F,5,0) -> 物料消耗
A13: 12 | B13: 4521260 | C13: CAESAR酱（3.78L*2瓶/箱） | D13: 22.68 | E13: 7.56 | F13: 升 | G13: L | H13: 公升 | I13: =D13-E13 -> 15.12 | J13: =VLOOKUP(B13,本月系统单价mb5b!$B:$P,15,0) -> 9.5952381 | K13: =I13*J13 -> 145.08 | L13: =IFERROR(VLOOKUP(B13,上月数量需更新!A:C,3,0),0) -> 74.69 | M13: =K13-L13 -> 70.39 | P13: =VLOOKUP(B13,物料分类!B:F,5,0) -> 成本-小料台类
A14: 13 | B14: 4505451 | C14: GLENFIDDICH 18（750ML/瓶） | D14: 1 | E14: 1 | F14: 瓶 | G14: BOT | H14: 瓶 | I14: =D14-E14 -> 0 | J14: =VLOOKUP(B14,本月系统单价mb5b!$B:$P,15,0) -> 57.31 | K14: =I14*J14 -> 0 | L14: =IFERROR(VLOOKUP(B14,上月数量需更新!A:C,3,0),0) -> 0 | M14: =K14-L14 -> 0 | P14: =VLOOKUP(B14,物料分类!B:F,5,0) -> 成本-酒水类
A15: 14 | B15: 4505448 | C15: JACK DANIELS （750ML/瓶） | D15: 1 | E15: 1 | F15: 瓶 | G15: BOT | H15: 瓶 | I15: =D15-E15 -> 0 | J15: =VLOOKUP(B15,本月系统单价mb5b!$B:$P,15,0) -> 29.25 | K15: =I15*J15 -> 0 | L15: =IFERROR(VLOOKUP(B15,上月数量需更新!A:C,3,0),0) -> 0 | M15: =K15-L15 -> 0 | P15: =VLOOKUP(B15,物料分类!B:F,5,0) -> 成本-酒水类
A16: 15 | B16: 4518902 | C16: KIRKLAND矿泉水（500ML*35瓶/箱） | D16: 35 | E16: 0 | F16: 瓶 | G16: BOT | H16: 瓶 | I16: =D16-E16 -> 35 | J16: =VLOOKUP(B16,本月系统单价mb5b!$B:$P,15,0) -> 0.21171429 | K16: =I16*J16 -> 7.41 | L16: =IFERROR(VLOOKUP(B16,上月数量需更新!A:C,3,0),0) -> 37.03 | M16: =K16-L16 -> -29.62 | P16: =VLOOKUP(B16,物料分类!B:F,5,0) -> 成本-酒水类
A17: 16 | B17: 4518131 | C17: KOOKSOONDANG（750ML*20瓶/箱） | D17: 716 | E17: 675 | F17: 瓶 | G17: BOT | H17: 瓶 | I17: =D17-E17 -> 41 | J17: =VLOOKUP(B17,本月系统单价mb5b!$B:$P,15,0) -> 5.38 | K17: =I17*J17 -> 220.58 | L17: =IFERROR(VLOOKUP(B17,上月数量需更新!A:C,3,0),0) -> 182.92 | M17: =K17-L17 -> 37.66 | N17: =VLOOKUP(B17,计算!R:X,7,0) -> 多使用26瓶 | O17: 少算了一箱,是695 | P17: =VLOOKUP(B17,物料分类!B:F,5,0) -> 成本-酒水类
A18: 17 | B18: 4528292 | C18: MALIBUCOCONUTRUMLIQUEUR（750ML/瓶） | D18: 3 | E18: 3 | F18: 瓶 | G18: BOT | H18: 瓶 | I18: =D18-E18 -> 0 | J18: =VLOOKUP(B18,本月系统单价mb5b!$B:$P,15,0) -> 19.97 | K18: =I18*J18 -> 0 | L18: =IFERROR(VLOOKUP(B18,上月数量需更新!A:C,3,0),0) -> 0 | M18: =K18-L18 -> 0 | P18: =VLOOKUP(B18,物料分类!B:F,5,0) -> 成本-酒水类
A19: 18 | B19: 4528291 | C19: MIDORI-MELON（750ML/瓶） | D19: 1 | E19: 0 | F19: 瓶 | G19: BOT | H19: 瓶 | I19: =D19-E19 -> 1 | J19: =VLOOKUP(B19,本月系统单价mb5b!$B:$P,15,0) -> 24.43 | K19: =I19*J19 -> 24.43 | L19: =IFERROR(VLOOKUP(B19,上月数量需更新!A:C,3,0),0) -> 0 | M19: =K19-L19 -> 24.43 | P19: =VLOOKUP(B19,物料分类!B:F,5,0) -> 成本-酒水类
A20: 264 | B20: 1500919 | C20: 洗碗液（红色， 20L/桶） | D20: 11 | E20: 0 | F20: 桶 | G20: Z36 | H20: 桶 | I20: =D20-E20 -> 11 | J20: =VLOOKUP(B20,本月系统单价mb5b!$B:$P,15,0) -> 82.12 | K20: =I20*J20 -> 903.32 | L20: =IFERROR(VLOOKUP(B20,上月数量需更新!A:C,3,0),0) -> 574.84 | M20: =K20-L20 -> 328.48 | P20: =VLOOKUP(B20,物料分类!B:F,5,0) -> 物料消耗
A21: 20 | B21: 4514744 | C21: SALSA辣酱（3.7L*2瓶/箱） | D21: 18 | E21: 11.1 | F21: 瓶 | G21: BOT | H21: 瓶 | I21: =D21-E21 -> 6.9 | J21: =VLOOKUP(B21,本月系统单价mb5b!$B:$P,15,0) -> 27.696111 | K21: =I21*J21 -> 191.10317 | L21: =IFERROR(VLOOKUP(B21,上月数量需更新!A:C,3,0),0) -> 525.99 | M21: =K21-L21 -> -334.88683 | P21: =VLOOKUP(B21,物料分类!B:F,5,0) -> 成本-小料台类
A22: 21 | B22: 4515975 | C22: SOHO LYCHEE荔枝酒（750ML/瓶） | D22: 8 | E22: 4 | F22: 瓶 | G22: BOT | H22: 瓶 | I22: =D22-E22 -> 4 | J22: =VLOOKUP(B22,本月系统单价mb5b!$B:$P,15,0) -> 26.76 | K22: =I22*J22 -> 107.04 | L22: =IFERROR(VLOOKUP(B22,上月数量需更新!A:C,3,0),0) -> 53.56 | M22: =K22-L22 -> 53.48 | P22: =VLOOKUP(B22,物料分类!B:F,5,0) -> 成本-酒水类
A23: 22 | B23: 4528183 | C23: UN-CHILLFILTEREDWHISKY（KAIYO，750ML/瓶） | D23: 1 | E23: 1 | F23: 瓶 | G23: BOT | H23: 瓶 | I23: =D23-E23 -> 0 | J23: =VLOOKUP(B23,本月系统单价mb5b!$B:$P,15,0) -> 96.72 | K23: =I23*J23 -> 0 | L23: =IFERROR(VLOOKUP(B23,上月数量需更新!A:C,3,0),0) -> 0 | M23: =K23-L23 -> 0 | P23: =VLOOKUP(B23,物料分类!B:F,5,0) -> 成本-酒水类
A24: 263 | B24: 1501010 | C24: 洗洁精（4L*4桶/箱） | D24: 148 | E24: 28 | F24: 桶 | G24: Z36 | H24: 桶 | I24: =D24-E24 -> 120 | J24: =VLOOKUP(B24,本月系统单价mb5b!$B:$P,15,0) -> 7.5 | K24: =I24*J24 -> 900 | L24: =IFERROR(VLOOKUP(B24,上月数量需更新!A:C,3,0),0) -> 810 | M24: =K24-L24 -> 90 | P24: =VLOOKUP(B24,物料分类!B:F,5,0) -> 物料消耗
A25: 151 | B25: 4003246 | C25: 客人围裙（黑色红边，20条/捆） | D25: 400 | E25: 20 | F25: 条 | G25: Z19 | H25: 条 | I25: =D25-E25 -> 380 | J25: =VLOOKUP(B25,本月系统单价mb5b!$B:$P,15,0) -> 2.16645 | K25: =I25*J25 -> 823.251 | L25: =IFERROR(VLOOKUP(B25,上月数量需更新!A:C,3,0),0) -> 433.29 | M25: =K25-L25 -> 389.961 | P25: =VLOOKUP(B25,物料分类!B:F,5,0) -> 物料消耗
A26: 282 | B26: 4529698 | C26: 漂白水（餐具专用，4L*4桶/箱） | D26: 76 | E26: 16 | F26: 桶 | G26: Z36 | H26: 桶 | I26: =D26-E26 -> 60 | J26: =VLOOKUP(B26,本月系统单价mb5b!$B:$P,15,0) -> 9.25 | K26: =I26*J26 -> 555 | L26: =IFERROR(VLOOKUP(B26,上月数量需更新!A:C,3,0),0) -> 342.25 | M26: =K26-L26 -> 212.75 | P26: =VLOOKUP(B26,物料分类!B:F,5,0) -> 物料消耗
A27: 104 | B27: 4000642 | C27: 双层抽纸（清风，130抽*96包/件） | D27: 1728 | E27: 288 | F27: 包 | G27: Z07 | H27: 包 | I27: =D27-E27 -> 1440 | J27: =VLOOKUP(B27,本月系统单价mb5b!$B:$P,15,0) -> 0.36471065 | K27: =I27*J27 -> 525.18333 | L27: =IFERROR(VLOOKUP(B27,上月数量需更新!A:C,3,0),0) -> 560.2 | M27: =K27-L27 -> -35.016667 | P27: =VLOOKUP(B27,物料分类!B:F,5,0) -> 物料消耗
A28: 27 | B28: 1501000 | C28: 一次性汤勺（1000个/箱） | D28: 19000 | E28: 6000 | F28: 个 | G28: Z05 | H28: 个 | I28: =D28-E28 -> 13000 | J28: =VLOOKUP(B28,本月系统单价mb5b!$B:$P,15,0) -> 0.039278947 | K28: =I28*J28 -> 510.62632 | L28: =IFERROR(VLOOKUP(B28,上月数量需更新!A:C,3,0),0) -> 698.4 | M28: =K28-L28 -> -187.77368 | P28: =VLOOKUP(B28,物料分类!B:F,5,0) -> 物料消耗
A29: 47 | B29: 1500979 | C29: 保鲜膜（762M*27.9CM/卷） | D29: 39 | E29: 13 | F29: 卷 | G29: Z08 | H29: 卷 | I29: =D29-E29 -> 26 | J29: =VLOOKUP(B29,本月系统单价mb5b!$B:$P,15,0) -> 19.276667 | K29: =I29*J29 -> 501.19333 | L29: =IFERROR(VLOOKUP(B29,上月数量需更新!A:C,3,0),0) -> 386.98 | M29: =K29-L29 -> 114.21333 | P29: =VLOOKUP(B29,物料分类!B:F,5,0) -> 物料消耗
... A102: 101 | B102: 4515419 | C102: 去肥黄瓜条（LB） | D102: 414.42 | E102: 94.6 | F102: 磅 | G102: CL5 | H102: 美 | I102: =D102-E102 -> 319.82 | J102: =VLOOKUP(B102,本月系统单价mb5b!$B:$P,15,0) -> 6.3235606 | K102: =I102*J102 -> 2022.4012 | L102: =IFERROR(VLOOKUP(B102,上月数量需更新!A:C,3,0),0) -> 2397.15 | M102: =K102-L102 -> -374.74884 | P102: =VLOOKUP(B102,物料分类!B:F,5,0) -> 成本-荤菜类
A103: 102 | B103: 4522918 | C103: 去骨牛小排（LB） | D103: 714.41 | E103: 103.67 | F103: 磅 | G103: CL5 | H103: 美 | I103: =D103-E103 -> 610.74 | J103: =VLOOKUP(B103,本月系统单价mb5b!$B:$P,15,0) -> 21.414034 | K103: =I103*J103 -> 13078.407 | L103: =IFERROR(VLOOKUP(B103,上月数量需更新!A:C,3,0),0) -> 10291.88 | M103: =K103-L103 -> 2786.5271 | N103: =VLOOKUP(B103,计算!R:X,7,0) -> 多使用105磅 | O103: 麻辣燙和烤肉套餐使用 | P103: =VLOOKUP(B103,物料分类!B:F,5,0) -> 成本-荤菜类
A104: 6 | B104: 8011411 | C104: 59G热敏收银纸（80*60MM，120卷/箱） | D104: 480 | E104: 120 | F104: 卷 | G104: Z08 | H104: 卷 | I104: =D104-E104 -> 360 | J104: =VLOOKUP(B104,本月系统单价mb5b!$B:$P,15,0) -> 0.64783333 | K104: =I104*J104 -> 233.22 | L104: =IFERROR(VLOOKUP(B104,上月数量需更新!A:C,3,0),0) -> 162.56 | M104: =K104-L104 -> 70.66 | P104: =VLOOKUP(B104,物料分类!B:F,5,0) -> 物料消耗
A105: 28 | B105: 4021486 | C105: 一次性纸杯（海底捞门店专用，50个*20提/件） | D105: 13000 | E105: 5000 | F105: 个 | G105: Z05 | H105: 个 | I105: =D105-E105 -> 8000 | J105: =VLOOKUP(B105,本月系统单价mb5b!$B:$P,15,0) -> 0.026607692 | K105: =I105*J105 -> 212.86154 | L105: =IFERROR(VLOOKUP(B105,上月数量需更新!A:C,3,0),0) -> 53.21 | M105: =K105-L105 -> 159.65154 | P105: =VLOOKUP(B105,物料分类!B:F,5,0) -> 物料消耗
A106: 105 | B106: 8014496 | C106: 变形车玩具（加拿大，3岁及以上，火箭人款，50个/件） | D106: 1000 | E106: 0 | F106: 个 | G106: Z05 | H106: 个 | I106: =D106-E106 -> 1000 | J106: =VLOOKUP(B106,本月系统单价mb5b!$B:$P,15,0) -> 0.80881 | K106: =I106*J106 -> 808.81 | L106: =IFERROR(VLOOKUP(B106,上月数量需更新!A:C,3,0),0) -> 0 | M106: =K106-L106 -> 808.81 | P106: =VLOOKUP(B106,物料分类!B:F,5,0) -> 服务费
A107: 106 | B107: 1500902 | C107: 可口可乐（355ML*32听/箱） | D107: 1259 | E107: 323 | F107: 听 | G107: Z01 | H107: 听 | I107: =D107-E107 -> 936 | J107: =VLOOKUP(B107,本月系统单价mb5b!$B:$P,15,0) -> 0.50996823 | K107: =I107*J107 -> 477.33026 | L107: =IFERROR(VLOOKUP(B107,上月数量需更新!A:C,3,0),0) -> 344.44 | M107: =K107-L107 -> 132.89026 | P107: =VLOOKUP(B107,物料分类!B:F,5,0) -> 成本-酒水类
A108: 175 | B108: 4505865 | C108: 打包盒盖子（1.5L，300个/箱） | D108: 3000 | E108: 900 | F108: 个 | G108: Z05 | H108: 个 | I108: =D108-E108 -> 2100 | J108: =VLOOKUP(B108,本月系统单价mb5b!$B:$P,15,0) -> 0.1 | K108: =I108*J108 -> 210 | L108: =IFERROR(VLOOKUP(B108,上月数量需更新!A:C,3,0),0) -> 240 | M108: =K108-L108 -> -30 | P108: =VLOOKUP(B108,物料分类!B:F,5,0) -> 物料消耗
A109: 285 | B109: 8010886 | C109: 潜心碟（华南，白瓷，6寸，100个/件） | D109: 200 | E109: 0 | F109: 个 | G109: Z05 | H109: 个 | I109: =D109-E109 -> 200 | J109: =VLOOKUP(B109,本月系统单价mb5b!$B:$P,15,0) -> 0.89215 | K109: =I109*J109 -> 178.43 | L109: =IFERROR(VLOOKUP(B109,上月数量需更新!A:C,3,0),0) -> 0 | M109: =K109-L109 -> 178.43 | P109: =VLOOKUP(B109,物料分类!B:F,5,0) -> 物料消耗
A110: 109 | B110: 4526645 | C110: 君度（750ML/瓶） | D110: 2 | E110: 2 | F110: 瓶 | G110: BOT | H110: 瓶 | I110: =D110-E110 -> 0 | J110: =VLOOKUP(B110,本月系统单价mb5b!$B:$P,15,0) -> 33.85 | K110: =I110*J110 -> 0 | L110: =IFERROR(VLOOKUP(B110,上月数量需更新!A:C,3,0),0) -> 0 | M110: =K110-L110 -> 0 | P110: =VLOOKUP(B110,物料分类!B:F,5,0) -> 成本-酒水类
A111: 110 | B111: 4501989 | C111: 味精（50LB/包） | D111: 80 | E111: 45 | F111: 磅 | G111: CL5 | H111: 美 | I111: =D111-E111 -> 35 | J111: =VLOOKUP(B111,本月系统单价mb5b!$B:$P,15,0) -> 1.2 | K111: =I111*J111 -> 42 | L111: =IFERROR(VLOOKUP(B111,上月数量需更新!A:C,3,0),0) -> 36 | M111: =K111-L111 -> 6 | P111: =VLOOKUP(B111,物料分类!B:F,5,0) -> 成本-小料台类
A112: 527 | B112: 4516323 | C112: 黑色手套L号（100个*10盒/箱） | D112: 4000 | E112: 0 | F112: 个 | G112: Z05 | H112: 个 | I112: =D112-E112 -> 4000 | J112: =VLOOKUP(B112,本月系统单价mb5b!$B:$P,15,0) -> 0.0429875 | K112: =I112*J112 -> 171.95 | L112: =IFERROR(VLOOKUP(B112,上月数量需更新!A:C,3,0),0) -> 0 | M112: =K112-L112 -> 171.95 | P112: =VLOOKUP(B112,物料分类!B:F,5,0) -> 物料消耗
A113: 112 | B113: 1500781 | C113: 咖色鸡蛋（30颗*6板/箱） | D113: 164 | E113: 22 | F113: 板 | G113: Z26 | H113: 板 | I113: =D113-E113 -> 142 | J113: =VLOOKUP(B113,本月系统单价mb5b!$B:$P,15,0) -> 11.915488 | K113: =I113*J113 -> 1691.9993 | L113: =IFERROR(VLOOKUP(B113,上月数量需更新!A:C,3,0),0) -> 2284.94 | M113: =K113-L113 -> -592.94073 | P113: =VLOOKUP(B113,物料分类!B:F,5,0) -> 成本-荤菜类
A114: 113 | B114: 4522916 | C114: 咸蛋黄鱼丸（1LB*20包/箱） | D114: 116 | E114: 20 | F114: 磅 | G114: CL5 | H114: 美 | I114: =D114-E114 -> 96 | J114: =VLOOKUP(B114,本月系统单价mb5b!$B:$P,15,0) -> 7.25 | K114: =I114*J114 -> 696 | L114: =IFERROR(VLOOKUP(B114,上月数量需更新!A:C,3,0),0) -> 819.25 | M114: =K114-L114 -> -123.25 | P114: =VLOOKUP(B114,物料分类!B:F,5,0) -> 成本-荤菜类
A115: 114 | B115: 4530204 | C115: 哈密瓜冰淇淋（75ML*36个/箱） | D115: 5616 | E115: 432 | F115: 个 | G115: Z05 | H115: 个 | I115: =D115-E115 -> 5184 | J115: =VLOOKUP(B115,本月系统单价mb5b!$B:$P,15,0) -> 0.45 | K115: =I115*J115 -> 2332.8 | L115: =IFERROR(VLOOKUP(B115,上月数量需更新!A:C,3,0),0) -> 243 | M115: =K115-L115 -> 2089.8 | P115: =VLOOKUP(B115,物料分类!B:F,5,0) -> 成本-小料台类
... A118: 117 | B118: 4505992 | C118: 啤酒瓶子定金 | D118: 68 | E118: 0 | F118: 瓶 | G118: BOT | H118: 瓶 | I118: =D118-E118 -> 68 | J118: =VLOOKUP(B118,本月系统单价mb5b!$B:$P,15,0) -> 0.1 | K118: =I118*J118 -> 6.8 | L118: =IFERROR(VLOOKUP(B118,上月数量需更新!A:C,3,0),0) -> 14 | M118: =K118-L118 -> -7.2 | P118: =VLOOKUP(B118,物料分类!B:F,5,0) -> 成本-酒水类
A119: 118 | B119: 4528801 | C119: 啤酒（SAPPORO，30L/桶） | D119: 25.5 | E119: 7 | F119: 桶 | G119: Z36 | H119: 桶 | I119: =D119-E119 -> 18.5 | J119: =VLOOKUP(B119,本月系统单价mb5b!$B:$P,15,0) -> 127.97843 | K119: =I119*J119 -> 2367.601 | L119: =IFERROR(VLOOKUP(B119,上月数量需更新!A:C,3,0),0) -> 2621.97 | M119: =K119-L119 -> -254.36902 | N119: =VLOOKUP(B119,计算!R:X,7,0) -> 少使用4桶 | O119: 盤點无誤(上個月多用了三桶) | P119: =VLOOKUP(B119,物料分类!B:F,5,0) -> 成本-酒水类
A120: 119 | B120: 4529794 | C120: 喷射奶油（KIRKLAND，400G*2罐/袋） | D120: 25 | E120: 7 | F120: 罐 | G120: CL9 | H120: 罐 | I120: =D120-E120 -> 18 | J120: =VLOOKUP(B120,本月系统单价mb5b!$B:$P,15,0) -> 4.9948 | K120: =I120*J120 -> 89.9064 | L120: =IFERROR(VLOOKUP(B120,上月数量需更新!A:C,3,0),0) -> 59.94 | M120: =K120-L120 -> 29.9664 | P120: =VLOOKUP(B120,物料分类!B:F,5,0) -> 成本-酒水类
A121: 96 | B121: 1500960 | C121: 卷袋（12MM*20MM， 4卷/箱） | D121: 30 | E121: 12 | F121: 卷 | G121: Z08 | H121: 卷 | I121: =D121-E121 -> 18 | J121: =VLOOKUP(B121,本月系统单价mb5b!$B:$P,15,0) -> 9.5086667 | K121: =I121*J121 -> 171.156 | L121: =IFERROR(VLOOKUP(B121,上月数量需更新!A:C,3,0),0) -> 247.66 | M121: =K121-L121 -> -76.504 | P121: =VLOOKUP(B121,物料分类!B:F,5,0) -> 物料消耗
A122: 121 | B122: 1501160 | C122: 四季豆（LB） | D122: 0 | E122: 0 | F122: 磅 | G122: CL5 | H122: 美 | I122: =D122-E122 -> 0 | J122: =VLOOKUP(B122,本月系统单价mb5b!$B:$P,15,0) -> #DIV/0! | K122: =I122*J122 -> #DIV/0! | L122: =IFERROR(VLOOKUP(B122,上月数量需更新!A:C,3,0),0) -> 52.8 | M122: =K122-L122 -> #DIV/0! | P122: =VLOOKUP(B122,物料分类!B:F,5,0) -> 员工餐
A123: 122 | B123: 1500842 | C123: 四川辣椒面（1LB/包） | D123: 28 | E123: 17 | F123: 磅 | G123: CL5 | H123: 美 | I123: =D123-E123 -> 11 | J123: =VLOOKUP(B123,本月系统单价mb5b!$B:$P,15,0) -> 5.5235714 | K123: =I123*J123 -> 60.759286 | L123: =IFERROR(VLOOKUP(B123,上月数量需更新!A:C,3,0),0) -> 114.45 | M123: =K123-L123 -> -53.690714 | P123: =VLOOKUP(B123,物料分类!B:F,5,0) -> 成本-小料台类
A124: 123 | B124: 4517273 | C124: 圆糯米（4LB*6包/箱） | D124: 16 | E124: 12 | F124: 磅 | G124: CL5 | H124: 美 | I124: =D124-E124 -> 4 | J124: =VLOOKUP(B124,本月系统单价mb5b!$B:$P,15,0) -> 0.916875 | K124: =I124*J124 -> 3.6675 | L124: =IFERROR(VLOOKUP(B124,上月数量需更新!A:C,3,0),0) -> 29.33 | M124: =K124-L124 -> -25.6625 | P124: =VLOOKUP(B124,物料分类!B:F,5,0) -> 成本-小料台类
A125: 124 | B125: 4502382 | C125: 土豆（50LB/箱） | D125: 630 | E125: 50 | F125: 磅 | G125: CL5 | H125: 美 | I125: =D125-E125 -> 580 | J125: =VLOOKUP(B125,本月系统单价mb5b!$B:$P,15,0) -> 0.4498254 | K125: =I125*J125 -> 260.89873 | L125: =IFERROR(VLOOKUP(B125,上月数量需更新!A:C,3,0),0) -> 190.3 | M125: =K125-L125 -> 70.59873 | P125: =VLOOKUP(B125,物料分类!B:F,5,0) -> 成本-素菜类
A126: 125 | B126: 4518904 | C126: 圣女果（20LB/箱） | D126: 340 | E126: 0 | F126: 磅 | G126: CL5 | H126: 美 | I126: =D126-E126 -> 340 | J126: =VLOOKUP(B126,本月系统单价mb5b!$B:$P,15,0) -> 1.8392059 | K126: =I126*J126 -> 625.33 | L126: =IFERROR(VLOOKUP(B126,上月数量需更新!A:C,3,0),0) -> 370.67 | M126: =K126-L126 -> 254.66 | P126: =VLOOKUP(B126,物料分类!B:F,5,0) -> 成本-小料台类
A127: 126 | B127: 1500821 | C127: 地瓜淀粉（灵鹿 400G*40包/箱） | D127: 64 | E127: 30 | F127: 包 | G127: Z07 | H127: 包 | I127: =D127-E127 -> 34 | J127: =VLOOKUP(B127,本月系统单价mb5b!$B:$P,15,0) -> 1.625 | K127: =I127*J127 -> 55.25 | L127: =IFERROR(VLOOKUP(B127,上月数量需更新!A:C,3,0),0) -> 351 | M127: =K127-L127 -> -295.75 | P127: =VLOOKUP(B127,物料分类!B:F,5,0) -> 成本-小吃类
A128: 127 | B128: 1501013 | C128: 墨鱼仔（20-40，400G*20包/箱） | D128: 93.2 | E128: 12 | F128: 公斤 | G128: KG | H128: 公斤 | I128: =D128-E128 -> 81.2 | J128: =VLOOKUP(B128,本月系统单价mb5b!$B:$P,15,0) -> 11.25 | K128: =I128*J128 -> 913.5 | L128: =IFERROR(VLOOKUP(B128,上月数量需更新!A:C,3,0),0) -> 733.5 | M128: =K128-L128 -> 180 | P128: =VLOOKUP(B128,物料分类!B:F,5,0) -> 成本-荤菜类
A129: 128 | B129: 4519171 | C129: 墨鱼仔（340G*20包/箱） | D129: 13.6 | E129: 0 | F129: 公斤 | G129: KG | H129: 公斤 | I129: =D129-E129 -> 13.6 | J129: =VLOOKUP(B129,本月系统单价mb5b!$B:$P,15,0) -> 12.5 | K129: =I129*J129 -> 170 | L129: =IFERROR(VLOOKUP(B129,上月数量需更新!A:C,3,0),0) -> 0 | M129: =K129-L129 -> 170 | P129: =VLOOKUP(B129,物料分类!B:F,5,0) -> 成本-荤菜类
A130: 129 | B130: 1500701 | C130: 墨鱼筒（LB,U1-U2， 10KG/箱 ） | D130: 0 | E130: 0 | F130: 磅 | G130: CL5 | H130: 美 | I130: =D130-E130 -> 0 | J130: =VLOOKUP(B130,本月系统单价mb5b!$B:$P,15,0) -> #DIV/0! | K130: =I130*J130 -> #DIV/0! | L130: =IFERROR(VLOOKUP(B130,上月数量需更新!A:C,3,0),0) -> 0 | M130: =K130-L130 -> #DIV/0! | P130: =VLOOKUP(B130,物料分类!B:F,5,0) -> 成本-荤菜类
A131: 130 | B131: 8012407 | C131: 夏季担当女工服（2XL码，黑色） | D131: 5 | E131: 5 | F131: 件 | G131: Z18 | H131: 件 | I131: =D131-E131 -> 0 | J131: =VLOOKUP(B131,本月系统单价mb5b!$B:$P,15,0) -> 11.482 | K131: =I131*J131 -> 0 | L131: =IFERROR(VLOOKUP(B131,上月数量需更新!A:C,3,0),0) -> 0 | M131: =K131-L131 -> 0 | P131: =VLOOKUP(B131,物料分类!B:F,5,0) -> 服装费
... A235: 234 | B235: 1501710 | C235: 桂花糖（食全食美，320G*24瓶/箱） | D235: 7.2 | E235: 5.44 | F235: 公斤 | G235: KG | H235: 公斤 | I235: =D235-E235 -> 1.76 | J235: =VLOOKUP(B235,本月系统单价mb5b!$B:$P,15,0) -> 10.156944 | K235: =I235*J235 -> 17.876222 | L235: =IFERROR(VLOOKUP(B235,上月数量需更新!A:C,3,0),0) -> 0.81 | M235: =K235-L235 -> 17.066222 | P235: =VLOOKUP(B235,物料分类!B:F,5,0) -> 成本-小吃类
A236: 235 | B236: 4523956 | C236: 桂花蚌（LB） | D236: 120 | E236: 24 | F236: 磅 | G236: CL5 | H236: 美 | I236: =D236-E236 -> 96 | J236: =VLOOKUP(B236,本月系统单价mb5b!$B:$P,15,0) -> 35 | K236: =I236*J236 -> 3360 | L236: =IFERROR(VLOOKUP(B236,上月数量需更新!A:C,3,0),0) -> 3360 | M236: =K236-L236 -> 0 | N236: =VLOOKUP(B236,计算!R:X,7,0) -> 多使用22磅 | O236: 盤點无誤 | P236: =VLOOKUP(B236,物料分类!B:F,5,0) -> 成本-荤菜类
A237: 236 | B237: 1500682 | C237: 梅花猪肉（LB） | D237: 89.19 | E237: 4.5 | F237: 磅 | G237: CL5 | H237: 美 | I237: =D237-E237 -> 84.69 | J237: =VLOOKUP(B237,本月系统单价mb5b!$B:$P,15,0) -> 3.0258998 | K237: =I237*J237 -> 256.26345 | L237: =IFERROR(VLOOKUP(B237,上月数量需更新!A:C,3,0),0) -> 276.94 | M237: =K237-L237 -> -20.676549 | P237: =VLOOKUP(B237,物料分类!B:F,5,0) -> 成本-荤菜类
A238: 237 | B238: 4530906 | C238: 椰膏（400ML*24罐/箱） | D238: 96 | E238: 82 | F238: 罐 | G238: CL9 | H238: 罐 | I238: =D238-E238 -> 14 | J238: =VLOOKUP(B238,本月系统单价mb5b!$B:$P,15,0) -> 1.5 | K238: =I238*J238 -> 21 | L238: =IFERROR(VLOOKUP(B238,上月数量需更新!A:C,3,0),0) -> 0 | M238: =K238-L238 -> 21 | P238: =VLOOKUP(B238,物料分类!B:F,5,0) -> 成本-酒水类
A239: 238 | B239: 4529103 | C239: 榛果巧克力醬（3KG/罐） | D239: 24 | E239: 6 | F239: 公斤 | G239: KG | H239: 公斤 | I239: =D239-E239 -> 18 | J239: =VLOOKUP(B239,本月系统单价mb5b!$B:$P,15,0) -> 11.33 | K239: =I239*J239 -> 203.94 | L239: =IFERROR(VLOOKUP(B239,上月数量需更新!A:C,3,0),0) -> 118.96 | M239: =K239-L239 -> 84.98 | P239: =VLOOKUP(B239,物料分类!B:F,5,0) -> 成本-酒水类
A240: 239 | B240: 4723811 | C240: 榨菜（乌江，80G*100袋/件） | D240: 38 | E240: 8 | F240: 公斤 | G240: KG | H240: 公斤 | I240: =D240-E240 -> 30 | J240: =VLOOKUP(B240,本月系统单价mb5b!$B:$P,15,0) -> 5.7236842 | K240: =I240*J240 -> 171.71053 | L240: =IFERROR(VLOOKUP(B240,上月数量需更新!A:C,3,0),0) -> 174 | M240: =K240-L240 -> -2.2894737 | P240: =VLOOKUP(B240,物料分类!B:F,5,0) -> 成本-小料台类
A241: 240 | B241: 1500710 | C241: 榴莲球（1KG*10包/箱） | D241: 30 | E241: 9 | F241: 公斤 | G241: KG | H241: 公斤 | I241: =D241-E241 -> 21 | J241: =VLOOKUP(B241,本月系统单价mb5b!$B:$P,15,0) -> 15.076333 | K241: =I241*J241 -> 316.603 | L241: =IFERROR(VLOOKUP(B241,上月数量需更新!A:C,3,0),0) -> 289.34 | M241: =K241-L241 -> 27.263 | P241: =VLOOKUP(B241,物料分类!B:F,5,0) -> 成本-小吃类
A242: 241 | B242: 1500776 | C242: 橙子（40LB/箱） | D242: 4701.8 | E242: 120 | F242: 磅 | G242: CL5 | H242: 美 | I242: =D242-E242 -> 4581.8 | J242: =VLOOKUP(B242,本月系统单价mb5b!$B:$P,15,0) -> 1.2709473 | K242: =I242*J242 -> 5823.2263 | L242: =IFERROR(VLOOKUP(B242,上月数量需更新!A:C,3,0),0) -> 2591.64 | M242: =K242-L242 -> 3231.5863 | P242: =VLOOKUP(B242,物料分类!B:F,5,0) -> 成本-小料台类
A243: 242 | B243: 4526757 | C243: 橙汁（960ML*12瓶/箱） | D243: 13 | E243: 9 | F243: 瓶 | G243: BOT | H243: 瓶 | I243: =D243-E243 -> 4 | J243: =VLOOKUP(B243,本月系统单价mb5b!$B:$P,15,0) -> 3.6507692 | K243: =I243*J243 -> 14.603077 | L243: =IFERROR(VLOOKUP(B243,上月数量需更新!A:C,3,0),0) -> 9.7 | M243: =K243-L243 -> 4.9030769 | P243: =VLOOKUP(B243,物料分类!B:F,5,0) -> 成本-酒水类
A244: 243 | B244: 4019089 | C244: 正宗椰树牌椰汁（245ML*24盒/件） | D244: 163 | E244: 69 | F244: 盒 | G244: Z06 | H244: 盒 | I244: =D244-E244 -> 94 | J244: =VLOOKUP(B244,本月系统单价mb5b!$B:$P,15,0) -> 1.0207975 | K244: =I244*J244 -> 95.954969 | L244: =IFERROR(VLOOKUP(B244,上月数量需更新!A:C,3,0),0) -> 102.07 | M244: =K244-L244 -> -6.1150307 | P244: =VLOOKUP(B244,物料分类!B:F,5,0) -> 成本-酒水类
A245: 244 | B245: 4522462 | C245: 毛肚（7KG/箱） | D245: 90.19 | E245: 0 | F245: 公斤 | G245: KG | H245: 公斤 | I245: =D245-E245 -> 90.19 | J245: =VLOOKUP(B245,本月系统单价mb5b!$B:$P,15,0) -> 12.306575 | K245: =I245*J245 -> 1109.93 | L245: =IFERROR(VLOOKUP(B245,上月数量需更新!A:C,3,0),0) -> 2383.31 | M245: =K245-L245 -> -1273.38 | P245: =VLOOKUP(B245,物料分类!B:F,5,0) -> 成本-荤菜类
A246: 245 | B246: 1500684 | C246: 毛肚（LB） | D246: 185.16 | E246: 0 | F246: 磅 | G246: CL5 | H246: 美 | I246: =D246-E246 -> 185.16 | J246: =VLOOKUP(B246,本月系统单价mb5b!$B:$P,15,0) -> 6.8000108 | K246: =I246*J246 -> 1259.09 | L246: =IFERROR(VLOOKUP(B246,上月数量需更新!A:C,3,0),0) -> 1049.24 | M246: =K246-L246 -> 209.85 | P246: =VLOOKUP(B246,物料分类!B:F,5,0) -> 成本-荤菜类
A247: 246 | B247: 1500728 | C247: 毛豆荚（六福，454G*20包/件） | D247: 300 | E247: 0 | F247: 包 | G247: Z07 | H247: 包 | I247: =D247-E247 -> 300 | J247: =VLOOKUP(B247,本月系统单价mb5b!$B:$P,15,0) -> 1.3 | K247: =I247*J247 -> 390 | L247: =IFERROR(VLOOKUP(B247,上月数量需更新!A:C,3,0),0) -> 78 | M247: =K247-L247 -> 312 | P247: =VLOOKUP(B247,物料分类!B:F,5,0) -> 成本-小料台类
A248: 247 | B248: 4512865 | C248: 水磨小圆子（安井，250G*28包/箱） | D248: 17.75 | E248: 5.5 | F248: 公斤 | G248: KG | H248: 公斤 | I248: =D248-E248 -> 12.25 | J248: =VLOOKUP(B248,本月系统单价mb5b!$B:$P,15,0) -> 6 | K248: =I248*J248 -> 73.5 | L248: =IFERROR(VLOOKUP(B248,上月数量需更新!A:C,3,0),0) -> 43.5 | M248: =K248-L248 -> 30 | P248: =VLOOKUP(B248,物料分类!B:F,5,0) -> 成本-小吃类
A249: 248 | B249: 1500740 | C249: 汕尾叶（鲜， 10支/把） | D249: 4 | E249: 0 | F249: 把 | G249: Z24 | H249: 把 | I249: =D249-E249 -> 4 | J249: =VLOOKUP(B249,本月系统单价mb5b!$B:$P,15,0) -> 15 | K249: =I249*J249 -> 60 | L249: =IFERROR(VLOOKUP(B249,上月数量需更新!A:C,3,0),0) -> 45 | M249: =K249-L249 -> 15 | P249: =VLOOKUP(B249,物料分类!B:F,5,0) -> 成本-荤菜类
A250: 249 | B250: 4503951 | C250: 江小白 40 度（50ML*36瓶/箱） | D250: 107 | E250: 64 | F250: 瓶 | G250: BOT | H250: 瓶 | I250: =D250-E250 -> 43 | J250: =VLOOKUP(B250,本月系统单价mb5b!$B:$P,15,0) -> 3.62 | K250: =I250*J250 -> 155.66 | L250: =IFERROR(VLOOKUP(B250,上月数量需更新!A:C,3,0),0) -> 25.34 | M250: =K250-L250 -> 130.32 | N250: =VLOOKUP(B250,计算!R:X,7,0) -> 多使用29瓶 | O250: 樓下少盤了一箱 | P250: =VLOOKUP(B250,物料分类!B:F,5,0) -> 成本-酒水类
A251: 250 | B251: 4519224 | C251: 沙姜（LB） | D251: 4 | E251: 1 | F251: 磅 | G251: CL5 | H251: 美 | I251: =D251-E251 -> 3 | J251: =VLOOKUP(B251,本月系统单价mb5b!$B:$P,15,0) -> 8.5 | K251: =I251*J251 -> 25.5 | L251: =IFERROR(VLOOKUP(B251,上月数量需更新!A:C,3,0),0) -> 34 | M251: =K251-L251 -> -8.5 | P251: =VLOOKUP(B251,物料分类!B:F,5,0) -> 成本-锅底类
A252: 251 | B252: 1500797 | C252: 沙律酱（4L/桶） | D252: 11 | E252: 6 | F252: 桶 | G252: Z36 | H252: 桶 | I252: =D252-E252 -> 5 | J252: =VLOOKUP(B252,本月系统单价mb5b!$B:$P,15,0) -> 21.076364 | K252: =I252*J252 -> 105.38182 | L252: =IFERROR(VLOOKUP(B252,上月数量需更新!A:C,3,0),0) -> 197.69 | M252: =K252-L252 -> -92.308182 | P252: =VLOOKUP(B252,物料分类!B:F,5,0) -> 成本-小料台类
A253: 252 | B253: 1000132 | C253: 沙茶酱（牛头，3KG*6瓶/件） | D253: 144 | E253: 27 | F253: 公斤 | G253: KG | H253: 公斤 | I253: =D253-E253 -> 117 | J253: =VLOOKUP(B253,本月系统单价mb5b!$B:$P,15,0) -> 8.5 | K253: =I253*J253 -> 994.5 | L253: =IFERROR(VLOOKUP(B253,上月数量需更新!A:C,3,0),0) -> 994.5 | M253: =K253-L253 -> 0 | P253: =VLOOKUP(B253,物料分类!B:F,5,0) -> 成本-小料台类
A254: 253 | B254: 1501285 | C254: 泉字酱油（5加仑/桶） | D254: 2 | E254: 0.8 | F254: 桶 | G254: Z36 | H254: 桶 | I254: =D254-E254 -> 1.2 | J254: =VLOOKUP(B254,本月系统单价mb5b!$B:$P,15,0) -> 45.5 | K254: =I254*J254 -> 54.6 | L254: =IFERROR(VLOOKUP(B254,上月数量需更新!A:C,3,0),0) -> 63.7 | M254: =K254-L254 -> -9.1 | P254: =VLOOKUP(B254,物料分类!B:F,5,0) -> 成本-小料台类
A255: 254 | B255: 4727592 | C255: 泡小米辣（泡坛，2KG*6包/件） | D255: 24 | E255: 10 | F255: 公斤 | G255: KG | H255: 公斤 | I255: =D255-E255 -> 14 | J255: =VLOOKUP(B255,本月系统单价mb5b!$B:$P,15,0) -> 2.4166667 | K255: =I255*J255 -> 33.833333 | L255: =IFERROR(VLOOKUP(B255,上月数量需更新!A:C,3,0),0) -> 87 | M255: =K255-L255 -> -53.166667 | P255: =VLOOKUP(B255,物料分类!B:F,5,0) -> 成本-小料台类
A256: 255 | B256: 4523800 | C256: 泡椒笋丝（1KG*10包/箱） | D256: 70 | E256: 70 | F256: 公斤 | G256: KG | H256: 公斤 | I256: =D256-E256 -> 0 | J256: =VLOOKUP(B256,本月系统单价mb5b!$B:$P,15,0) -> 4.5184286 | K256: =I256*J256 -> 0 | L256: =IFERROR(VLOOKUP(B256,上月数量需更新!A:C,3,0),0) -> 135.55 | M256: =K256-L256 -> -135.55 | P256: =VLOOKUP(B256,物料分类!B:F,5,0) -> 成本-小料台类
A257: 256 | B257: 4024474 | C257: 泡椒鱼皮（龙威，1KG*10包/件） | D257: 140 | E257: 40 | F257: 公斤 | G257: KG | H257: 公斤 | I257: =D257-E257 -> 100 | J257: =VLOOKUP(B257,本月系统单价mb5b!$B:$P,15,0) -> 4.7713571 | K257: =I257*J257 -> 477.13571 | L257: =IFERROR(VLOOKUP(B257,上月数量需更新!A:C,3,0),0) -> 1240.54 | M257: =K257-L257 -> -763.40429 | P257: =VLOOKUP(B257,物料分类!B:F,5,0) -> 成本-小料台类
A258: 257 | B258: 4511130 | C258: 泰国椰奶（查哥，400ML*24盒/件） | D258: 214 | E258: 48 | F258: 盒 | G258: Z06 | H258: 盒 | I258: =D258-E258 -> 166 | J258: =VLOOKUP(B258,本月系统单价mb5b!$B:$P,15,0) -> 1.9145794 | K258: =I258*J258 -> 317.82019 | L258: =IFERROR(VLOOKUP(B258,上月数量需更新!A:C,3,0),0) -> 0 | M258: =K258-L258 -> 317.82019 | P258: =VLOOKUP(B258,物料分类!B:F,5,0) -> 成本-锅底类
A259: 258 | B259: 4513626 | C259: 泰式甜辣酱（4.5L*3瓶/箱） | D259: 11 | E259: 3 | F259: 瓶 | G259: BOT | H259: 瓶 | I259: =D259-E259 -> 8 | J259: =VLOOKUP(B259,本月系统单价mb5b!$B:$P,15,0) -> 17.439091 | K259: =I259*J259 -> 139.51273 | L259: =IFERROR(VLOOKUP(B259,上月数量需更新!A:C,3,0),0) -> 51.5 | M259: =K259-L259 -> 88.012727 | P259: =VLOOKUP(B259,物料分类!B:F,5,0) -> 成本-小吃类
A260: 325 | B260: 4517994 | C260: 玻璃带把扎啤杯（600ML，24个/件） | D260: 24 | E260: 0 | F260: 个 | G260: Z05 | H260: 个 | I260: =D260-E260 -> 24 | J260: =VLOOKUP(B260,本月系统单价mb5b!$B:$P,15,0) -> 1.71375 | K260: =I260*J260 -> 41.13 | L260: =IFERROR(VLOOKUP(B260,上月数量需更新!A:C,3,0),0) -> 0 | M260: =K260-L260 -> 41.13 | P260: =VLOOKUP(B260,物料分类!B:F,5,0) -> 物料消耗
A261: 261 | B261: 1500924 | C261: 洗杯快干剂（4L*4桶/箱） | D261: 3 | E261: 2 | F261: 桶 | G261: Z36 | H261: 桶 | I261: =D261-E261 -> 1 | J261: =VLOOKUP(B261,本月系统单价mb5b!$B:$P,15,0) -> 28.323333 | K261: =I261*J261 -> 28.323333 | L261: =IFERROR(VLOOKUP(B261,上月数量需更新!A:C,3,0),0) -> 28.33 | M261: =K261-L261 -> -0.0066666667 | P261: =VLOOKUP(B261,物料分类!B:F,5,0) -> 物料消耗
A262: 369 | B262: 8010071 | C262: 红酒醒酒器（新款1.8L，带金属过滤头） | D262: 8 | E262: 6 | F262: 个 | G262: Z05 | H262: 个 | I262: =D262-E262 -> 2 | J262: =VLOOKUP(B262,本月系统单价mb5b!$B:$P,15,0) -> 13.82 | K262: =I262*J262 -> 27.64 | L262: =IFERROR(VLOOKUP(B262,上月数量需更新!A:C,3,0),0) -> 0 | M262: =K262-L262 -> 27.64 | P262: =VLOOKUP(B262,物料分类!B:F,5,0) -> 物料消耗
... A271: 270 | B271: 4528206 | C271: 海带苗（350G*30包/箱） | D271: 10.5 | E271: 5.25 | F271: 公斤 | G271: KG | H271: 公斤 | I271: =D271-E271 -> 5.25 | J271: =VLOOKUP(B271,本月系统单价mb5b!$B:$P,15,0) -> 5.2380952 | K271: =I271*J271 -> 27.5 | L271: =IFERROR(VLOOKUP(B271,上月数量需更新!A:C,3,0),0) -> 0 | M271: =K271-L271 -> 27.5 | P271: =VLOOKUP(B271,物料分类!B:F,5,0) -> 成本-素菜类
A272: 271 | B272: 4733325 | C272: 海底捞啤酒（大麦拉格，500ML*12瓶/件） | D272: 339 | E272: 233 | F272: 瓶 | G272: BOT | H272: 瓶 | I272: =D272-E272 -> 106 | J272: =VLOOKUP(B272,本月系统单价mb5b!$B:$P,15,0) -> 2.9966667 | K272: =I272*J272 -> 317.64667 | L272: =IFERROR(VLOOKUP(B272,上月数量需更新!A:C,3,0),0) -> 284.68 | M272: =K272-L272 -> 32.966667 | N272: =VLOOKUP(B272,计算!R:X,7,0) -> 少使用1瓶 | O272: 盤點无誤 | P272: =VLOOKUP(B272,物料分类!B:F,5,0) -> 成本-酒水类
A273: 272 | B273: 4502863 | C273: 海底捞德式小麦啤酒（500ML*12瓶/件） | D273: 364 | E273: 303 | F273: 瓶 | G273: BOT | H273: 瓶 | I273: =D273-E273 -> 61 | J273: =VLOOKUP(B273,本月系统单价mb5b!$B:$P,15,0) -> 3 | K273: =I273*J273 -> 183 | L273: =IFERROR(VLOOKUP(B273,上月数量需更新!A:C,3,0),0) -> 363 | M273: =K273-L273 -> -180 | N273: =VLOOKUP(B273,计算!R:X,7,0) -> 少使用40瓶 | O273: 少算了3箱是339 | P273: =VLOOKUP(B273,物料分类!B:F,5,0) -> 成本-酒水类
A274: 273 | B274: 4520458 | C274: 海盐奶盖粉（1KG*20包/箱） | D274: 16 | E274: 11 | F274: 包 | G274: Z07 | H274: 包 | I274: =D274-E274 -> 5 | J274: =VLOOKUP(B274,本月系统单价mb5b!$B:$P,15,0) -> 11.72125 | K274: =I274*J274 -> 58.60625 | L274: =IFERROR(VLOOKUP(B274,上月数量需更新!A:C,3,0),0) -> 46.88 | M274: =K274-L274 -> 11.72625 | P274: =VLOOKUP(B274,物料分类!B:F,5,0) -> 成本-酒水类
A275: 274 | B275: 4513501 | C275: 海鲜菇（250G*50包/箱） | D275: 650 | E275: 35 | F275: 包 | G275: Z07 | H275: 包 | I275: =D275-E275 -> 615 | J275: =VLOOKUP(B275,本月系统单价mb5b!$B:$P,15,0) -> 0.52 | K275: =I275*J275 -> 319.8 | L275: =IFERROR(VLOOKUP(B275,上月数量需更新!A:C,3,0),0) -> 578.71 | M275: =K275-L275 -> -258.91 | P275: =VLOOKUP(B275,物料分类!B:F,5,0) -> 成本-素菜类
A276: 275 | B276: 1500865 | C276: 海鲜酱（李锦记，1.75L*6瓶/箱） | D276: 23 | E276: 6 | F276: 瓶 | G276: BOT | H276: 瓶 | I276: =D276-E276 -> 17 | J276: =VLOOKUP(B276,本月系统单价mb5b!$B:$P,15,0) -> 8.4330435 | K276: =I276*J276 -> 143.36174 | L276: =IFERROR(VLOOKUP(B276,上月数量需更新!A:C,3,0),0) -> 118.07 | M276: =K276-L276 -> 25.291739 | P276: =VLOOKUP(B276,物料分类!B:F,5,0) -> 成本-小料台类
A277: 186 | B277: 8013731 | C277: 拾盒垫纸（船盒，大号，50个*12包/箱） | D277: 600 | E277: 0 | F277: 个 | G277: Z05 | H277: 个 | I277: =D277-E277 -> 600 | J277: =VLOOKUP(B277,本月系统单价mb5b!$B:$P,15,0) -> 0.023333333 | K277: =I277*J277 -> 14 | L277: =IFERROR(VLOOKUP(B277,上月数量需更新!A:C,3,0),0) -> 32.68 | M277: =K277-L277 -> -18.68 | P277: =VLOOKUP(B277,物料分类!B:F,5,0) -> 物料消耗
A278: 277 | B278: 4520558 | C278: 淡奶油（946ML/盒） | D278: 46 | E278: 7 | F278: 盒 | G278: Z06 | H278: 盒 | I278: =D278-E278 -> 39 | J278: =VLOOKUP(B278,本月系统单价mb5b!$B:$P,15,0) -> 5.491087 | K278: =I278*J278 -> 214.15239 | L278: =IFERROR(VLOOKUP(B278,上月数量需更新!A:C,3,0),0) -> 225.21 | M278: =K278-L278 -> -11.057609 | P278: =VLOOKUP(B278,物料分类!B:F,5,0) -> 成本-酒水类
A279: 278 | B279: 3000759 | C279: 清油底料（300G*40包/件） | D279: 1140 | E279: 660 | F279: 公斤 | G279: KG | H279: 公斤 | I279: =D279-E279 -> 480 | J279: =VLOOKUP(B279,本月系统单价mb5b!$B:$P,15,0) -> 8.6823947 | K279: =I279*J279 -> 4167.5495 | L279: =IFERROR(VLOOKUP(B279,上月数量需更新!A:C,3,0),0) -> 5553.03 | M279: =K279-L279 -> -1385.4805 | N279: =VLOOKUP(B279,计算!R:X,7,0) -> 少使用了97kg | O279: 麻辣牛奶和麻辣燙和加辣使用 | P279: =VLOOKUP(B279,物料分类!B:F,5,0) -> 成本-锅底类
A280: 279 | B280: 3003393 | C280: 清油麻辣火锅底料（250G*30包/件）_加拿大版 | D280: 967.5 | E280: 262.5 | F280: 公斤 | G280: KG | H280: 公斤 | I280: =D280-E280 -> 705 | J280: =VLOOKUP(B280,本月系统单价mb5b!$B:$P,15,0) -> 8.4693437 | K280: =I280*J280 -> 5970.8873 | L280: =IFERROR(VLOOKUP(B280,上月数量需更新!A:C,3,0),0) -> 6288.65 | M280: =K280-L280 -> -317.76271 | P280: =VLOOKUP(B280,物料分类!B:F,5,0) -> 成本-锅底类
A281: 280 | B281: 1500736 | C281: 滑豆腐（700G*12盒/箱） | D281: 203 | E281: 16 | F281: 盒 | G281: Z06 | H281: 盒 | I281: =D281-E281 -> 187 | J281: =VLOOKUP(B281,本月系统单价mb5b!$B:$P,15,0) -> 2.2918227 | K281: =I281*J281 -> 428.57084 | L281: =IFERROR(VLOOKUP(B281,上月数量需更新!A:C,3,0),0) -> 515.99 | M281: =K281-L281 -> -87.419163 | P281: =VLOOKUP(B281,物料分类!B:F,5,0) -> 成本-素菜类
A282: 281 | B282: 4726198 | C282: 满天星 | D282: 22 | E282: 2 | F282: 把 | G282: Z24 | H282: 把 | I282: =D282-E282 -> 20 | J282: =VLOOKUP(B282,本月系统单价mb5b!$B:$P,15,0) -> 22 | K282: =I282*J282 -> 440 | L282: =IFERROR(VLOOKUP(B282,上月数量需更新!A:C,3,0),0) -> 440 | M282: =K282-L282 -> 0 | P282: =VLOOKUP(B282,物料分类!B:F,5,0) -> 成本-荤菜类
A283: 301 | B283: 8011445 | C283: 牙签（独立包装，500包*20盒/件） | D283: 2000 | E283: 0 | F283: 包 | G283: Z07 | H283: 包 | I283: =D283-E283 -> 2000 | J283: =VLOOKUP(B283,本月系统单价mb5b!$B:$P,15,0) -> 0.0057 | K283: =I283*J283 -> 11.4 | L283: =IFERROR(VLOOKUP(B283,上月数量需更新!A:C,3,0),0) -> 102.59 | M283: =K283-L283 -> -91.19 | P283: =VLOOKUP(B283,物料分类!B:F,5,0) -> 物料消耗
A284: 260 | B284: 1500938 | C284: 洗手液（4L*4桶/箱） | D284: 4 | E284: 3 | F284: 桶 | G284: Z36 | H284: 桶 | I284: =D284-E284 -> 1 | J284: =VLOOKUP(B284,本月系统单价mb5b!$B:$P,15,0) -> 8.25 | K284: =I284*J284 -> 8.25 | L284: =IFERROR(VLOOKUP(B284,上月数量需更新!A:C,3,0),0) -> 8.25 | M284: =K284-L284 -> 0 | P284: =VLOOKUP(B284,物料分类!B:F,5,0) -> 物料消耗
A285: 174 | B285: 4505395 | C285: 打包杯（3.25OZ，2500个/箱） | D285: 2300 | E285: 2000 | F285: 个 | G285: Z05 | H285: 个 | I285: =D285-E285 -> 300 | J285: =VLOOKUP(B285,本月系统单价mb5b!$B:$P,15,0) -> 0.017026087 | K285: =I285*J285 -> 5.1078261 | L285: =IFERROR(VLOOKUP(B285,上月数量需更新!A:C,3,0),0) -> 0 | M285: =K285-L285 -> 5.1078261 | P285: =VLOOKUP(B285,物料分类!B:F,5,0) -> 物料消耗
...

Sheet 上月数量需更新
B3: 值
A4: 物料 | B4: 求和项:单价1 | C4: 求和项:系统发出金额
A5: 1000049 | B5: 2.3469388 | C5: 483
A6: 1000096 | B6: 7.2468944 | C6: 46.67
A7: 1000132 | B7: 8.5 | C7: 994.5
A8: 1004576 | B8: 0.11872587 | C8: 1611.11
A9: 1500009 | B9: 3.125 | C9: 288.75
A10: 1500059 | B10: 4.1660909 | C10: 458.27
A11: 1500612 | B11: 17.5 | C11: 105
A12: 1500677 | B12: 4.6104407 | C12: 25458.07
A13: 1500678 | B13: 6.2500182 | C13: 5139.89
A14: 1500679 | B14: 6.3786553 | C14: 11192.18
A15: 1500680 | B15: 3.7884829 | C15: 2529.57
A16: 1500681 | B16: 4.2043122 | C16: 2195.66
... A156: 4726198 | B156: 22 | C156: 440
A157: (空白) | B157: #DIV/0!
A158: 1500688 | B158: 4.38 | C158: 65.7
A159: 1500713 | B159: 3.5 | C159: 133
A160: 1500721 | B160: 0.6 | C160: 396
A161: 1500728 | B161: 1.3 | C161: 78
A162: 1500741 | B162: 22.99 | C162: 275.88
A163: 1500750 | B163: 3.6471154 | C163: 37.93
A164: 1500783 | B164: 1.8 | C164: 52.2
A165: 1500784 | B165: 0.9 | C165: 22.77
A166: 1500795 | B166: 19.53 | C166: 117.18
A167: 1500831 | B167: 12.5 | C167: 75
A168: 1500837 | B168: 12.5 | C168: 12.5
A169: 1500838 | B169: 8.3288752 | C169: 242.87
... A482: 8704092 | B482: 0.21196667 | C482: 63.59
A483: 总计 | B483: 1.1857183 | C483: 345104.2

Sheet 上月数量zfi0156
A1: 开始日期 | B1: 结束日期 | C1: 工厂 | D1: 工厂描述 | E1: 物料 | F1: 物料描述 | G1: Bun | H1: 单位描述 | I1: 大类 | J1: 系统发出单价 | K1: 数量 | L1: 系统发出金额 | M1: 物料分类 | N1: 物料分类描述
A2: 45748 | B2: 45777 | C2: CA07 | D2: 加拿大七店 | E2: 1000049 | F2: 金标生抽（海天，4.9L*2桶/件） | G2: L | H2: 升 | I2: 成本类 | J2: 2.35 | K2: 205.8 | L2: 483 | M2: Z05 | N2: 成本-其他类 | O2: 1 | P2: 成本类 | Q2: 成本-小料台类
A3: 45748 | B3: 45777 | C3: CA07 | D3: 加拿大七店 | E3: 1000096 | F3: 辣椒酱（辣妹子，920G*12瓶/件） | G3: KG | H3: 公斤 | I3: 成本类 | J3: 7.25 | K3: 6.44 | L3: 46.67 | M3: Z05 | N3: 成本-其他类 | O3: 1 | P3: 成本类 | Q3: 成本-小料台类
A4: 45748 | B4: 45777 | C4: CA07 | D4: 加拿大七店 | E4: 1000103 | F4: 大块腐乳（王致和，340G*15瓶/件） | G4: KG | H4: 公斤 | I4: 成本类 | J4: 7.31 | K4: 54.06 | L4: 395.12 | M4: Z05 | N4: 成本-其他类 | O4: 1 | P4: 成本类 | Q4: 成本-小料台类
A5: 45748 | B5: 45777 | C5: CA07 | D5: 加拿大七店 | E5: 1000132 | F5: 沙茶酱（牛头，3KG*6瓶/件） | G5: KG | H5: 公斤 | I5: 成本类 | J5: 8.5 | K5: 117 | L5: 994.5 | M5: Z05 | N5: 成本-其他类 | O5: 1 | P5: 成本类 | Q5: 成本-小料台类
A6: 45748 | B6: 45777 | C6: CA07 | D6: 加拿大七店 | E6: 1001413 | F6: 卤水汁（李锦记，410ML*12瓶/件） | G6: L | H6: 升 | I6: 成本类 | J6: 14.37 | K6: 2.46 | L6: 35.34 | M6: Z05 | N6: 成本-其他类 | O6: 1 | P6: 成本类 | Q6: 成本-荤菜类
A7: 45748 | B7: 45777 | C7: CA07 | D7: 加拿大七店 | E7: 1003028 | F7: 牛油（20KG/件） | G7: KG | H7: 公斤 | I7: 成本类 | J7: 4.18 | K7: 500 | L7: 2092.49 | M7: Z02 | N7: 成本-荤菜类 | O7: 1 | P7: 成本类 | Q7: 成本-锅底类
A8: 45748 | B8: 45777 | C8: CA07 | D8: 加拿大七店 | E8: 1004576 | F8: 虎牙脆（20G*230包/件） | G8: Z07 | H8: 包 | I8: 成本类 | J8: 0.12 | K8: 13570 | L8: 1611.11 | M8: Z10 | N8: 服务费-其他类 | O8: 1 | P8: 成本类 | Q8: 成本-小料台类
A9: 45748 | B9: 45777 | C9: CA07 | D9: 加拿大七店 | E9: 1500009 | F9: 蚝油（李锦记，2.2KG*6桶/件） | G9: KG | H9: 公斤 | I9: 成本类 | J9: 3.13 | K9: 92.4 | L9: 288.75 | M9: Z02 | N9: 成本-荤菜类 | O9: 1 | P9: 成本类 | Q9: 成本-小料台类
A10: 45748 | B10: 45777 | C10: CA07 | D10: 加拿大七店 | E10: 1500059 | F10: 三鲜粉TLTF-20（10KG*2包/件） | G10: KG | H10: 公斤 | I10: 成本类 | J10: 4.17 | K10: 110 | L10: 458.27 | M10: Z05 | N10: 成本-其他类 | O10: 1 | P10: 成本类 | Q10: 成本-锅底类
A11: 45748 | B11: 45777 | C11: CA07 | D11: 加拿大七店 | E11: 1500529 | F11: 果糖（环泰，5KG*4桶/件） | G11: KG | H11: 公斤 | I11: 成本类 | J11: 2.75 | K11: 165 | L11: 453.75 | M11: Z05 | N11: 成本-其他类 | O11: 1 | P11: 成本类 | Q11: 成本-酒水类
A12: 45748 | B12: 45777 | C12: CA07 | D12: 加拿大七店 | E12: 1500612 | F12: 花椒油（川老汇，1.8L*6包/件） | G12: Z07 | H12: 包 | I12: 成本类 | J12: 17.5 | K12: 6 | L12: 105 | M12: Z05 | N12: 成本-其他类 | O12: 1 | P12: 成本类 | Q12: 成本-小料台类
A13: 45748 | B13: 45777 | C13: CA07 | D13: 加拿大七店 | E13: 1500677 | F13: 牛腩肉（LB） | G13: CL5 | H13: 磅-美 | I13: 费用类 | J13: 4.61 | K13: 130 | L13: 599.13 | M13: Z02 | N13: 成本-荤菜类 | O13: 1 | P13: 成本类 | Q13: 成本-荤菜类
... A18: 45748 | B18: 45777 | C18: CA07 | D18: 加拿大七店 | E18: 1500680 | F18: 带皮去骨鸡腿肉（LB） | G18: CL5 | H18: 磅-美 | I18: 成本类 | J18: 3.79 | K18: 513.7 | L18: 1946.28 | M18: Z02 | N18: 成本-荤菜类 | O18: 1 | P18: 成本类 | Q18: 成本-荤菜类
A19: 45748 | B19: 45777 | C19: CA07 | D19: 加拿大七店 | E19: 1500681 | F19: 去皮五花肉（LB） | G19: CL5 | H19: 磅-美 | I19: 费用类 | J19: 4.2 | K19: 54 | L19: 227.03 | M19: Z02 | N19: 成本-荤菜类 | O19: 1 | P19: 成本类 | Q19: 成本-小吃类 | S19: 240911更新
A20: 45748 | B20: 45777 | C20: CA07 | D20: 加拿大七店 | E20: 1500681 | F20: 去皮五花肉（LB） | G20: CL5 | H20: 磅-美 | I20: 成本类 | J20: 4.2 | K20: 468.24 | L20: 1968.63 | M20: Z02 | N20: 成本-荤菜类 | O20: 1 | P20: 成本类 | Q20: 成本-小吃类 | S20: 240911更新
A21: 45748 | B21: 45777 | C21: CA07 | D21: 加拿大七店 | E21: 1500682 | F21: 梅花猪肉（LB） | G21: CL5 | H21: 磅-美 | I21: 费用类 | J21: 3.02 | K21: 22 | L21: 66.36 | M21: Z02 | N21: 成本-荤菜类 | O21: 1 | P21: 成本类 | Q21: 成本-荤菜类
A22: 45748 | B22: 45777 | C22: CA07 | D22: 加拿大七店 | E22: 1500682 | F22: 梅花猪肉（LB） | G22: CL5 | H22: 磅-美 | I22: 成本类 | J22: 3.02 | K22: 69.81 | L22: 210.58 | M22: Z02 | N22: 成本-荤菜类 | O22: 1 | P22: 成本类 | Q22: 成本-荤菜类
A23: 45748 | B23: 45777 | C23: CA07 | D23: 加拿大七店 | E23: 1500684 | F23: 毛肚（LB） | G23: CL5 | H23: 磅-美 | I23: 成本类 | J23: 6.8 | K23: 154.3 | L23: 1049.24 | M23: Z02 | N23: 成本-荤菜类 | O23: 1 | P23: 成本类 | Q23: 成本-荤菜类
A24: 45748 | B24: 45777 | C24: CA07 | D24: 加拿大七店 | E24: 1500685 | F24: 牛黄喉（LB） | G24: CL5 | H24: 磅-美 | I24: 成本类 | J24: 6.99 | K24: 232.5 | L24: 1625.17 | M24: Z02 | N24: 成本-荤菜类 | O24: 1 | P24: 成本类 | Q24: 成本-荤菜类
A25: 45748 | B25: 45777 | C25: CA07 | D25: 加拿大七店 | E25: 1500686 | F25: 牛舌（LB） | G25: CL5 | H25: 磅-美 | I25: 成本类 | J25: 14.99 | K25: 437.94 | L25: 6564.73 | M25: Z02 | N25: 成本-荤菜类 | O25: 1 | P25: 成本类 | Q25: 成本-荤菜类
A26: 45748 | B26: 45777 | C26: CA07 | D26: 加拿大七店 | E26: 1500687 | F26: 猪棒骨（LB） | G26: CL5 | H26: 磅-美 | I26: 成本类 | J26: 1.08 | K26: 1585.376 | L26: 1716.99 | M26: Z02 | N26: 成本-荤菜类 | O26: 1 | P26: 成本类 | Q26: 成本-锅底类
A27: 45748 | B27: 45777 | C27: CA07 | D27: 加拿大七店 | E27: 1500688 | F27: 带皮带骨鸡腿（冻） | G27: KG | H27: 公斤 | I27: 费用类 | J27: 4.38 | K27: 15 | L27: 65.7 | M27: Z02 | N27: 成本-荤菜类 | O27: 1 | P27: 成本类 | Q27: 成本-荤菜类
A28: 45748 | B28: 45777 | C28: CA07 | D28: 加拿大七店 | E28: 1500694 | F28: 猪排骨（员工餐， LB） | G28: CL5 | H28: 磅-美 | I28: 费用类 | J28: 2.69 | K28: 123 | L28: 330.87 | M28: Z02 | N28: 成本-荤菜类 | O28: 2 | P28: 费用类 | Q28: 员工餐
A29: 45748 | B29: 45777 | C29: CA07 | D29: 加拿大七店 | E29: 1500695 | F29: 白虾仁（41-50，4LB*6包/箱 ） | G29: CL5 | H29: 磅-美 | I29: 费用类 | J29: 5.21 | K29: 120 | L29: 625 | M29: Z02 | N29: 成本-荤菜类 | O29: 2 | P29: 费用类 | Q29: 员工餐
A30: 45748 | B30: 45777 | C30: CA07 | D30: 加拿大七店 | E30: 1500700 | F30: 冷冻巴沙鱼（12-14 ，10KG/箱） | G30: KG | H30: 公斤 | I30: 费用类 | J30: 3.65 | K30: 40 | L30: 146 | M30: Z02 | N30: 成本-荤菜类 | O30: 1 | P30: 成本类 | Q30: 成本-荤菜类
A31: 45748 | B31: 45777 | C31: CA07 | D31: 加拿大七店 | E31: 1500700 | F31: 冷冻巴沙鱼（12-14 ，10KG/箱） | G31: KG | H31: 公斤 | I31: 成本类 | J31: 3.65 | K31: 313.27 | L31: 1143.44 | M31: Z02 | N31: 成本-荤菜类 | O31: 1 | P31: 成本类 | Q31: 成本-荤菜类
A32: 45748 | B32: 45777 | C32: CA07 | D32: 加拿大七店 | E32: 1500703 | F32: 带头南美白虾（30-40，4LB*6包/箱 ） | G32: CL5 | H32: 磅-美 | I32: 成本类 | J32: 4.33 | K32: 344 | L32: 1490.67 | M32: Z02 | N32: 成本-荤菜类 | O32: 1 | P32: 成本类 | Q32: 成本-荤菜类
... A138: 45748 | B138: 45777 | C138: CA07 | D138: 加拿大七店 | E138: 1500918 | F138: 牛栏山二锅头（100ML/瓶） | G138: BOT | H138: 瓶 | I138: 成本类 | J138: 4.38 | K138: 33 | L138: 144.54 | M138: Z04 | N138: 成本-酒水类 | O138: 1 | P138: 成本类 | Q138: 成本-酒水类
A139: 45748 | B139: 45777 | C139: CA07 | D139: 加拿大七店 | E139: 1500919 | F139: 洗碗液（红色， 20L/桶） | G139: Z36 | H139: 桶 | I139: 费用类 | J139: 82.12 | K139: 7 | L139: 574.84 | M139: Z11 | N139: 物料消耗-清洁类 | O139: 2 | P139: 费用类 | Q139: 物料消耗 | R139: 清洁类
A140: 45748 | B140: 45777 | C140: CA07 | D140: 加拿大七店 | E140: 1500920 | F140: 快干剂（蓝色， 20L/桶） | G140: Z36 | H140: 桶 | I140: 费用类 | J140: 127.7 | K140: 4 | L140: 510.8 | M140: Z11 | N140: 物料消耗-清洁类 | O140: 2 | P140: 费用类 | Q140: 物料消耗 | R140: 清洁类
A141: 45748 | B141: 45777 | C141: CA07 | D141: 加拿大七店 | E141: 1500923 | F141: 洗杯红药水（4L*4桶/箱） | G141: Z36 | H141: 桶 | I141: 费用类 | J141: 18.6 | K141: 1 | L141: 18.6 | M141: Z15 | N141: 物料消耗-其他类 | O141: 2 | P141: 费用类 | Q141: 物料消耗 | R141: 清洁类
A142: 45748 | B142: 45777 | C142: CA07 | D142: 加拿大七店 | E142: 1500924 | F142: 洗杯快干剂（4L*4桶/箱） | G142: Z36 | H142: 桶 | I142: 费用类 | J142: 28.33 | K142: 1 | L142: 28.33 | M142: Z11 | N142: 物料消耗-清洁类 | O142: 2 | P142: 费用类 | Q142: 物料消耗
A143: 45748 | B143: 45777 | C143: CA07 | D143: 加拿大七店 | E143: 1500925 | F143: 洗地苏打（25KG/包） | G143: KG | H143: 公斤 | I143: 费用类 | J143: 2.4 | K143: 5 | L143: 11.99 | M143: Z11 | N143: 物料消耗-清洁类 | O143: 2 | P143: 费用类 | Q143: 物料消耗 | R143: 清洁类
A144: 45748 | B144: 45777 | C144: CA07 | D144: 加拿大七店 | E144: 1500938 | F144: 洗手液（4L*4桶/箱） | G144: Z36 | H144: 桶 | I144: 费用类 | J144: 8.25 | K144: 1 | L144: 8.25 | M144: Z11 | N144: 物料消耗-清洁类 | O144: 2 | P144: 费用类 | Q144: 物料消耗 | R144: 清洁类
A145: 45748 | B145: 45777 | C145: CA07 | D145: 加拿大七店 | E145: 1500944 | F145: 咖色单张擦手纸（4000张/箱） | G145: Z34 | H145: 箱 | I145: 费用类 | J145: 33.5 | K145: 8 | L145: 268 | M145: Z13 | N145: 物料消耗-纸巾类 | O145: 2 | P145: 费用类 | Q145: 物料消耗 | R145: 纸巾类
A146: 45748 | B146: 45777 | C146: CA07 | D146: 加拿大七店 | E146: 1500957 | F146: 8.5" 8MM 纸吸管（500根*2包/箱） | G146: Z07 | H146: 包 | I146: 费用类 | J146: 10 | K146: 20 | L146: 200 | M146: Z15 | N146: 物料消耗-其他类 | O146: 2 | P146: 费用类 | Q146: 物料消耗 | R146: 餐具类
A147: 45748 | B147: 45777 | C147: CA07 | D147: 加拿大七店 | E147: 1500960 | F147: 卷袋（12MM*20MM， 4卷/箱） | G147: Z08 | H147: 卷 | I147: 费用类 | J147: 9.53 | K147: 26 | L147: 247.66 | M147: Z15 | N147: 物料消耗-其他类 | O147: 2 | P147: 费用类 | Q147: 物料消耗 | R147: 其他类
A148: 45748 | B148: 45777 | C148: CA07 | D148: 加拿大七店 | E148: 1500961 | F148: 卷袋（8.5MM*12MM， 4卷/箱） | G148: Z08 | H148: 卷 | I148: 费用类 | J148: 9.5 | K148: 14 | L148: 133 | M148: Z15 | N148: 物料消耗-其他类 | O148: 2 | P148: 费用类 | Q148: 物料消耗 | R148: 其他类
A149: 45748 | B149: 45777 | C149: CA07 | D149: 加拿大七店 | E149: 1500963 | F149: 一次性叉（1000个/箱） | G149: Z05 | H149: 个 | I149: 费用类 | J149: 0.04 | K149: 3000 | L149: 118.5 | M149: Z15 | N149: 物料消耗-其他类 | O149: 2 | P149: 费用类 | Q149: 物料消耗 | R149: 餐具类
A150: 45748 | B150: 45777 | C150: CA07 | D150: 加拿大七店 | E150: 1500979 | F150: 保鲜膜（762M*27.9CM/卷） | G150: Z08 | H150: 卷 | I150: 费用类 | J150: 18.43 | K150: 21 | L150: 386.98 | M150: Z15 | N150: 物料消耗-其他类 | O150: 2 | P150: 费用类 | Q150: 物料消耗 | R150: 餐具类
A151: 45748 | B151: 45777 | C151: CA07 | D151: 加拿大七店 | E151: 1500980 | F151: 运输费用（批） | G151: F01 | H151: 批 | I151: 成本类 | J151: 17 | K151: 12 | L151: 204 | M151: Z15 | N151: 物料消耗-其他类 | O151: 1 | P151: 成本类 | Q151: 成本-素菜类
A152: 45748 | B152: 45777 | C152: CA07 | D152: 加拿大七店 | E152: 1500982 | F152: 红彩椒（LB） | G152: CL5 | H152: 磅-美 | I152: 费用类 | J152: 2.04 | K152: 33.2 | L152: 67.89 | M152: Z05 | N152: 成本-其他类 | O152: 2 | P152: 费用类 | Q152: 员工餐
A153: 45748 | B153: 45777 | C153: CA07 | D153: 加拿大七店 | E153: 1500983 | F153: 青彩椒（LB） | G153: CL5 | H153: 磅-美 | I153: 费用类 | J153: 1.47 | K153: 33.55 | L153: 49.23 | M153: Z05 | N153: 成本-其他类 | O153: 2 | P153: 费用类 | Q153: 员工餐
A154: 45748 | B154: 45777 | C154: CA07 | D154: 加拿大七店 | E154: 1500984 | F154: 中葱（5KG/箱） | G154: KG | H154: 公斤 | I154: 成本类 | J154: 4.37 | K154: 45 | L154: 196.61 | M154: Z05 | N154: 成本-其他类 | O154: 1 | P154: 成本类 | Q154: 成本-小料台类
A155: 45748 | B155: 45777 | C155: CA07 | D155: 加拿大七店 | E155: 1500987 | F155: 藕/莲菜（44LB/箱） | G155: CL5 | H155: 磅-美 | I155: 费用类 | J155: 1.97 | K155: 20 | L155: 39.3 | M155: Z03 | N155: 成本-素菜类 | O155: 1 | P155: 成本类 | Q155: 成本-素菜类
A156: 45748 | B156: 45777 | C156: CA07 | D156: 加拿大七店 | E156: 1500987 | F156: 藕/莲菜（44LB/箱） | G156: CL5 | H156: 磅-美 | I156: 成本类 | J156: 1.95 | K156: 464 | L156: 903.7 | M156: Z03 | N156: 成本-素菜类 | O156: 1 | P156: 成本类 | Q156: 成本-素菜类
A157: 45748 | B157: 45777 | C157: CA07 | D157: 加拿大七店 | E157: 1500996 | F157: 羊腿肉（去骨，KG） | G157: KG | H157: 公斤 | I157: 成本类 | J157: 17.56 | K157: 77.035 | L157: 1353.03 | M157: Z02 | N157: 成本-荤菜类 | O157: 1 | P157: 成本类 | Q157: 成本-荤菜类
A158: 45748 | B158: 45777 | C158: CA07 | D158: 加拿大七店 | E158: 1500998 | F158: 鸡汁（410G*12瓶/箱） | G158: BOT | H158: 瓶 | I158: 成本类 | J158: 6.08 | K158: 4 | L158: 24.33 | M158: Z05 | N158: 成本-其他类 | O158: 1 | P158: 成本类 | Q158: 成本-小料台类
A159: 45748 | B159: 45777 | C159: CA07 | D159: 加拿大七店 | E159: 1501000 | F159: 一次性汤勺（1000个/箱） | G159: Z05 | H159: 个 | I159: 费用类 | J159: 0.04 | K159: 18000 | L159: 698.4 | M159: Z15 | N159: 物料消耗-其他类 | O159: 2 | P159: 费用类 | Q159: 物料消耗 | R159: 餐具类
A160: 45748 | B160: 45777 | C160: CA07 | D160: 加拿大七店 | E160: 1501001 | F160: 咖色外卖纸盒（26 OZ，450个/箱） | G160: Z05 | H160: 个 | I160: 费用类 | J160: 0.1 | K160: 2700 | L160: 258 | M160: Z15 | N160: 物料消耗-其他类 | O160: 2 | P160: 费用类 | Q160: 物料消耗 | R160: 餐具类
A161: 45748 | B161: 45777 | C161: CA07 | D161: 加拿大七店 | E161: 1501008 | F161: 蘸料盖（1.5 OZ ，2500个/箱） | G161: Z05 | H161: 个 | I161: 费用类 | J161: 0.01 | K161: 5000 | L161: 50 | M161: Z15 | N161: 物料消耗-其他类 | O161: 2 | P161: 费用类 | Q161: 物料消耗 | R161: 餐具类
A162: 45748 | B162: 45777 | C162: CA07 | D162: 加拿大七店 | E162: 1501009 | F162: 漂白剂（4L*4桶/箱） | G162: Z36 | H162: 桶 | I162: 费用类 | J162: 6.75 | K162: 12 | L162: 81 | M162: Z11 | N162: 物料消耗-清洁类 | O162: 2 | P162: 费用类 | Q162: 物料消耗 | R162: 清洁类
A163: 45748 | B163: 45777 | C163: CA07 | D163: 加拿大七店 | E163: 1501010 | F163: 洗洁精（4L*4桶/箱） | G163: Z36 | H163: 桶 | I163: 费用类 | J163: 7.5 | K163: 108 | L163: 810 | M163: Z11 | N163: 物料消耗-清洁类 | O163: 2 | P163: 费用类 | Q163: 物料消耗 | R163: 清洁类
A164: 45748 | B164: 45777 | C164: CA07 | D164: 加拿大七店 | E164: 1501013 | F164: 墨鱼仔（20-40，400G*20包/箱） | G164: KG | H164: 公斤 | I164: 成本类 | J164: 11.25 | K164: 65.2 | L164: 733.5 | M164: Z02 | N164: 成本-荤菜类 | O164: 1 | P164: 成本类 | Q164: 成本-荤菜类
A165: 45748 | B165: 45777 | C165: CA07 | D165: 加拿大七店 | E165: 1501029 | F165: 美极鲜酱油（800ML*6瓶/箱） | G165: BOT | H165: 瓶 | I165: 成本类 | J165: 8 | K165: 30 | L165: 240 | M165: Z05 | N165: 成本-其他类 | O165: 1 | P165: 成本类 | Q165: 成本-小料台类
A166: 45748 | B166: 45777 | C166: CA07 | D166: 加拿大七店 | E166: 1501032 | F166: 老抽（裕益牌，12L/桶） | G166: L | H166: 升 | I166: 成本类 | J166: 7.21 | K166: 10 | L166: 72.08 | M166: Z05 | N166: 成本-其他类 | O166: 1 | P166: 成本类 | Q166: 成本-小料台类
A167: 45748 | B167: 45777 | C167: CA07 | D167: 加拿大七店 | E167: 1501034 | F167: 烧烤盘 （A9-668-3，30个/箱） | G167: Z05 | H167: 个 | I167: 费用类 | J167: 5.38 | K167: 120 | L167: 645.72 | M167: Z12 | N167: 物料消耗-餐具类 | O167: 2 | P167: 费用类 | Q167: 物料消耗 | R167: 其他类 | S167: 2月新增
A168: 45748 | B168: 45777 | C168: CA07 | D168: 加拿大七店 | E168: 1501045 | F168: 寿司米（平和，40LB/袋） | G168: CL5 | H168: 磅-美 | I168: 成本类 | J168: 0.9 | K168: 80 | L168: 72 | M168: Z07 | N168: 服务费-小吃类 | O168: 1 | P168: 成本类 | Q168: 成本-小吃类
A169: 45748 | B169: 45777 | C169: CA07 | D169: 加拿大七店 | E169: 1501055 | F169: 鲜虾抄手（45个/包） | G169: Z05 | H169: 个 | I169: 成本类 | J169: 0.37 | K169: 2205 | L169: 808.5 | M169: Z21 | N169: 员工餐 | O169: 1 | P169: 成本类 | Q169: 成本-小吃类
A170: 45748 | B170: 45777 | C170: CA07 | D170: 加拿大七店 | E170: 1501154 | F170: 单晶冰糖（400G*48包/箱） | G170: Z07 | H170: 包 | I170: 成本类 | J170: 1.38 | K170: 144 | L170: 198.75 | M170: Z05 | N170: 成本-其他类 | O170: 1 | P170: 成本类 | Q170: 成本-小料台类
A171: 45748 | B171: 45777 | C171: CA07 | D171: 加拿大七店 | E171: 1501159 | F171: 牛板腱（LB） | G171: CL5 | H171: 磅-美 | I171: 成本类 | J171: 6.99 | K171: 836.58 | L171: 5848.18 | M171: Z02 | N171: 成本-荤菜类 | O171: 1 | P171: 成本类 | Q171: 成本-荤菜类
A172: 45748 | B172: 45777 | C172: CA07 | D172: 加拿大七店 | E172: 1501160 | F172: 四季豆（LB） | G172: CL5 | H172: 磅-美 | I172: 费用类 | J172: 3.3 | K172: 16 | L172: 52.8 | M172: Z05 | N172: 成本-其他类 | O172: 2 | P172: 费用类 | Q172: 员工餐
A173: 45748 | B173: 45777 | C173: CA07 | D173: 加拿大七店 | E173: 1501165 | F173: 消毒水（4L*4桶/箱） | G173: Z36 | H173: 桶 | I173: 费用类 | J173: 12.13 | K173: 2 | L173: 24.25 | M173: Z11 | N173: 物料消耗-清洁类 | O173: 2 | P173: 费用类 | Q173: 物料消耗
A174: 45748 | B174: 45777 | C174: CA07 | D174: 加拿大七店 | E174: 1501178 | F174: 柚子茶（1KG*12瓶/箱） | G174: KG | H174: 公斤 | I174: 成本类 | J174: 7 | K174: 112 | L174: 783.97 | M174: Z04 | N174: 成本-酒水类 | O174: 1 | P174: 成本类 | Q174: 成本-酒水类
A175: 45748 | B175: 45777 | C175: CA07 | D175: 加拿大七店 | E175: 1501190 | F175: 薯条（4.5LB*6包/箱） | G175: Z07 | H175: 包 | I175: 成本类 | J175: 8.23 | K175: 19 | L175: 156.3 | M175: Z07 | N175: 服务费-小吃类 | O175: 1 | P175: 成本类 | Q175: 成本-小吃类
A176: 45748 | B176: 45777 | C176: CA07 | D176: 加拿大七店 | E176: 1501192 | F176: 薯条蘸酱粉（403G*12包/箱） | G176: Z07 | H176: 包 | I176: 成本类 | J176: 3.24 | K176: 20 | L176: 64.87 | M176: Z05 | N176: 成本-其他类 | O176: 1 | P176: 成本类 | Q176: 成本-小吃类
A177: 45748 | B177: 45777 | C177: CA07 | D177: 加拿大七店 | E177: 1501193 | F177: BC肉蟹（LB） | G177: CL5 | H177: 磅-美 | I177: 成本类 | J177: 19.61 | K177: 3.79 | L177: 74.34 | M177: Z02 | N177: 成本-荤菜类 | O177: 1 | P177: 成本类 | Q177: 成本-荤菜类
A178: 45748 | B178: 45777 | C178: CA07 | D178: 加拿大七店 | E178: 1501253 | F178: 猪大肠 （KG） | G178: KG | H178: 公斤 | I178: 费用类 | J178: 6.94 | K178: 10 | L178: 69.39 | M178: Z02 | N178: 成本-荤菜类 | O178: 1 | P178: 成本类 | Q178: 成本-荤菜类
A179: 45748 | B179: 45777 | C179: CA07 | D179: 加拿大七店 | E179: 1501253 | F179: 猪大肠 （KG） | G179: KG | H179: 公斤 | I179: 成本类 | J179: 6.94 | K179: 59.62 | L179: 413.73 | M179: Z02 | N179: 成本-荤菜类 | O179: 1 | P179: 成本类 | Q179: 成本-荤菜类
... A212: 45748 | B212: 45777 | C212: CA07 | D212: 加拿大七店 | E212: 3010923 | F212: 草莓芝士味雪人儿糕点_美国内销_45G*120个/件 | G212: EA | H212: 个 | I212: 成本类 | J212: 1.19 | K212: 40 | L212: 47.67 | M212: Z07 | N212: 服务费-小吃类 | O212: 1 | P212: 成本类 | Q212: 成本-小吃类
A213: 45748 | B213: 45777 | C213: CA07 | D213: 加拿大七店 | E213: 4000465 | F213: 喷雾瓶（安利） | G213: Z05 | H213: 个 | I213: 费用类 | J213: 5.06 | K213: 10 | L213: 50.55 | M213: Z15 | N213: 物料消耗-其他类 | O213: 2 | P213: 费用类 | Q213: 物料消耗 | R213: 清洁类
A214: 45748 | B214: 45777 | C214: CA07 | D214: 加拿大七店 | E214: 4000635 | F214: 加多宝（310ML*24听/件） | G214: Z01 | H214: 听 | I214: 成本类 | J214: 0.79 | K214: 211 | L214: 167.04 | M214: Z04 | N214: 成本-酒水类 | O214: 1 | P214: 成本类 | Q214: 成本-酒水类
A215: 45748 | B215: 45777 | C215: CA07 | D215: 加拿大七店 | E215: 4000642 | F215: 双层抽纸（清风，130抽*96包/件） | G215: Z07 | H215: 包 | I215: 费用类 | J215: 0.36 | K215: 1536 | L215: 560.2 | M215: Z13 | N215: 物料消耗-纸巾类 | O215: 2 | P215: 费用类 | Q215: 物料消耗 | R215: 纸巾类
A216: 45748 | B216: 45777 | C216: CA07 | D216: 加拿大七店 | E216: 4001742 | F216: 喷雾瓶喷头（安利） | G216: Z05 | H216: 个 | I216: 费用类 | J216: 3.61 | K216: 10 | L216: 36.11 | M216: Z15 | N216: 物料消耗-其他类 | O216: 2 | P216: 费用类 | Q216: 物料消耗 | R216: 其他类
A217: 45748 | B217: 45777 | C217: CA07 | D217: 加拿大七店 | E217: 4001969 | F217: 芥末（43G/盒） | G217: KG | H217: 公斤 | I217: 成本类 | J217: 34.66 | K217: 0.058 | L217: 2.01 | M217: Z05 | N217: 成本-其他类 | O217: 1 | P217: 成本类 | Q217: 成本-小料台类
A218: 45748 | B218: 45777 | C218: CA07 | D218: 加拿大七店 | E218: 4003066 | F218: 青岛啤酒（330ML*24瓶/件） | G218: BOT | H218: 瓶 | I218: 成本类 | J218: 1.9 | K218: 207 | L218: 394.2 | M218: Z04 | N218: 成本-酒水类 | O218: 1 | P218: 成本类 | Q218: 成本-酒水类
A219: 45748 | B219: 45777 | C219: CA07 | D219: 加拿大七店 | E219: 4003246 | F219: 客人围裙（黑色红边，20条/捆） | G219: Z19 | H219: 条 | I219: 费用类 | J219: 2.17 | K219: 200 | L219: 433.29 | M219: Z15 | N219: 物料消耗-其他类 | O219: 2 | P219: 费用类 | Q219: 物料消耗 | R219: 其他类
A220: 45748 | B220: 45777 | C220: CA07 | D220: 加拿大七店 | E220: 4004440 | F220: 鸡粉调味料（李锦记，1KG*12桶/件） | G220: KG | H220: 公斤 | I220: 成本类 | J220: 8.97 | K220: 9 | L220: 80.7 | M220: Z05 | N220: 成本-其他类 | O220: 1 | P220: 成本类 | Q220: 成本-小料台类
A221: 45748 | B221: 45777 | C221: CA07 | D221: 加拿大七店 | E221: 4005465 | F221: 香辣酱（美乐，1KG*12瓶/件） | G221: KG | H221: 公斤 | I221: 成本类 | J221: 7.09 | K221: 60 | L221: 425.56 | M221: Z05 | N221: 成本-其他类 | O221: 1 | P221: 成本类 | Q221: 成本-小料台类
A222: 45748 | B222: 45777 | C222: CA07 | D222: 加拿大七店 | E222: 4006187 | F222: 无粉丁腈手套（蓝色，L，100只*10盒/件） | G222: Z21 | H222: 只 | I222: 费用类 | J222: 0.03 | K222: 4000 | L222: 117.74 | M222: Z20 | N222: 劳动保护费 | O222: 2 | P222: 费用类 | Q222: 物料消耗
A223: 45748 | B223: 45777 | C223: CA07 | D223: 加拿大七店 | E223: 4006188 | F223: 无粉丁腈手套（蓝色，M，100只*10盒/件） | G223: Z21 | H223: 只 | I223: 费用类 | J223: 0.03 | K223: 5000 | L223: 150.67 | M223: Z20 | N223: 劳动保护费 | O223: 2 | P223: 费用类 | Q223: 服装费
A224: 45748 | B224: 45777 | C224: CA07 | D224: 加拿大七店 | E224: 4006189 | F224: 无粉丁腈手套（蓝色，S，100只*10盒/件） | G224: Z21 | H224: 只 | I224: 费用类 | J224: 0.03 | K224: 4000 | L224: 122 | M224: Z20 | N224: 劳动保护费 | O224: 2 | P224: 费用类 | Q224: 服装费
A225: 45748 | B225: 45777 | C225: CA07 | D225: 加拿大七店 | E225: 4017075 | F225: 冰粉粉（康雅酷，40G*100包/件） | G225: Z07 | H225: 包 | I225: 成本类 | J225: 0.38 | K225: 900 | L225: 342.48 | M225: Z07 | N225: 服务费-小吃类 | O225: 1 | P225: 成本类 | Q225: 成本-小料台类
A226: 45748 | B226: 45777 | C226: CA07 | D226: 加拿大七店 | E226: 4017892 | F226: 捞面面节（三全，2.5KG*4包/件） | G226: KG | H226: 公斤 | I226: 成本类 | J226: 2.4 | K226: 40 | L226: 96 | M226: Z07 | N226: 服务费-小吃类 | O226: 1 | P226: 成本类 | Q226: 成本-小吃类
A227: 45748 | B227: 45777 | C227: CA07 | D227: 加拿大七店 | E227: 4018767 | F227: 纯芝麻酱（富味乡，2KG*10袋/件） | G227: KG | H227: 公斤 | I227: 成本类 | J227: 4.5 | K227: 140 | L227: 629.68 | M227: Z05 | N227: 成本-其他类 | O227: 1 | P227: 成本类 | Q227: 成本-小料台类
A228: 45748 | B228: 45777 | C228: CA07 | D228: 加拿大七店 | E228: 4018965 | F228: 黑鱼片（1KG*10包/箱） | G228: KG | H228: 公斤 | I228: 成本类 | J228: 10.5 | K228: 94 | L228: 986.97 | M228: Z02 | N228: 成本-荤菜类 | O228: 1 | P228: 成本类 | Q228: 成本-荤菜类
A229: 45748 | B229: 45777 | C229: CA07 | D229: 加拿大七店 | E229: 4019089 | F229: 正宗椰树牌椰汁（245ML*24盒/件） | G229: Z06 | H229: 盒 | I229: 成本类 | J229: 1.02 | K229: 100 | L229: 102.07 | M229: Z04 | N229: 成本-酒水类 | O229: 1 | P229: 成本类 | Q229: 成本-酒水类
A230: 45748 | B230: 45777 | C230: CA07 | D230: 加拿大七店 | E230: 4019343 | F230: 奶酪鱼条（500G*20盒/件 ） | G230: KG | H230: 公斤 | I230: 成本类 | J230: 8.33 | K230: 70 | L230: 583.41 | M230: Z02 | N230: 成本-荤菜类 | O230: 1 | P230: 成本类 | Q230: 成本-小吃类
A231: 45748 | B231: 45777 | C231: CA07 | D231: 加拿大七店 | E231: 4020091 | F231: 速冻虾滑（越南，DL443厂，1.6KG*6包/件） | G231: KG | H231: 公斤 | I231: 成本类 | J231: 17.11 | K231: 393.6 | L231: 6734.53 | M231: Z02 | N231: 成本-荤菜类 | O231: 1 | P231: 成本类 | Q231: 成本-荤菜类
A232: 45748 | B232: 45777 | C232: CA07 | D232: 加拿大七店 | E232: 4020719 | F232: 速冻黄金熔岩虾球（越南DL443，250G*20包/件） | G232: KG | H232: 公斤 | I232: 成本类 | J232: 15.23 | K232: 40 | L232: 609.12 | M232: Z07 | N232: 服务费-小吃类 | O232: 1 | P232: 成本类 | Q232: 成本-小吃类
A233: 45748 | B233: 45777 | C233: CA07 | D233: 加拿大七店 | E233: 4021486 | F233: 一次性纸杯（海底捞门店专用，50个*20提/件） | G233: Z05 | H233: 个 | I233: 费用类 | J233: 0.03 | K233: 2000 | L233: 53.21 | M233: Z12 | N233: 物料消耗-餐具类 | O233: 2 | P233: 费用类 | Q233: 物料消耗 | R233: 餐具类
A234: 45748 | B234: 45777 | C234: CA07 | D234: 加拿大七店 | E234: 4021537 | F234: 达尔文百洁布（9*8CM，10卷/箱） | G234: Z08 | H234: 卷 | I234: 费用类 | J234: 12.02 | K234: 8 | L234: 96.14 | M234: Z11 | N234: 物料消耗-清洁类 | O234: 2 | P234: 费用类 | Q234: 物料消耗
A235: 45748 | B235: 45777 | C235: CA07 | D235: 加拿大七店 | E235: 4023572 | F235: 双层卷纸（12卷/箱） | G235: Z08 | H235: 卷 | I235: 费用类 | J235: 0.46 | K235: 551 | L235: 252.88 | M235: Z11 | N235: 物料消耗-清洁类 | O235: 2 | P235: 费用类 | Q235: 物料消耗
A236: 45748 | B236: 45777 | C236: CA07 | D236: 加拿大七店 | E236: 4024119 | F236: 升级版调料勺 | G236: Z05 | H236: 个 | I236: 费用类 | J236: 1.72 | K236: 20 | L236: 34.45 | M236: Z15 | N236: 物料消耗-其他类 | O236: 2 | P236: 费用类 | Q236: 物料消耗 | R236: 餐具类
A237: 45748 | B237: 45777 | C237: CA07 | D237: 加拿大七店 | E237: 4024474 | F237: 泡椒鱼皮（龙威，1KG*10包/件） | G237: KG | H237: 公斤 | I237: 成本类 | J237: 4.77 | K237: 260 | L237: 1240.54 | M237: Z09 | N237: 服务费-凉菜类 | O237: 1 | P237: 成本类 | Q237: 成本-小料台类
A238: 45748 | B238: 45777 | C238: CA07 | D238: 加拿大七店 | E238: 4026797 | F238: 冻油豆皮（龙伟，1KG*10包/件） | G238: KG | H238: 公斤 | I238: 成本类 | J238: 6.5 | K238: 66.5 | L238: 432.5 | M238: Z03 | N238: 成本-素菜类 | O238: 1 | P238: 成本类 | Q238: 成本-素菜类
A239: 45748 | B239: 45777 | C239: CA07 | D239: 加拿大七店 | E239: 4028096 | F239: 圆形透亮钢化杯（48只/件） | G239: Z21 | H239: 只 | I239: 费用类 | J239: 0.7 | K239: 192 | L239: 134.28 | M239: Z15 | N239: 物料消耗-其他类 | O239: 2 | P239: 费用类 | Q239: 物料消耗 | R239: 餐具类 | S239: 6月新增
A240: 45748 | B240: 45777 | C240: CA07 | D240: 加拿大七店 | E240: 4028302 | F240: 烤花生仁切碎（中粮，2.5KG*4包/件） | G240: KG | H240: 公斤 | I240: 成本类 | J240: 6.73 | K240: 100 | L240: 672.73 | M240: Z05 | N240: 成本-其他类 | O240: 1 | P240: 成本类 | Q240: 成本-小料台类
A241: 45748 | B241: 45777 | C241: CA07 | D241: 加拿大七店 | E241: 4028719 | F241: 醇然心动混合薄荷糖（海亿，2.28KG*4包/件） | G241: KG | H241: 公斤 | I241: 成本类 | J241: 4.27 | K241: 136.8 | L241: 583.95 | M241: Z10 | N241: 服务费-其他类 | O241: 1 | P241: 成本类 | Q241: 成本-小料台类
...

Sheet 本月系统单价mb5b
A1: ValA | B1: 物料 | C1: 开始日期 | D1: 结束日期 | E1: 期初库存 | F1: 总收货数量 | G1: 总发货数量 | H1: 期末库存 | I1: 计 | J1: 期初金额 | K1: 总收货金额 | L1: 总发货金额 | M1: 期末金额 | N1: 货币 | O1: 物料描述 | P1: 单价
A2: CA07 | B2: 1000049 | C2: 2025.05.01 | D2: 2025.05.31 | E2: 49 | F2: 215.6 | G2: 0 | H2: 264.6 | I2: L | J2: 115 | K2: 506 | L2: 0 | M2: 621 | N2: CAD | O2: 金标生抽（海天，4.9L*2桶/件） | P2: =M2/H2 -> 2.3469388
A3: CA07 | B3: 1000096 | C3: 2025.05.01 | D3: 2025.05.31 | E3: 12.88 | F3: 0 | G3: 0 | H3: 12.88 | I3: KG | J3: 93.33 | K3: 0 | L3: 0 | M3: 93.33 | N3: CAD | O3: 辣椒酱（辣妹子，920G*12瓶/件） | P3: =M3/H3 -> 7.246118
A4: CA07 | B4: 1000103 | C4: 2025.05.01 | D4: 2025.05.31 | E4: 15.3 | F4: 0 | G4: 0 | H4: 15.3 | I4: KG | J4: 111.83 | K4: 0 | L4: 0 | M4: 111.83 | N4: CAD | O4: 大块腐乳（王致和，340G*15瓶/件） | P4: =M4/H4 -> 7.3091503
A5: CA07 | B5: 1000132 | C5: 2025.05.01 | D5: 2025.05.31 | E5: 36 | F5: 108 | G5: 0 | H5: 144 | I5: KG | J5: 306 | K5: 918 | L5: 0 | M5: 1224 | N5: CAD | O5: 沙茶酱（牛头，3KG*6瓶/件） | P5: =M5/H5 -> 8.5
A6: CA07 | B6: 1000233 | C6: 2025.05.01 | D6: 2025.05.31 | E6: 0 | F6: 0 | G6: 0 | H6: 0 | I6: KG | J6: 0 | K6: 0 | L6: 0 | M6: 0 | N6: CAD | O6: 甜面酱（散装，4KG*4包/件） | P6: =M6/H6 -> #DIV/0!
A7: CA07 | B7: 1000266 | C7: 2025.05.01 | D7: 2025.05.31 | E7: 0 | F7: 0 | G7: 0 | H7: 0 | I7: L | J7: 0 | K7: 0 | L7: 0 | M7: 0 | N7: CAD | O7: 特级头抽（500ML*12瓶/件） | P7: =M7/H7 -> #DIV/0!
A8: CA07 | B8: 1001170 | C8: 2025.05.01 | D8: 2025.05.31 | E8: 0 | F8: 0 | G8: 0 | H8: 0 | I8: KG | J8: 0 | K8: 0 | L8: 0 | M8: 0 | N8: CAD | O8: 墨鱼仔（越南，12KG/件） | P8: =M8/H8 -> #DIV/0!
A9: CA07 | B9: 1001268 | C9: 2025.05.01 | D9: 2025.05.31 | E9: 0 | F9: 0 | G9: 0 | H9: 0 | I9: KG | J9: 0 | K9: 0 | L9: 0 | M9: 0 | N9: CAD | O9: 辣椒酱（辣妹子，248G*24瓶/件） | P9: =M9/H9 -> #DIV/0!
A10: CA07 | B10: 1001413 | C10: 2025.05.01 | D10: 2025.05.31 | E10: 1.23 | F10: 4.92 | G10: 0 | H10: 6.15 | I10: L | J10: 17.67 | K10: 70.68 | L10: 0 | M10: 88.35 | N10: CAD | O10: 卤水汁（李锦记，410ML*12瓶/件） | P10: =M10/H10 -> 14.365854
A11: CA07 | B11: 1003028 | C11: 2025.05.01 | D11: 2025.05.31 | E11: 20 | F11: 500 | G11: 0 | H11: 520 | I11: KG | J11: 83.7 | K11: 2092.5 | L11: 0 | M11: 2176.2 | N11: CAD | O11: 牛油（20KG/件） | P11: =M11/H11 -> 4.185
A12: CA07 | B12: 1004576 | C12: 2025.05.01 | D12: 2025.05.31 | E12: 0 | F12: 10120 | G12: 0 | H12: 10120 | I12: Z07 | J12: 0 | K12: 1069.61 | L12: 0 | M12: 1069.61 | N12: CAD | O12: 虎牙脆（20G*230包/件） | P12: =M12/H12 -> 0.10569269
A13: CA07 | B13: 1500009 | C13: 2025.05.01 | D13: 2025.05.31 | E13: 15.4 | F13: 105.6 | G13: 0 | H13: 121 | I13: KG | J13: 48.12 | K13: 330 | L13: 0 | M13: 378.12 | N13: CAD | O13: 蚝油（李锦记，2.2KG*6桶/件） | P13: =M13/H13 -> 3.1249587
... A2236: CA07 | B2236: 8704096 | C2236: 2025.05.01 | D2236: 2025.05.31 | E2236: 98 | F2236: 392 | G2236: 0 | H2236: 490 | I2236: Z07 | J2236: 407.21 | K2236: 1574.27 | L2236: 0 | M2236: 1981.48 | N2236: CAD | O2236: 酒精湿巾（海底捞，独立包装，100片*14包/箱） | P2236: =M2236/H2236 -> 4.0438367
A2237: CA07 | B2237: 8704101 | C2237: 2025.05.01 | D2237: 2025.05.31 | E2237: 0 | F2237: 0 | G2237: 0 | H2237: 0 | I2237: Z05 | J2237: 0 | K2237: 0 | L2237: 0 | M2237: 0 | N2237: CAD | O2237: 208012 | P2237: =M2237/H2237 -> #DIV/0!
A2238: CA07 | B2238: 8704102 | C2238: 2025.05.01 | D2238: 2025.05.31 | E2238: 0 | F2238: 0 | G2238: 0 | H2238: 0 | I2238: Z11 | J2238: 0 | K2238: 0 | L2238: 0 | M2238: 0 | N2238: CAD | O2238: 长胶手套（出口） | P2238: =M2238/H2238 -> #DIV/0!
A2239: CA07 | B2239: 8704109 | C2239: 2025.05.01 | D2239: 2025.05.31 | E2239: 0 | F2239: 0 | G2239: 0 | H2239: 0 | I2239: Z06 | J2239: 0 | K2239: 0 | L2239: 0 | M2239: 0 | N2239: CAD | O2239: 五双装家庭筷（定制，礼品，120盒/箱） | P2239: =M2239/H2239 -> #DIV/0!
A2240: CA07 | B2240: 8704126 | C2240: 2025.05.01 | D2240: 2025.05.31 | E2240: 0 | F2240: 0 | G2240: 0 | H2240: 0 | I2240: Z05 | J2240: 0 | K2240: 0 | L2240: 0 | M2240: 0 | N2240: CAD | O2240: 小嗨-生日快乐手提袋（100个/件） | P2240: =M2240/H2240 -> #DIV/0!
A2241: CA07 | B2241: 8704127 | C2241: 2025.05.01 | D2241: 2025.05.31 | E2241: 0 | F2241: 0 | G2241: 0 | H2241: 0 | I2241: Z05 | J2241: 0 | K2241: 0 | L2241: 0 | M2241: 0 | N2241: CAD | O2241: 大打包纸袋（加拿大，法语专用，200个/件） | P2241: =M2241/H2241 -> #DIV/0!
A2242: CA07 | B2242: 8704128 | C2242: 2025.05.01 | D2242: 2025.05.31 | E2242: 0 | F2242: 0 | G2242: 0 | H2242: 0 | I2242: Z05 | J2242: 0 | K2242: 0 | L2242: 0 | M2242: 0 | N2242: CAD | O2242: 小打包纸袋（加拿大，法语专用，300个/件） | P2242: =M2242/H2242 -> #DIV/0!
A2243: CA07 | B2243: 8704129 | C2243: 2025.05.01 | D2243: 2025.05.31 | E2243: 0 | F2243: 0 | G2243: 0 | H2243: 0 | I2243: Z05 | J2243: 0 | K2243: 0 | L2243: 0 | M2243: 0 | N2243: CAD | O2243: 零食打包袋（加拿大，法语专用，1000个/件） | P2243: =M2243/H2243 -> #DIV/0!
P2244: =M2244/H2244 -> #DIV/0!
P2245: =M2245/H2245 -> #DIV/0!
P2246: =M2246/H2246 -> #DIV/0!
P2247: =M2247/H2247 -> #DIV/0!
P2248: =M2248/H2248 -> #DIV/0!
P2249: =M2249/H2249 -> #DIV/0!
P2250: =M2250/H2250 -> #DIV/0!
P2251: =M2251/H2251 -> #DIV/0!
P2252: =M2252/H2252 -> #DIV/0!
P2253: =M2253/H2253 -> #DIV/0!
P2254: =M2254/H2254 -> #DIV/0!
P2255: =M2255/H2255 -> #DIV/0!
... P2646: =M2646/H2646 -> #DIV/0!

Sheet 透视表
A1: 大类名称 | B1: (多项)
A3: 菜品编码 | B3: 菜品名称 | C3: 求和项:折算数量计算
A4: 01010106 | B4: 清水锅 | C4: 57942
A5: 01060061 | B5: 麻辣火锅（有渣） | C5: 34272
A6: 01060062 | B6: 猪骨汤 | C6: 116270
A7: 01060063 | B7: 菌汤火锅 | C7: 41922
A8: 01060064 | B8: 经典麻辣火锅 | C8: 45243
A9: 01060066 | B9: 番茄火锅 | C9: 162348
A10: 01060115 | B10: 胡椒猪肚鸡火锅 | C10: 20800
A11: 01060204 | B11: 酸菜鲜锅 | C11: 6262
A12: 01060227 | B12: 麻辣火锅（无渣） | C12: 41800
A13: 01310005 | B13: 叻沙火锅 | C13: 17424
A14: 12010002 | B14: 柠檬冰红茶 341ML | C14: 741
A15: 12010003 | B15: 甜豆浆（1L） | C15: 1728
... A50: 70000539 | B50: Peller family 红酒 | C50: 66
A51: 总计 | C51: 10800543

Sheet 红火台销售汇总
A1: 检索 | B1: 门店名称 | C1: 编码 | D1: 菜品编码 | E1: 菜品短编码 | F1: 菜品名称 | G1: 规格 | H1: 出品数量 | I1: 退菜数量 | J1: 实际出品数据（出品数量-退菜数量） | K1: 大类名称 | L1: 子类名称
A2: =B2&D2&E2&G2 -> 加拿大七店906001343013整份 | B2: 加拿大七店 | D2: 9060013 | E2: 43013 | F2: 黑猪肉 | G2: 整份 | H2: 960 | I2: 2 | J2: =H2-I2 -> 958 | K2: 荤菜 | L2: 牛/羊肉
A3: =B3&D3&E3&G3 -> 加拿大七店110102621002693半份 | B3: 加拿大七店 | D3: 11010262 | E3: 1002693 | F3: 白米饭(半） | G3: 半份 | H3: 239 | I3: 1 | J3: =H3-I3 -> 238 | K3: 小吃甜品 | L3: 主食类
A4: =B4&D4&E4&G4 -> 加拿大七店1101026250303整份 | B4: 加拿大七店 | D4: 11010262 | E4: 50303 | F4: 白米饭 | G4: 整份 | H4: 931 | I4: 6 | J4: =H4-I4 -> 925 | K4: 小吃甜品 | L4: 主食类
A5: =B5&D5&E5&G5 -> 加拿大七店1002013841184半份 | B5: 加拿大七店 | D5: 10020138 | E5: 41184 | F5: 芋头(半) | G5: 半份 | H5: 245 | I5: 3 | J5: =H5-I5 -> 242 | K5: 素菜 | L5: 根茎类
A6: =B6&D6&E6&G6 -> 加拿大七店1002013841183整份 | B6: 加拿大七店 | D6: 10020138 | E6: 41183 | F6: 芋头 | G6: 整份 | H6: 84 | I6: 1 | J6: =H6-I6 -> 83 | K6: 素菜 | L6: 根茎类
A7: =B7&D7&E7&G7 -> 加拿大七店1002001741017整份 | B7: 加拿大七店 | C7: =D7&G7 -> 10020017整份 | D7: 10020017 | E7: 41017 | F7: 菌类拼盘 | G7: 整份 | H7: 673 | I7: 1 | J7: =H7-I7 -> 672 | K7: 素菜 | L7: 菌类
A8: =B8&D8&E8&G8 -> 加拿大七店1301004170041冰镇 | B8: 加拿大七店 | C8: =D8&G8 -> 13010041冰镇 | D8: 13010041 | E8: 70041 | F8: 雪碧 | G8: 冰镇 | H8: 192 | I8: 0 | J8: =H8-I8 -> 192 | K8: 酒水饮料 | L8: 饮料
A9: =B9&D9&E9&G9 -> 加拿大七店700004077864份 | B9: 加拿大七店 | D9: 70000407 | E9: 7864 | F9: 肉汁奶酪薯条 | G9: 份 | H9: 100 | I9: 0 | J9: =H9-I9 -> 100 | K9: 小吃甜品 | L9: 小吃类
A10: =B10&D10&E10&G10 -> 加拿大七店90000413拼锅 | B10: 加拿大七店 | D10: 90000413 | F10: 冬阴功锅底 | G10: 拼锅 | H10: 331 | I10: 10 | J10: =H10-I10 -> 321 | K10: 锅底类 | L10: 拼锅类
A11: =B11&D11&E11&G11 -> 加拿大七店90000413四宫格 | B11: 加拿大七店 | C11: =D11&G11 -> 90000413四宫格 | D11: 90000413 | F11: 冬阴功锅底 | G11: 四宫格 | H11: 634 | I11: 6 | J11: =H11-I11 -> 628 | K11: 锅底类 | L11: 四宫格类
A12: =B12&D12&E12&G12 -> 加拿大七店70000769四宫格 | B12: 加拿大七店 | C12: =D12&G12 -> 70000769四宫格 | D12: 70000769 | F12: 寿喜锅底 | G12: 四宫格 | H12: 701 | I12: 11 | J12: =H12-I12 -> 690 | K12: 锅底类 | L12: 四宫格类
A13: =B13&D13&E13&G13 -> 加拿大七店70000769拼锅 | B13: 加拿大七店 | C13: =D13&G13 -> 70000769拼锅 | D13: 70000769 | F13: 寿喜锅底 | G13: 拼锅 | H13: 268 | I13: 7 | J13: =H13-I13 -> 261 | K13: 锅底类 | L13: 拼锅类
A14: =B14&D14&E14&G14 -> 加拿大七店7000064877308整份 | B14: 加拿大七店 | C14: =D14&G14 -> 70000648整份 | D14: 70000648 | E14: 77308 | F14: 澳洲青边鲍 | G14: 整份 | H14: 40 | I14: 1 | J14: =H14-I14 -> 39 | K14: 荤菜 | L14: 河/海鲜类
A15: =B15&D15&E15&G15 -> 加拿大七店1301004770047冰镇 | B15: 加拿大七店 | C15: =D15&G15 -> 13010047冰镇 | D15: 13010047 | E15: 70047 | F15: 椰汁 | G15: 冰镇 | H15: 88 | I15: 9 | J15: =H15-I15 -> 79 | K15: 酒水饮料 | L15: 饮料
A16: =B16&D16&E16&G16 -> 加拿大七店900017381003592整份 | B16: 加拿大七店 | C16: =D16&G16 -> 90001738整份 | D16: 90001738 | E16: 1003592 | F16: 炸馒头【金砖】 | G16: 整份 | H16: 1689 | I16: 6 | J16: =H16-I16 -> 1683 | K16: 火锅周边 | L16: 赠送及其他
A17: =B17&D17&E17&G17 -> 加拿大七店70002428拼锅 | B17: 加拿大七店 | C17: =D17&G17 -> 70002428拼锅 | D17: 70002428 | F17: 麻辣牛奶火锅 | G17: 拼锅 | H17: 306 | I17: 11 | J17: =H17-I17 -> 295 | K17: 锅底类 | L17: 拼锅类
A18: =B18&D18&E18&G18 -> 加拿大七店70002428四宫格 | B18: 加拿大七店 | D18: 70002428 | F18: 麻辣牛奶火锅 | G18: 四宫格 | H18: 630 | I18: 10 | J18: =H18-I18 -> 620 | K18: 锅底类 | L18: 四宫格类
A19: =B19&D19&E19&G19 -> 加拿大七店906009043251整份 | B19: 加拿大七店 | C19: =D19&G19 -> 9060090整份 | D19: 9060090 | E19: 43251 | F19: 港式鱼腐 | G19: 整份 | H19: 118 | I19: 0 | J19: =H19-I19 -> 118 | K19: 荤菜 | L19: 其他荤菜
A20: =B20&D20&E20&G20 -> 加拿大七店906009043252半份 | B20: 加拿大七店 | C20: =D20&G20 -> 9060090半份 | D20: 9060090 | E20: 43252 | F20: 港式鱼腐(半) | G20: 半份 | H20: 273 | I20: 1 | J20: =H20-I20 -> 272 | K20: 荤菜 | L20: 其他荤菜
A21: =B21&D21&E21&G21 -> 加拿大七店1001004440051整份 | B21: 加拿大七店 | C21: =D21&G21 -> 10010044整份 | D21: 10010044 | E21: 40051 | F21: 油条 | G21: 整份 | H21: 415 | I21: 5 | J21: =H21-I21 -> 410 | K21: 小吃甜品 | L21: 小吃类
A22: =B22&D22&E22&G22 -> 加拿大七店904036433429整份 | B22: 加拿大七店 | C22: =D22&G22 -> 9040364整份 | D22: 9040364 | E22: 33429 | F22: 芝士风味脆皮肠 | G22: 整份 | H22: 293 | I22: 1 | J22: =H22-I22 -> 292 | K22: 经典火锅菜 | L22: 经典火锅菜类
A23: =B23&D23&E23&G23 -> 加拿大七店1101037950485整份 | B23: 加拿大七店 | C23: =D23&G23 -> 11010379整份 | D23: 11010379 | E23: 50485 | F23: 乌冬面 | G23: 整份 | H23: 1050 | I23: 4 | J23: =H23-I23 -> 1046 | K23: 素菜 | L23: 豆面制品
A24: =B24&D24&E24&G24 -> 加拿大七店7000118278433整份 | B24: 加拿大七店 | D24: 70001182 | E24: 78433 | F24: Prime级去骨牛小排 | G24: 整份 | H24: 1315 | I24: 9 | J24: =H24-I24 -> 1306 | K24: 荤菜 | L24: 牛/羊肉
A25: =B25&D25&E25&G25 -> 加拿大七店1002002541025整份 | B25: 加拿大七店 | D25: 10020025 | E25: 41025 | F25: 冬瓜 | G25: 整份 | H25: 390 | I25: 1 | J25: =H25-I25 -> 389 | K25: 素菜 | L25: 根茎类
A26: =B26&D26&E26&G26 -> 加拿大七店1201000160001整份 | B26: 加拿大七店 | D26: 12010001 | E26: 60001 | F26: 自选小料/每位 | G26: 整份 | H26: 17793 | I26: 74 | J26: =H26-I26 -> 17719 | K26: 火锅周边 | L26: 自选调料
A27: =B27&D27&E27&G27 -> 加拿大七店1101003050055整份 | B27: 加拿大七店 | D27: 11010030 | E27: 50055 | F27: 长寿面 | G27: 整份 | H27: 247 | I27: 4 | J27: =H27-I27 -> 243 | K27: 火锅周边 | L27: 赠送及其他
A28: =B28&D28&E28&G28 -> 加拿大七店1002002771120份 | B28: 加拿大七店 | D28: 10020027 | E28: 71120 | F28: 山药 | G28: 份 | H28: 140 | I28: 0 | J28: =H28-I28 -> 140 | K28: 素菜 | L28: 根茎类
A29: =B29&D29&E29&G29 -> 加拿大七店901002130022半份 | B29: 加拿大七店 | D29: 9010021 | E29: 30022 | F29: 捞派羊肉(半) | G29: 半份 | H29: 239 | I29: 1 | J29: =H29-I29 -> 238 | K29: 经典火锅菜 | L29: 经典火锅菜类
A30: =B30&D30&E30&G30 -> 加拿大七店901002130021整份 | B30: 加拿大七店 | D30: 9010021 | E30: 30021 | F30: 捞派羊肉 | G30: 整份 | H30: 193 | I30: 1 | J30: =H30-I30 -> 192 | K30: 经典火锅菜 | L30: 经典火锅菜类
A31: =B31&D31&E31&G31 -> 加拿大七店903033032331整份 | B31: 加拿大七店 | D31: 9030330 | E31: 32331 | F31: 脆皖鱼 | G31: 整份 | H31: 179 | I31: 1 | J31: =H31-I31 -> 178 | K31: 荤菜 | L31: 河/海鲜类
A32: =B32&D32&E32&G32 -> 加拿大七店903033032332半份 | B32: 加拿大七店 | D32: 9030330 | E32: 32332 | F32: 脆皖鱼(半) | G32: 半份 | H32: 308 | I32: 3 | J32: =H32-I32 -> 305 | K32: 荤菜 | L32: 河/海鲜类
A33: =B33&D33&E33&G33 -> 加拿大七店1002002341023整份 | B33: 加拿大七店 | D33: 10020023 | E33: 41023 | F33: 茼蒿 | G33: 整份 | H33: 535 | I33: 2 | J33: =H33-I33 -> 533 | K33: 素菜 | L33: 蔬菜类
A34: =B34&D34&E34&G34 -> 加拿大七店1002002341024半份 | B34: 加拿大七店 | D34: 10020023 | E34: 41024 | F34: 茼蒿(半) | G34: 半份 | H34: 638 | I34: 4 | J34: =H34-I34 -> 634 | K34: 素菜 | L34: 蔬菜类
A35: =B35&D35&E35&G35 -> 加拿大七店1201000260002冰镇 | B35: 加拿大七店 | D35: 12010002 | E35: 60002 | F35: 柠檬冰红茶 341ML | G35: 冰镇 | H35: 134 | I35: 1 | J35: =H35-I35 -> 133 | K35: 酒水饮料 | L35: 饮料
... A40: =B40&D40&E40&G40 -> 加拿大七店7000120678510半份 | B40: 加拿大七店 | D40: 70001206 | E40: 78510 | F40: 8秒劲道油豆皮（半） | G40: 半份 | H40: 294 | I40: 0 | J40: =H40-I40 -> 294 | K40: 素菜 | L40: 豆面制品
A41: =B41&D41&E41&G41 -> 加拿大七店7000120678509整份 | B41: 加拿大七店 | C41: =D41&G41 -> 70001206整份 | D41: 70001206 | E41: 78509 | F41: 8秒劲道油豆皮 | G41: 整份 | H41: 180 | I41: 0 | J41: =H41-I41 -> 180 | K41: 素菜 | L41: 豆面制品
A42: =B42&D42&E42&G42 -> 加拿大七店1202004261045整份 | B42: 加拿大七店 | C42: =D42&G42 -> 12020042整份 | D42: 12020042 | E42: 61045 | F42: 未使用小料 | G42: 整份 | H42: 4355 | I42: 7 | J42: =H42-I42 -> 4348 | K42: 火锅周边 | L42: 赠送及其他
A43: =B43&D43&E43&G43 -> 加拿大七店7000169879583半份 | B43: 加拿大七店 | C43: =D43&G43 -> 70001698半份 | D43: 70001698 | E43: 79583 | F43: 手工现做牛筋丸（半） | G43: 半份 | H43: 245 | I43: 1 | J43: =H43-I43 -> 244 | K43: 荤菜 | L43: 丸滑类
A44: =B44&D44&E44&G44 -> 加拿大七店7000169879582整份 | B44: 加拿大七店 | C44: =D44&G44 -> 70001698整份 | D44: 70001698 | E44: 79582 | F44: 手工现做牛筋丸 | G44: 整份 | H44: 178 | I44: 0 | J44: =H44-I44 -> 178 | K44: 荤菜 | L44: 丸滑类
A45: =B45&D45&E45&G45 -> 加拿大七店1001031240521整份 | B45: 加拿大七店 | C45: =D45&G45 -> 10010312整份 | D45: 10010312 | E45: 40521 | F45: 豆皮 | G45: 整份 | H45: 455 | I45: 2 | J45: =H45-I45 -> 453 | K45: 素菜 | L45: 豆面制品
A46: =B46&D46&E46&G46 -> 加拿大七店900028141109399瓶 | B46: 加拿大七店 | D46: 90002814 | E46: 1109399 | F46: 草莓奶盖椰椰 | G46: 瓶 | H46: 490 | I46: 2 | J46: =H46-I46 -> 488 | K46: 酒水饮料 | L46: 饮料
A47: =B47&D47&E47&G47 -> 加拿大七店902006331063整份 | B47: 加拿大七店 | D47: 9020063 | E47: 31063 | F47: 捞派虾滑 | G47: 整份 | H47: 1661 | I47: 6 | J47: =H47-I47 -> 1655 | K47: 荤菜 | L47: 丸滑类
A48: =B48&D48&E48&G48 -> 加拿大七店1301004070040冰镇 | B48: 加拿大七店 | D48: 13010040 | E48: 70040 | F48: 可口可乐 | G48: 冰镇 | H48: 554 | I48: 3 | J48: =H48-I48 -> 551 | K48: 酒水饮料 | L48: 饮料
A49: =B49&D49&E49&G49 -> 加拿大七店1002027041280半份 | B49: 加拿大七店 | D49: 10020270 | E49: 41280 | F49: 宽粉(半) | G49: 半份 | H49: 501 | I49: 2 | J49: =H49-I49 -> 499 | K49: 素菜 | L49: 豆面制品
A50: =B50&D50&E50&G50 -> 加拿大七店1002027041279整份 | B50: 加拿大七店 | D50: 10020270 | E50: 41279 | F50: 宽粉 | G50: 整份 | H50: 356 | I50: 0 | J50: =H50-I50 -> 356 | K50: 素菜 | L50: 豆面制品
A51: =B51&D51&E51&G51 -> 加拿大七店1060062单锅 | B51: 加拿大七店 | D51: 1060062 | F51: 三鲜猪骨火锅 | G51: 单锅 | H51: 53 | I51: 7 | J51: =H51-I51 -> 46 | K51: 锅底类 | L51: 单锅类
A52: =B52&D52&E52&G52 -> 加拿大七店1060062拼锅 | B52: 加拿大七店 | D52: 1060062 | F52: 三鲜猪骨火锅 | G52: 拼锅 | H52: 1190 | I52: 26 | J52: =H52-I52 -> 1164 | K52: 锅底类 | L52: 拼锅类
A53: =B53&D53&E53&G53 -> 加拿大七店1060062四宫格 | B53: 加拿大七店 | D53: 1060062 | F53: 三鲜猪骨火锅 | G53: 四宫格 | H53: 1381 | I53: 27 | J53: =H53-I53 -> 1354 | K53: 锅底类 | L53: 四宫格类
A54: =B54&D54&E54&G54 -> 加拿大七店301002320024半份 | B54: 加拿大七店 | D54: 3010023 | E54: 20024 | F54: 猪血(半) | G54: 半份 | H54: 553 | I54: 3 | J54: =H54-I54 -> 550 | K54: 经典火锅菜 | L54: 经典火锅菜类
A55: =B55&D55&E55&G55 -> 加拿大七店301002320023整份 | B55: 加拿大七店 | D55: 3010023 | E55: 20023 | F55: 猪血 | G55: 整份 | H55: 191 | I55: 1 | J55: =H55-I55 -> 190 | K55: 经典火锅菜 | L55: 经典火锅菜类
A56: =B56&D56&E56&G56 -> 加拿大七店1060061拼锅 | B56: 加拿大七店 | D56: 1060061 | F56: 清油麻辣火锅 | G56: 拼锅 | H56: 276 | I56: 11 | J56: =H56-I56 -> 265 | K56: 锅底类 | L56: 拼锅类
A57: =B57&D57&E57&G57 -> 加拿大七店1060061四宫格 | B57: 加拿大七店 | D57: 1060061 | F57: 清油麻辣火锅 | G57: 四宫格 | H57: 494 | I57: 5 | J57: =H57-I57 -> 489 | K57: 锅底类 | L57: 四宫格类
A58: =B58&D58&E58&G58 -> 加拿大七店1060064拼锅 | B58: 加拿大七店 | D58: 1060064 | F58: 经典麻辣火锅 | G58: 拼锅 | H58: 798 | I58: 21 | J58: =H58-I58 -> 777 | K58: 锅底类 | L58: 拼锅类
A59: =B59&D59&E59&G59 -> 加拿大七店1060064四宫格 | B59: 加拿大七店 | D59: 1060064 | F59: 经典麻辣火锅 | G59: 四宫格 | H59: 1230 | I59: 17 | J59: =H59-I59 -> 1213 | K59: 锅底类 | L59: 四宫格类
A60: =B60&D60&E60&G60 -> 加拿大七店1060063拼锅 | B60: 加拿大七店 | C60: =D60&G60 -> 1060063拼锅 | D60: 1060063 | F60: 菌汤火锅 | G60: 拼锅 | H60: 358 | I60: 9 | J60: =H60-I60 -> 349 | K60: 锅底类 | L60: 拼锅类
A61: =B61&D61&E61&G61 -> 加拿大七店1060063四宫格 | B61: 加拿大七店 | C61: =D61&G61 -> 1060063四宫格 | D61: 1060063 | F61: 菌汤火锅 | G61: 四宫格 | H61: 708 | I61: 11 | J61: =H61-I61 -> 697 | K61: 锅底类 | L61: 四宫格类
A62: =B62&D62&E62&G62 -> 加拿大七店1060066拼锅 | B62: 加拿大七店 | C62: =D62&G62 -> 1060066拼锅 | D62: 1060066 | F62: 番茄火锅 | G62: 拼锅 | H62: 1331 | I62: 32 | J62: =H62-I62 -> 1299 | K62: 锅底类 | L62: 拼锅类
A63: =B63&D63&E63&G63 -> 加拿大七店1060066四宫格 | B63: 加拿大七店 | C63: =D63&G63 -> 1060066四宫格 | D63: 1060066 | F63: 番茄火锅 | G63: 四宫格 | H63: 2096 | I63: 35 | J63: =H63-I63 -> 2061 | K63: 锅底类 | L63: 四宫格类
A64: =B64&D64&E64&G64 -> 加拿大七店901029830355整份 | B64: 加拿大七店 | C64: =D64&G64 -> 9010298整份 | D64: 9010298 | E64: 30355 | F64: 和牛牛舌 | G64: 整份 | H64: 846 | I64: 8 | J64: =H64-I64 -> 838 | K64: 荤菜 | L64: 牛/羊肉
A65: =B65&D65&E65&G65 -> 加拿大七店900025331005372冰镇 | B65: 加拿大七店 | C65: =D65&G65 -> 90002533冰镇 | D65: 90002533 | E65: 1005372 | F65: 白桃果肉汁 | G65: 冰镇 | H65: 12 | I65: 7 | J65: =H65-I65 -> 5 | K65: 酒水饮料 | L65: 饮料
A66: =B66&D66&E66&G66 -> 加拿大七店1401003580005整份 | B66: 加拿大七店 | C66: =D66&G66 -> 14010035整份 | D66: 14010035 | E66: 80005 | F66: 蒸蛋 | G66: 整份 | H66: 441 | I66: 5 | J66: =H66-I66 -> 436 | K66: 火锅周边 | L66: 赠送及其他
A67: =B67&D67&E67&G67 -> 加拿大七店901005130053整份 | B67: 加拿大七店 | C67: =D67&G67 -> 9010051整份 | D67: 9010051 | E67: 30053 | F67: 雪花和牛 | G67: 整份 | H67: 272 | I67: 2 | J67: =H67-I67 -> 270 | K67: 荤菜 | L67: 牛/羊肉
A68: =B68&D68&E68&G68 -> 加拿大七店900012011004228瓶 | B68: 加拿大七店 | C68: =D68&G68 -> 90001201瓶 | D68: 90001201 | E68: 1004228 | F68: 浓浓抹茶生椰 | G68: 瓶 | H68: 284 | I68: 2 | J68: =H68-I68 -> 282 | K68: 酒水饮料 | L68: 饮料
A69: =B69&D69&E69&G69 -> 加拿大七店900012011004229扎 | B69: 加拿大七店 | C69: =D69&G69 -> 90001201扎 | D69: 90001201 | E69: 1004229 | F69: 浓浓抹茶生椰 | G69: 扎 | H69: 70 | I69: 3 | J69: =H69-I69 -> 67 | K69: 酒水饮料 | L69: 饮料
A70: =B70&D70&E70&G70 -> 加拿大七店301002720027条 | B70: 加拿大七店 | C70: =D70&G70 -> 3010027条 | D70: 3010027 | E70: 20027 | F70: 捞派捞面 | G70: 条 | H70: 1765 | I70: 51 | J70: =H70-I70 -> 1714 | K70: 素菜 | L70: 豆面制品
A71: =B71&D71&E71&G71 -> 加拿大七店1001002540025整份 | B71: 加拿大七店 | C71: =D71&G71 -> 10010025整份 | D71: 10010025 | E71: 40025 | F71: 鲜腐竹 | G71: 整份 | H71: 909 | I71: 3 | J71: =H71-I71 -> 906 | K71: 素菜 | L71: 豆面制品
A72: =B72&D72&E72&G72 -> 加拿大七店1003023642239整份 | B72: 加拿大七店 | C72: =D72&G72 -> 10030236整份 | D72: 10030236 | E72: 42239 | F72: 竹笙 | G72: 整份 | H72: 310 | I72: 0 | J72: =H72-I72 -> 310 | K72: 素菜 | L72: 菌类
A73: =B73&D73&E73&G73 -> 加拿大七店1101011950137片 | B73: 加拿大七店 | C73: =D73&G73 -> 11010119片 | D73: 11010119 | E73: 50137 | F73: 辛拉面 | G73: 片 | H73: 764 | I73: 1 | J73: =H73-I73 -> 763 | K73: 素菜 | L73: 豆面制品
A74: =B74&D74&E74&G74 -> 加拿大七店1002016041167整份 | B74: 加拿大七店 | C74: =D74&G74 -> 10020160整份 | D74: 10020160 | E74: 41167 | F74: 贡菜 | G74: 整份 | H74: 641 | I74: 5 | J74: =H74-I74 -> 636 | K74: 素菜 | L74: 根茎类
A75: =B75&D75&E75&G75 -> 加拿大七店1404008182081整份 | B75: 加拿大七店 | C75: =D75&G75 -> 14040081整份 | D75: 14040081 | E75: 82081 | F75: 果盘 | G75: 整份 | H75: 474 | I75: 4 | J75: =H75-I75 -> 470 | K75: 火锅周边 | L75: 赠送及其他
... A78: =B78&D78&E78&G78 -> 加拿大七店1002004141041整份 | B78: 加拿大七店 | C78: =D78&G78 -> 10020041整份 | D78: 10020041 | E78: 41041 | F78: 高山青竹笋 | G78: 整份 | H78: 419 | I78: 0 | J78: =H78-I78 -> 419 | K78: 素菜 | L78: 根茎类
A79: =B79&D79&E79&G79 -> 加拿大七店904006533066半份 | B79: 加拿大七店 | D79: 9040065 | E79: 33066 | F79: 蟹味棒(半) | G79: 半份 | H79: 350 | I79: 1 | J79: =H79-I79 -> 349 | K79: 经典火锅菜 | L79: 经典火锅菜类
A80: =B80&D80&E80&G80 -> 加拿大七店904006533065整份 | B80: 加拿大七店 | D80: 9040065 | E80: 33065 | F80: 蟹味棒 | G80: 整份 | H80: 121 | I80: 0 | J80: =H80-I80 -> 121 | K80: 经典火锅菜 | L80: 经典火锅菜类
A81: =B81&D81&E81&G81 -> 加拿大七店904006333063整份 | B81: 加拿大七店 | D81: 9040063 | E81: 33063 | F81: 鹌鹑蛋 | G81: 整份 | H81: 809 | I81: 5 | J81: =H81-I81 -> 804 | K81: 经典火锅菜 | L81: 经典火锅菜类
A82: =B82&D82&E82&G82 -> 加拿大七店1014000969009整份 | B82: 加拿大七店 | D82: 10140009 | E82: 69009 | F82: 蔬菜拼盘 | G82: 整份 | H82: 1017 | I82: 3 | J82: =H82-I82 -> 1014 | K82: 素菜 | L82: 蔬菜类
A83: =B83&D83&E83&G83 -> 加拿大七店1002004741047整份 | B83: 加拿大七店 | D83: 10020047 | E83: 41047 | F83: 魔芋丝 | G83: 整份 | H83: 547 | I83: 0 | J83: =H83-I83 -> 547 | K83: 素菜 | L83: 豆面制品
A84: =B84&D84&E84&G84 -> 加拿大七店1301045770457冰镇 | B84: 加拿大七店 | D84: 13010457 | E84: 70457 | F84: 北冰洋 | G84: 冰镇 | H84: 159 | I84: 3 | J84: =H84-I84 -> 156 | K84: 酒水饮料 | L84: 饮料
A85: =B85&D85&E85&G85 -> 加拿大七店1002004341044半份 | B85: 加拿大七店 | D85: 10020043 | E85: 41044 | F85: 海带(半) | G85: 半份 | H85: 214 | I85: 0 | J85: =H85-I85 -> 214 | K85: 素菜 | L85: 根茎类
A86: =B86&D86&E86&G86 -> 加拿大七店1002004341043整份 | B86: 加拿大七店 | D86: 10020043 | E86: 41043 | F86: 海带 | G86: 整份 | H86: 84 | I86: 0 | J86: =H86-I86 -> 84 | K86: 素菜 | L86: 根茎类
A87: =B87&D87&E87&G87 -> 加拿大七店1060115拼锅 | B87: 加拿大七店 | D87: 1060115 | F87: 胡椒猪肚鸡火锅 | G87: 拼锅 | H87: 281 | I87: 3 | J87: =H87-I87 -> 278 | K87: 锅底类 | L87: 拼锅类
A88: =B88&D88&E88&G88 -> 加拿大七店1060115四宫格 | B88: 加拿大七店 | D88: 1060115 | F88: 胡椒猪肚鸡火锅 | G88: 四宫格 | H88: 682 | I88: 12 | J88: =H88-I88 -> 670 | K88: 锅底类 | L88: 四宫格类
A89: =B89&D89&E89&G89 -> 加拿大七店1102003551035整份 | B89: 加拿大七店 | D89: 11020035 | E89: 51035 | F89: 糖蒜 | G89: 整份 | H89: 143 | I89: 0 | J89: =H89-I89 -> 143 | K89: 小吃甜品 | L89: 小吃类
A90: =B90&D90&E90&G90 -> 加拿大七店1301045570455冰镇 | B90: 加拿大七店 | D90: 13010455 | E90: 70455 | F90: 健怡可乐 | G90: 冰镇 | H90: 475 | I90: 8 | J90: =H90-I90 -> 467 | K90: 酒水饮料 | L90: 饮料
A91: =B91&D91&E91&G91 -> 加拿大七店1001001740017整份 | B91: 加拿大七店 | D91: 10010017 | E91: 40017 | F91: 冻豆腐 | G91: 整份 | H91: 614 | I91: 2 | J91: =H91-I91 -> 612 | K91: 素菜 | L91: 豆面制品
A92: =B92&D92&E92&G92 -> 加拿大七店1101040750529整份 | B92: 加拿大七店 | C92: =D92&G92 -> 11010407整份 | D92: 11010407 | E92: 50529 | F92: 酒酿圆子（冰镇） | G92: 整份 | H92: 222 | I92: 3 | J92: =H92-I92 -> 219 | K92: 小吃甜品 | L92: 甜品类
A93: =B93&D93&E93&G93 -> 加拿大七店1010106拼锅 | B93: 加拿大七店 | C93: =D93&G93 -> 1010106拼锅 | D93: 1010106 | F93: 清水火锅 | G93: 拼锅 | H93: 375 | I93: 14 | J93: =H93-I93 -> 361 | K93: 锅底类 | L93: 拼锅类
A94: =B94&D94&E94&G94 -> 加拿大七店1010106四宫格 | B94: 加拿大七店 | D94: 1010106 | F94: 清水火锅 | G94: 四宫格 | H94: 4139 | I94: 82 | J94: =H94-I94 -> 4057 | K94: 锅底类 | L94: 四宫格类
A95: =B95&D95&E95&G95 -> 加拿大七店1001001540015整份 | B95: 加拿大七店 | D95: 10010015 | E95: 40015 | F95: 鲜豆腐 | G95: 整份 | H95: 663 | I95: 1 | J95: =H95-I95 -> 662 | K95: 素菜 | L95: 豆面制品
A96: =B96&D96&E96&G96 -> 加拿大七店7000147679074整份 | B96: 加拿大七店 | D96: 70001476 | E96: 79074 | F96: 黑鱼片 | G96: 整份 | H96: 171 | I96: 1 | J96: =H96-I96 -> 170 | K96: 荤菜 | L96: 河/海鲜类
A97: =B97&D97&E97&G97 -> 加拿大七店7000147679075半份 | B97: 加拿大七店 | C97: =D97&G97 -> 70001476半份 | D97: 70001476 | E97: 79075 | F97: 黑鱼片(半） | G97: 半份 | H97: 312 | I97: 4 | J97: =H97-I97 -> 308 | K97: 荤菜 | L97: 河/海鲜类
A98: =B98&D98&E98&G98 -> 加拿大七店7000066277330整份 | B98: 加拿大七店 | C98: =D98&G98 -> 70000662整份 | D98: 70000662 | E98: 77330 | F98: 豆腐泡 | G98: 整份 | H98: 542 | I98: 1 | J98: =H98-I98 -> 541 | K98: 素菜 | L98: 豆面制品
A99: =B99&D99&E99&G99 -> 加拿大七店110100081002694整份 | B99: 加拿大七店 | C99: =D99&G99 -> 11010008整份 | D99: 11010008 | E99: 1002694 | F99: 蛋炒饭 | G99: 整份 | H99: 742 | I99: 15 | J99: =H99-I99 -> 727 | K99: 小吃甜品 | L99: 主食类
A100: =B100&D100&E100&G100 -> 加拿大七店110100081002695半份 | B100: 加拿大七店 | C100: =D100&G100 -> 11010008半份 | D100: 11010008 | E100: 1002695 | F100: 蛋炒饭(半） | G100: 半份 | H100: 271 | I100: 3 | J100: =H100-I100 -> 268 | K100: 小吃甜品 | L100: 主食类
A101: =B101&D101&E101&G101 -> 加拿大七店1002005141051整份 | B101: 加拿大七店 | C101: =D101&G101 -> 10020051整份 | D101: 10020051 | E101: 41051 | F101: 青笋 | G101: 整份 | H101: 419 | I101: 3 | J101: =H101-I101 -> 416 | K101: 素菜 | L101: 根茎类
A102: =B102&D102&E102&G102 -> 加拿大七店1101000550009整份 | B102: 加拿大七店 | C102: =D102&G102 -> 11010005整份 | D102: 11010005 | E102: 50009 | F102: 金馒头 | G102: 整份 | H102: 573 | I102: 5 | J102: =H102-I102 -> 568 | K102: 小吃甜品 | L102: 小吃类
A103: =B103&D103&E103&G103 -> 加拿大七店1002005341054半份 | B103: 加拿大七店 | C103: =D103&G103 -> 10020053半份 | D103: 10020053 | E103: 41054 | F103: 白萝卜(半) | G103: 半份 | H103: 192 | I103: 1 | J103: =H103-I103 -> 191 | K103: 素菜 | L103: 根茎类
A104: =B104&D104&E104&G104 -> 加拿大七店1002005341053整份 | B104: 加拿大七店 | C104: =D104&G104 -> 10020053整份 | D104: 10020053 | E104: 41053 | F104: 白萝卜 | G104: 整份 | H104: 90 | I104: 5 | J104: =H104-I104 -> 85 | K104: 素菜 | L104: 根茎类
A105: =B105&D105&E105&G105 -> 加拿大七店1101048350681整份 | B105: 加拿大七店 | C105: =D105&G105 -> 11010483整份 | D105: 11010483 | E105: 50681 | F105: 熔岩虾球 | G105: 整份 | H105: 293 | I105: 0 | J105: =H105-I105 -> 293 | K105: 小吃甜品 | L105: 小吃类
A106: =B106&D106&E106&G106 -> 加拿大七店901032530395整份 | B106: 加拿大七店 | D106: 9010325 | E106: 30395 | F106: 精品牛板腱肉（偏瘦） | G106: 整份 | H106: 2021 | I106: 11 | J106: =H106-I106 -> 2010 | K106: 荤菜 | L106: 牛/羊肉
...

Sheet Sheet3
A2: 每月需更新数据
A3: 求和项:实际出品数据（出品数量-退菜数量）
A4: 检索 | B4: 汇总
A5: (空白)
A6: 1412000184001整份 | B6: 32
A7: 加拿大七店1301044570445冰镇 | B7: 156
A8: 加拿大七店906001343013整份 | B8: 958
A9: 加拿大七店110102621002693半份 | B9: 238
A10: 加拿大七店1101026250303整份 | B10: 925
A11: 加拿大七店1002013841184半份 | B11: 242
A12: 加拿大七店1002013841183整份 | B12: 83
A13: 加拿大七店1002001741017整份 | B13: 672
A14: 加拿大七店1301004170041冰镇 | B14: 192
A15: 加拿大七店700004077864份 | B15: 100
A16: 加拿大七店7000064877308整份 | B16: 39
A17: 加拿大七店902051831869磅 | B17: 1
... A262: 1304028473284常温 | B262: 3
A263: 130101471108213扎
A264: 910050181109547份
A265: 加拿大七店2601037008套餐 | B265: 907
A266: 加拿大七店910057161111214份 | B266: 696
A267: 加拿大七店910059501111493份 | B267: 3303
A268: 加拿大七店910057321111186瓶 | B268: 59
A269: 加拿大七店1002058041625整份 | B269: 84
A270: 加拿大七店1401008580055整份 | B270: 94
A271: 加拿大七店901014730175整份 | B271: 156
A272: 加拿大七店1010681单锅 | B272: 1
A273: 加拿大七店1310005四宫格 | B273: 328
A274: 1310005拼锅 | B274: 145
A275: 903049832583整份 | B275: 46
A276: 902051831869磅 | B276: 1
... A279: 1000000305套餐 | B279: 25
A280: 1310005单锅
A281: 910059741111526瓶
A282: 900002051001819个
A283: 900021311004528整份
A284: 910059091111487份
A285: 7000069377384整份
A286: 902026831273整份
A287: 总计 | B287: 128781

Sheet 计算
A1: 检索 | B1: 区域名称 | C1: 门店名称 | D1: 大类名称 | E1: 子类名称 | F1: 菜品编码 | G1: 菜品短编码 | H1: 菜品名称 | I1: 菜品名称（系统） | J1: 规格 | K1: 菜品单价 | L1: 菜品单位 | M1: 实收数量 | N1: 出品分量 | O1: 损耗 | P1: 物料单位 | Q1: 红火台理论量 | R1: 物料号 | S1: 物料描述 | T1: 物料用量 | U1: 差异 | V1: 备注1 | W1: 套餐 | X1: 备注 | Y1: 单位 | Z1: 差异绝对值
A2: =C2&F2&G2&J2 -> 加拿大七店1060061单锅 | B2: 加拿大 | C2: 加拿大七店 | D2: 锅底类 | E2: 锅底类 | F2: 1060061 | H2: 清油麻辣火锅 | I2: 清油麻辣火锅 | J2: 单锅 | K2: 28.95 | L2: 锅 | M2: =IFERROR(VLOOKUP(A2,Sheet3!$A:$B,2,0),0) -> 3 | N2: 1 | O2: 1 | Q2: =M2*N2*O2 -> 3 | R2: 3000759 | S2: =VLOOKUP(R2,'CA07-本月-盘点结果'!$B:$C,2,0) -> 清油底料（300G*40包/件） | T2: =VLOOKUP(R2,'CA07-本月-盘点结果'!B:I,8,0) -> 480 | U2: =T2-Q2-Q3-Q4-Q23-Q24-Q25-W2 -> -124.15 | W2: =325*0.3 -> 97.5 | X2: 少使用了97kg | Y2: 公斤 | Z2: 120.4
A3: =C3&F3&G3&J3 -> 加拿大七店1060061拼锅 | B3: 加拿大 | C3: 加拿大七店 | D3: 锅底类 | E3: 锅底类 | F3: 1060061 | H3: 清油麻辣火锅 | I3: 清油麻辣火锅 | J3: 拼锅 | K3: 14.95 | L3: 锅 | M3: =IFERROR(VLOOKUP(A3,Sheet3!$A:$B,2,0),0) -> 265 | N3: 0.5 | O3: 1 | Q3: =M3*N3*O3 -> 132.5 | R3: 3000759 | S3: =VLOOKUP(R3,'CA07-本月-盘点结果'!$B:$C,2,0) -> 清油底料（300G*40包/件） | Y3: 公斤 | Z3: 0
A4: =C4&F4&G4&J4 -> 加拿大七店1060061四宫格 | B4: 加拿大 | C4: 加拿大七店 | D4: 锅底类 | E4: 锅底类 | F4: 1060061 | H4: 清油麻辣火锅 | I4: 清油麻辣火锅 | J4: 四宫格 | K4: 5.95 | L4: 锅 | M4: =IFERROR(VLOOKUP(A4,Sheet3!$A:$B,2,0),0)+18 -> 507 | N4: 0.25 | O4: 1 | Q4: =M4*N4*O4 -> 126.75 | R4: 3000759 | S4: =VLOOKUP(R4,'CA07-本月-盘点结果'!$B:$C,2,0) -> 清油底料（300G*40包/件） | Y4: 公斤 | Z4: 0
A5: =C5&F5&G5&J5 -> 加拿大七店1060062单锅 | B5: 加拿大 | C5: 加拿大七店 | D5: 锅底类 | E5: 锅底类 | F5: 1060062 | H5: 三鲜猪骨火锅 | I5: 三鲜火锅 | J5: 单锅 | K5: 24.95 | L5: 锅 | M5: =IFERROR(VLOOKUP(A5,Sheet3!$A:$B,2,0),0) -> 46 | N5: 0.15 | O5: 1 | P5: 0.354 | Q5: =M5*N5*O5 -> 6.9 | R5: 1500882 | S5: =VLOOKUP(R5,'CA07-本月-盘点结果'!$B:$C,2,0) -> 三花淡奶（354ML*48瓶/箱） | T5: =VLOOKUP(R5,'CA07-本月-盘点结果'!B:I,8,0) -> 974 | U5: =T5-(Q5+Q6+Q7+Q186+Q187+Q188+Q189+Q190+Q191)/P5 -> 564.4661 | Y5: 瓶 | Z5: 9.82
A6: =C6&F6&G6&J6 -> 加拿大七店1060062拼锅 | B6: 加拿大 | C6: 加拿大七店 | D6: 锅底类 | E6: 锅底类 | F6: 1060062 | H6: 三鲜猪骨火锅 | I6: 三鲜火锅 | J6: 拼锅 | K6: 12.95 | L6: 锅 | M6: =IFERROR(VLOOKUP(A6,Sheet3!$A:$B,2,0),0) -> 1164 | N6: 0.075 | O6: 1 | P6: 0.354 | Q6: =M6*N6*O6 -> 87.3 | R6: 1500882 | S6: =VLOOKUP(R6,'CA07-本月-盘点结果'!$B:$C,2,0) -> 三花淡奶（354ML*48瓶/箱） | Y6: 瓶 | Z6: 0
A7: =C7&F7&G7&J7 -> 加拿大七店1060062四宫格 | B7: 加拿大 | C7: 加拿大七店 | D7: 锅底类 | E7: 锅底类 | F7: 1060062 | H7: 三鲜猪骨火锅 | I7: 三鲜火锅 | J7: 四宫格 | K7: 4.95 | L7: 锅 | M7: =IFERROR(VLOOKUP(A7,Sheet3!$A:$B,2,0),0) -> 1354 | N7: 0.0375 | O7: 1 | P7: 0.354 | Q7: =M7*N7*O7 -> 50.775 | R7: 1500882 | S7: =VLOOKUP(R7,'CA07-本月-盘点结果'!$B:$C,2,0) -> 三花淡奶（354ML*48瓶/箱） | Y7: 瓶 | Z7: 0
A8: =C8&F8&G8&J8 -> 加拿大七店1060063单锅 | B8: 加拿大 | C8: 加拿大七店 | D8: 锅底类 | E8: 锅底类 | F8: 1060063 | H8: 菌汤火锅 | I8: 菌汤火锅 | J8: 单锅 | K8: 24.95 | L8: 锅 | M8: =IFERROR(VLOOKUP(A8,Sheet3!$A:$B,2,0),0) -> 7 | N8: 0.42 | O8: 1 | Q8: =M8*N8*O8 -> 2.94 | R8: 4514602 | S8: =VLOOKUP(R8,'CA07-本月-盘点结果'!$B:$C,2,0) -> 菌汤火锅底料（105G*60袋/箱） | T8: =VLOOKUP(R8,'CA07-本月-盘点结果'!B:I,8,0) -> 214.2 | U8: =T8-Q8-Q9-Q10-W8 -> 41.025 | W8: =216*0.11 -> 23.76 | X8: 多使用41kg | Y8: 公斤 | Z8: 31.71
A9: =C9&F9&G9&J9 -> 加拿大七店1060063拼锅 | B9: 加拿大 | C9: 加拿大七店 | D9: 锅底类 | E9: 锅底类 | F9: 1060063 | H9: 菌汤火锅 | I9: 菌汤火锅 | J9: 拼锅 | K9: 12.95 | L9: 锅 | M9: =IFERROR(VLOOKUP(A9,Sheet3!$A:$B,2,0),0) -> 349 | N9: 0.21 | O9: 1 | Q9: =M9*N9*O9 -> 73.29 | R9: 4514602 | S9: =VLOOKUP(R9,'CA07-本月-盘点结果'!$B:$C,2,0) -> 菌汤火锅底料（105G*60袋/箱） | Y9: 公斤 | Z9: 0
A10: =C10&F10&G10&J10 -> 加拿大七店1060063四宫格 | B10: 加拿大 | C10: 加拿大七店 | D10: 锅底类 | E10: 锅底类 | F10: 1060063 | H10: 菌汤火锅 | I10: 菌汤火锅 | J10: 四宫格 | K10: 5.95 | L10: 锅 | M10: =IFERROR(VLOOKUP(A10,Sheet3!$A:$B,2,0),0) -> 697 | N10: 0.105 | O10: 1 | Q10: =M10*N10*O10 -> 73.185 | R10: 4514602 | S10: =VLOOKUP(R10,'CA07-本月-盘点结果'!$B:$C,2,0) -> 菌汤火锅底料（105G*60袋/箱） | Y10: 公斤 | Z10: 0
A11: =C11&F11&G11&J11 -> 加拿大七店1060064单锅 | B11: 加拿大 | C11: 加拿大七店 | D11: 锅底类 | E11: 锅底类 | F11: 1060064 | H11: 经典麻辣火锅 | I11: 经典麻辣火锅 | J11: 单锅 | K11: 36.95 | L11: 锅 | M11: =IFERROR(VLOOKUP(A11,Sheet3!$A:$B,2,0),0) -> 8 | N11: 1 | O11: 1 | Q11: =M11*N11*O11 -> 8 | R11: 3003393 | S11: =VLOOKUP(R11,'CA07-本月-盘点结果'!$B:$C,2,0) -> 清油麻辣火锅底料（250G*30包/件）_加拿大版 | T11: =VLOOKUP(R11,'CA07-本月-盘点结果'!B:I,8,0) -> 705 | U11: =T11-Q11-Q12-Q13 -> 5.25 | Y11: 公斤 | Z11: 17.25
A12: =C12&F12&G12&J12 -> 加拿大七店1060064拼锅 | B12: 加拿大 | C12: 加拿大七店 | D12: 锅底类 | E12: 锅底类 | F12: 1060064 | H12: 经典麻辣火锅 | I12: 经典麻辣火锅 | J12: 拼锅 | K12: 18.95 | L12: 锅 | M12: =IFERROR(VLOOKUP(A12,Sheet3!$A:$B,2,0),0) -> 777 | N12: 0.5 | O12: 1 | Q12: =M12*N12*O12 -> 388.5 | R12: 3003393 | S12: =VLOOKUP(R12,'CA07-本月-盘点结果'!$B:$C,2,0) -> 清油麻辣火锅底料（250G*30包/件）_加拿大版 | Y12: 公斤 | Z12: 0
A13: =C13&F13&G13&J13 -> 加拿大七店1060064四宫格 | B13: 加拿大 | C13: 加拿大七店 | D13: 锅底类 | E13: 锅底类 | F13: 1060064 | H13: 经典麻辣火锅 | I13: 经典麻辣火锅 | J13: 四宫格 | K13: 9.95 | L13: 锅 | M13: =IFERROR(VLOOKUP(A13,Sheet3!$A:$B,2,0),0) -> 1213 | N13: 0.25 | O13: 1 | Q13: =M13*N13*O13 -> 303.25 | R13: 3003393 | S13: =VLOOKUP(R13,'CA07-本月-盘点结果'!$B:$C,2,0) -> 清油麻辣火锅底料（250G*30包/件）_加拿大版 | Y13: 公斤 | Z13: 0
A14: =C14&F14&G14&J14 -> 加拿大七店1060066单锅 | B14: 加拿大 | C14: 加拿大七店 | D14: 锅底类 | E14: 锅底类 | F14: 1060066 | H14: 番茄火锅 | I14: 番茄火锅 | J14: 单锅 | K14: 24.95 | L14: 锅 | M14: =IFERROR(VLOOKUP(A14,Sheet3!$A:$B,2,0),0) -> 41 | N14: 1.2 | O14: 1 | Q14: =M14*N14*O14 -> 49.2 | R14: 3002745 | S14: =VLOOKUP(R14,'CA07-本月-盘点结果'!$B:$C,2,0) -> 番茄火锅底料（300G*40包/件，加拿大内用） | T14: =VLOOKUP(R14,'CA07-本月-盘点结果'!B:I,8,0) -> 2268 | U14: =T14-Q14-Q15-Q16-W14 -> 677.4 | W14: =444*0.3 -> 133.2 | X14: 多使用677kg | Y14: 公斤 | Z14: 626.4
A15: =C15&F15&G15&J15 -> 加拿大七店1060066拼锅 | B15: 加拿大 | C15: 加拿大七店 | D15: 锅底类 | E15: 锅底类 | F15: 1060066 | H15: 番茄火锅 | I15: 番茄火锅 | J15: 拼锅 | K15: 12.95 | L15: 锅 | M15: =IFERROR(VLOOKUP(A15,Sheet3!$A:$B,2,0),0) -> 1299 | N15: 0.6 | O15: 1 | Q15: =M15*N15*O15 -> 779.4 | R15: 3002745 | S15: =VLOOKUP(R15,'CA07-本月-盘点结果'!$B:$C,2,0) -> 番茄火锅底料（300G*40包/件，加拿大内用） | Y15: 公斤 | Z15: 0
A16: =C16&F16&G16&J16 -> 加拿大七店1060066四宫格 | B16: 加拿大 | C16: 加拿大七店 | D16: 锅底类 | E16: 锅底类 | F16: 1060066 | H16: 番茄火锅 | I16: 番茄火锅 | J16: 四宫格 | K16: 6.95 | L16: 锅 | M16: =IFERROR(VLOOKUP(A16,Sheet3!$A:$B,2,0),0)+35 -> 2096 | N16: 0.3 | O16: 1 | Q16: =M16*N16*O16 -> 628.8 | R16: 3002745 | S16: =VLOOKUP(R16,'CA07-本月-盘点结果'!$B:$C,2,0) -> 番茄火锅底料（300G*40包/件，加拿大内用） | Y16: 公斤 | Z16: 0
A17: =C17&F17&G17&J17 -> 加拿大七店1060115单锅 | B17: 加拿大 | C17: 加拿大七店 | D17: 锅底类 | E17: 锅底类 | F17: 1060115 | H17: 胡椒猪肚鸡火锅 | I17: 胡椒猪肚鸡火锅 | J17: 单锅 | K17: 40.95 | L17: 锅 | M17: =IFERROR(VLOOKUP(A17,Sheet3!$A:$B,2,0),0) -> 5 | N17: 0.2 | O17: 1 | P17: 2.2 | Q17: =M17*N17*O17 -> 1 | R17: 4504167 | S17: =VLOOKUP(R17,'CA07-本月-盘点结果'!$B:$C,2,0) -> 猪肚（LB） | T17: =VLOOKUP(R17,'CA07-本月-盘点结果'!B:I,8,0) -> 264 | U17: =T17-Q17*P17-Q18*P18-Q19*P19-Q135*P135-Q136*P136 -> 83.82 | Y17: 磅 | Z17: 115.94
A18: =C18&F18&G18&J18 -> 加拿大七店1060115四宫格 | B18: 加拿大 | C18: 加拿大七店 | D18: 锅底类 | E18: 锅底类 | F18: 1060115 | H18: 胡椒猪肚鸡火锅 | I18: 胡椒猪肚鸡火锅 | J18: 四宫格 | K18: 9.95 | L18: 锅 | M18: =IFERROR(VLOOKUP(A18,Sheet3!$A:$B,2,0),0) -> 670 | N18: 0.1 | O18: 1 | P18: 2.2 | Q18: =M18*N18*O18 -> 67 | R18: 4504167 | S18: =VLOOKUP(R18,'CA07-本月-盘点结果'!$B:$C,2,0) -> 猪肚（LB） | Y18: 磅 | Z18: 0
A19: =C19&F19&G19&J19 -> 加拿大七店1060115拼锅 | B19: 加拿大 | C19: 加拿大七店 | D19: 锅底类 | E19: 锅底类 | F19: 1060115 | H19: 胡椒猪肚鸡火锅 | I19: 胡椒猪肚鸡火锅 | J19: 拼锅 | K19: 18.95 | L19: 锅 | M19: =IFERROR(VLOOKUP(A19,Sheet3!$A:$B,2,0),0) -> 278 | N19: 0.05 | O19: 1 | P19: 2.2 | Q19: =M19*N19*O19 -> 13.9 | R19: 4504167 | S19: =VLOOKUP(R19,'CA07-本月-盘点结果'!$B:$C,2,0) -> 猪肚（LB） | Y19: 磅 | Z19: 0
A20: =C20&F20&G20&J20 -> 加拿大七店70000769四宫格 | B20: 加拿大 | C20: 加拿大七店 | D20: 锅底类 | E20: 锅底类 | F20: 70000769 | H20: 寿喜锅底 | I20: 寿喜锅底 | J20: 四宫格 | K20: 6.95 | L20: 锅 | M20: =IFERROR(VLOOKUP(A20,Sheet3!$A:$B,2,0),0) -> 690 | N20: 0.129 | O20: 1 | Q20: =M20*N20*O20 -> 89.01 | R20: 1501618 | S20: =VLOOKUP(R20,'CA07-本月-盘点结果'!$B:$C,2,0) -> 日式味淋MIRIN（20L/箱） | T20: =VLOOKUP(R20,'CA07-本月-盘点结果'!B:I,8,0) -> 185 | U20: =T20-Q20-Q21-Q22-W20 -> 24.524 | Y20: 升 | Z20: 19.98
A21: =C21&F21&G21&J21 -> 加拿大七店70000769单锅 | B21: 加拿大 | C21: 加拿大七店 | D21: 锅底类 | E21: 锅底类 | F21: 70000769 | H21: 寿喜锅底 | I21: 寿喜锅底 | J21: 单锅 | K21: 24.95 | L21: 锅 | M21: =IFERROR(VLOOKUP(A21,Sheet3!$A:$B,2,0),0) -> 8 | N21: 0.516 | O21: 1 | Q21: =M21*N21*O21 -> 4.128 | R21: 1501618 | S21: =VLOOKUP(R21,'CA07-本月-盘点结果'!$B:$C,2,0) -> 日式味淋MIRIN（20L/箱） | Y21: 升 | Z21: 0
A22: =C22&F22&G22&J22 -> 加拿大七店70000769拼锅 | B22: 加拿大 | C22: 加拿大七店 | D22: 锅底类 | E22: 锅底类 | F22: 70000769 | H22: 寿喜锅底 | I22: 寿喜锅底 | J22: 拼锅 | K22: 12.95 | L22: 锅 | M22: =IFERROR(VLOOKUP(A22,Sheet3!$A:$B,2,0),0) -> 261 | N22: 0.258 | O22: 1 | Q22: =M22*N22*O22 -> 67.338 | R22: 1501618 | S22: =VLOOKUP(R22,'CA07-本月-盘点结果'!$B:$C,2,0) -> 日式味淋MIRIN（20L/箱） | Y22: 升 | Z22: 0
A23: =C23&F23&G23&J23 -> 加拿大七店70002428四宫格 | B23: 加拿大 | C23: 加拿大七店 | D23: 锅底类 | E23: 锅底类 | F23: 70002428 | H23: 麻辣牛奶火锅 | I23: 麻辣牛奶火鍋 | J23: 四宫格 | K23: 5.95 | L23: 锅 | M23: =IFERROR(VLOOKUP(A23,Sheet3!$A:$B,2,0),0) -> 620 | N23: 0.2 | O23: 1 | P23: 20 | Q23: =M23*N23*O23 -> 124 | R23: 3000759 | S23: =VLOOKUP(R23,'CA07-本月-盘点结果'!$B:$C,2,0) -> 清油底料（300G*40包/件） | Y23: 公斤 | Z23: 0
A24: =C24&F24&G24&J24 -> 加拿大七店70002428拼锅 | B24: 加拿大 | C24: 加拿大七店 | D24: 锅底类 | E24: 锅底类 | F24: 70002428 | H24: 麻辣牛奶火锅 | I24: 麻辣牛奶火鍋 | J24: 拼锅 | K24: 11.95 | L24: 锅 | M24: =IFERROR(VLOOKUP(A24,Sheet3!$A:$B,2,0),0) -> 295 | N24: 0.4 | O24: 1 | P24: 20 | Q24: =M24*N24*O24 -> 118 | R24: 3000759 | S24: =VLOOKUP(R24,'CA07-本月-盘点结果'!$B:$C,2,0) -> 清油底料（300G*40包/件） | Y24: 公斤 | Z24: 0
A25: =C25&F25&G25&J25 -> 加拿大七店70002428单锅 | B25: 加拿大 | C25: 加拿大七店 | D25: 锅底类 | E25: 锅底类 | F25: 70002428 | H25: 麻辣牛奶火锅 | I25: 麻辣牛奶火鍋 | J25: 单锅 | K25: 24.95 | L25: 锅 | M25: =IFERROR(VLOOKUP(A25,Sheet3!$A:$B,2,0),0) -> 3 | N25: 0.8 | O25: 1 | P25: 20 | Q25: =M25*N25*O25 -> 2.4 | R25: 3000759 | S25: =VLOOKUP(R25,'CA07-本月-盘点结果'!$B:$C,2,0) -> 清油底料（300G*40包/件） | Y25: 公斤 | Z25: 0
A26: =C26&F26&G26&J26 -> 加拿大七店90000413单锅 | B26: 加拿大 | C26: 加拿大七店 | D26: 锅底类 | E26: 锅底类 | F26: 90000413 | H26: 冬阴功锅底 | I26: 冬阴功锅底 | J26: 单锅 | K26: 24.95 | L26: 锅 | M26: =IFERROR(VLOOKUP(A26,Sheet3!$A:$B,2,0),0) -> 7 | N26: 0.6 | O26: 1 | P26: 3 | Q26: =M26*N26*O26 -> 4.2 | R26: 4505163 | S26: =VLOOKUP(R26,'CA07-本月-盘点结果'!$B:$C,2,0) -> 冬阴功酱（PENTA，3KG*6包/件） | T26: =VLOOKUP(R26,'CA07-本月-盘点结果'!B:I,8,0) -> 55 | U26: =(T26*P26-Q26-Q27-Q28)/P26 -> -9.9 | Y26: 包 | Z26: 12.4
A27: =C27&F27&G27&J27 -> 加拿大七店90000413拼锅 | B27: 加拿大 | C27: 加拿大七店 | D27: 锅底类 | E27: 锅底类 | F27: 90000413 | H27: 冬阴功锅底 | I27: 冬阴功锅底 | J27: 拼锅 | K27: 11.95 | L27: 锅 | M27: =IFERROR(VLOOKUP(A27,Sheet3!$A:$B,2,0),0) -> 321 | N27: 0.3 | O27: 1 | P27: 3 | Q27: =M27*N27*O27 -> 96.3 | R27: 4505163 | S27: =VLOOKUP(R27,'CA07-本月-盘点结果'!$B:$C,2,0) -> 冬阴功酱（PENTA，3KG*6包/件） | Y27: 包 | Z27: 0
A28: =C28&F28&G28&J28 -> 加拿大七店90000413四宫格 | B28: 加拿大 | C28: 加拿大七店 | D28: 锅底类 | E28: 锅底类 | F28: 90000413 | H28: 冬阴功锅底 | I28: 冬阴功锅底 | J28: 四宫格 | K28: 5.95 | L28: 锅 | M28: =IFERROR(VLOOKUP(A28,Sheet3!$A:$B,2,0),0) -> 628 | N28: 0.15 | O28: 1 | P28: 3 | Q28: =M28*N28*O28 -> 94.2 | R28: 4505163 | S28: =VLOOKUP(R28,'CA07-本月-盘点结果'!$B:$C,2,0) -> 冬阴功酱（PENTA，3KG*6包/件） | Y28: 包 | Z28: 0
A29: =C29&F29&G29&J29 -> 加拿大七店90000659单锅 | B29: 加拿大 | C29: 加拿大七店 | D29: 锅底类 | E29: 锅底类 | F29: 90000659 | H29: 海底捞椰子鸡火锅 | I29: 椰子鸡火锅 | J29: 单锅 | K29: 39.95 | L29: 锅 | M29: =IFERROR(VLOOKUP(A29,Sheet3!$A:$B,2,0),0) -> 0 | N29: 0.14 | O29: 1 | Q29: =M29*N29*O29 -> 0 | R29: 4519135 | S29: =VLOOKUP(R29,'CA07-本月-盘点结果'!$B:$C,2,0) -> #N/A | T29: =VLOOKUP(R29,'CA07-本月-盘点结果'!B:I,8,0) -> #N/A | U29: =IFERROR(T29-Q29-Q30-Q31,0) -> 0 | Y29: #N/A | Z29: 0
A30: =C30&F30&G30&J30 -> 加拿大七店90000659拼锅 | B30: 加拿大 | C30: 加拿大七店 | D30: 锅底类 | E30: 锅底类 | F30: 90000659 | H30: 海底捞椰子鸡火锅 | I30: 椰子鸡火锅 | J30: 拼锅 | K30: 19.95 | L30: 锅 | M30: =IFERROR(VLOOKUP(A30,Sheet3!$A:$B,2,0),0) -> 0 | N30: 0.07 | O30: 1 | Q30: =M30*N30*O30 -> 0 | R30: 4519135 | S30: =VLOOKUP(R30,'CA07-本月-盘点结果'!$B:$C,2,0) -> #N/A | Y30: #N/A | Z30: 0
A31: =C31&F31&G31&J31 -> 加拿大七店90000659四宫格 | B31: 加拿大 | C31: 加拿大七店 | D31: 锅底类 | E31: 锅底类 | F31: 90000659 | H31: 海底捞椰子鸡火锅 | I31: 椰子鸡火锅 | J31: 四宫格 | K31: 9.95 | L31: 锅 | M31: =IFERROR(VLOOKUP(A31,Sheet3!$A:$B,2,0),0) -> 0 | N31: 0.035 | O31: 1 | Q31: =M31*N31*O31 -> 0 | R31: 4519135 | S31: =VLOOKUP(R31,'CA07-本月-盘点结果'!$B:$C,2,0) -> #N/A | Y31: #N/A | Z31: 0
A32: =C32&F32&G32&J32 -> 加拿大七店902007131071整份 | B32: 加拿大 | C32: 加拿大七店 | D32: 荤菜 | E32: 丸滑类 | F32: 9020071 | G32: 31071 | H32: 香菇猪肉丸 | I32: 香菇贡丸 | J32: 整份 | K32: 5.95 | L32: 份 | M32: =IFERROR(VLOOKUP(A32,Sheet3!$A:$B,2,0),0) -> 157 | N32: 0.1 | O32: 1 | P32: 2.2 | Q32: =M32*N32*O32 -> 15.7 | R32: 1500682 | S32: =VLOOKUP(R32,'CA07-本月-盘点结果'!$B:$C,2,0) -> 梅花猪肉（LB） | T32: =VLOOKUP(R32,'CA07-本月-盘点结果'!B:I,8,0) -> 84.69 | U32: =T32-Q32*P32-Q132*P132 -> 50.15 | Y32: 磅 | Z32: 29.59
A33: =C33&F33&G33&J33 -> 加拿大七店902024331247整份 | B33: 加拿大 | C33: 加拿大七店 | D33: 荤菜 | E33: 丸滑类 | F33: 9020243 | G33: 31247 | H33: 芝士牛肉丸 | I33: 芝士牛肉丸 | J33: 整份 | K33: 6.95 | L33: 份 | M33: =IFERROR(VLOOKUP(A33,Sheet3!$A:$B,2,0),0) -> 0 | N33: 0.1 | O33: 1 | Q33: =M33*N33*O33 -> 0 | S33: =VLOOKUP(R33,'CA07-本月-盘点结果'!$B:$C,2,0) -> #N/A | Y33: #N/A | Z33: 0
A34: =C34&F34&G34&J34 -> 加拿大七店902026331267整份 | B34: 加拿大 | C34: 加拿大七店 | D34: 荤菜 | E34: 丸滑类 | F34: 9020263 | G34: 31267 | H34: 蟹籽鱼包蛋 | I34: 蟹籽鱼包蛋 | J34: 整份 | K34: 8.95 | L34: 份 | M34: =IFERROR(VLOOKUP(A34,Sheet3!$A:$B,2,0),0) -> 0 | N34: 0.1 | O34: 1 | Q34: =M34*N34*O34 -> 0 | R34: 1500731 | S34: =VLOOKUP(R34,'CA07-本月-盘点结果'!$B:$C,2,0) -> #N/A | Y34: #N/A | Z34: 0
A35: =C35&F35&G35&J35 -> 加拿大七店902030531315整份 | B35: 加拿大 | C35: 加拿大七店 | D35: 荤菜 | E35: 丸滑类 | F35: 9020305 | G35: 31315 | H35: 鱼籽福袋 | I35: 鱼籽福袋 | J35: 整份 | K35: 9.95 | L35: 份 | M35: =IFERROR(VLOOKUP(A35,Sheet3!$A:$B,2,0),0) -> 119 | N35: 0.15 | O35: 1 | Q35: =M35*N35*O35 -> 17.85 | R35: 1501608 | S35: =VLOOKUP(R35,'CA07-本月-盘点结果'!$B:$C,2,0) -> 鲜虾福袋（1KG*10包/箱） | T35: =VLOOKUP(R35,'CA07-本月-盘点结果'!B:I,8,0) -> 69 | U35: =T35-Q35-Q36-W35 -> 25.15 | Y35: 公斤 | Z35: 13.58
A36: =C36&F36&G36&J36 -> 加拿大七店902030531316半份 | B36: 加拿大 | C36: 加拿大七店 | D36: 荤菜 | E36: 丸滑类 | F36: 9020305 | G36: 31316 | H36: 鱼籽福袋(半） | I36: 鱼籽福袋 | J36: 半份 | K36: 5.95 | L36: 份 | M36: =IFERROR(VLOOKUP(A36,Sheet3!$A:$B,2,0),0) -> 260 | N36: 0.1 | O36: 1 | Q36: =M36*N36*O36 -> 26 | R36: 1501608 | S36: =VLOOKUP(R36,'CA07-本月-盘点结果'!$B:$C,2,0) -> 鲜虾福袋（1KG*10包/箱） | T36: =VLOOKUP(R36,'CA07-本月-盘点结果'!B:I,8,0) -> 69 | Y36: 公斤 | Z36: 0
A37: =C37&F37&G37&J37 -> 加拿大七店700009771004157半份 | B37: 加拿大 | C37: 加拿大七店 | D37: 荤菜 | E37: 丸滑类 | F37: 70000977 | G37: 1004157 | H37: 脆爽Q弹竹荪虾滑(半) | I37: 脆爽Q弹竹荪虾滑 | J37: 半份 | K37: 9.95 | L37: 份 | M37: =IFERROR(VLOOKUP(A37,Sheet3!$A:$B,2,0),0) -> 0 | N37: 0.09 | O37: 1 | Q37: =M37*N37*O37 -> 0 | R37: 1501633 | S37: =VLOOKUP(R37,'CA07-本月-盘点结果'!$B:$C,2,0) -> 竹笙（1.125KG*4包/箱） | Y37: 公斤 | Z37: 0
A38: =C38&F38&G38&J38 -> 加拿大七店1003023642239整份 | B38: 加拿大 | C38: 加拿大七店 | D38: 素菜 | E38: 菌类 | F38: 10030236 | G38: 42239 | H38: 竹笙 | I38: 整份 | J38: 整份 | K38: 14.95 | L38: 份 | M38: =IFERROR(VLOOKUP(A38,Sheet3!$A:$B,2,0),0) -> 310 | N38: 0.13 | O38: 1 | Q38: =M38*N38*O38 -> 40.3 | R38: 1501633 | S38: =VLOOKUP(R38,'CA07-本月-盘点结果'!$B:$C,2,0) -> 竹笙（1.125KG*4包/箱） | T38: =VLOOKUP(R38,'CA07-本月-盘点结果'!B:I,8,0) -> 17.275 | U38: =T38-Q38/5 -> 9.215 | Y38: 公斤 | Z38: 10.03
A39: =C39&F39&G39&J39 -> 加拿大七店9000042997732份 | B39: 加拿大 | C39: 加拿大七店 | D39: 荤菜 | E39: 丸滑类 | F39: 90000429 | G39: 97732 | H39: 糯米鱼豆腐 | I39: 糯米鱼豆腐 | J39: 份 | K39: 5.95 | L39: 份 | M39: =IFERROR(VLOOKUP(A39,Sheet3!$A:$B,2,0),0) -> 417 | N39: 0.09 | O39: 1 | Q39: =M39*N39*O39 -> 37.53 | R39: 4513296 | S39: =VLOOKUP(R39,'CA07-本月-盘点结果'!$B:$C,2,0) -> 麻薯（2.5KG*4包/箱） | T39: =VLOOKUP(R39,'CA07-本月-盘点结果'!B:I,8,0) -> 32.5 | U39: =T39-Q39 -> -5.03 | Y39: #N/A | Z39: #N/A
A40: =C40&F40&G40&J40 -> 加拿大七店903001932019整份 | B40: 加拿大 | C40: 加拿大七店 | D40: 荤菜 | E40: 河/海鲜类 | F40: 9030019 | G40: 32019 | H40: 冰鲜白虾 | I40: 冻虾 | J40: 整份 | K40: 9.95 | L40: 份 | M40: =IFERROR(VLOOKUP(A40,Sheet3!$A:$B,2,0),0) -> 155 | N40: 0.28 | O40: 1 | P40: 2.2 | Q40: =M40*N40*O40 -> 43.4 | R40: 1500703 | S40: =VLOOKUP(R40,'CA07-本月-盘点结果'!$B:$C,2,0) -> 带头南美白虾（30-40，4LB*6包/箱 ） | T40: =VLOOKUP(R40,'CA07-本月-盘点结果'!B:I,8,0) -> 588 | U40: =T40-Q40*P40-Q41*P41-W40*P40*O40-Q197*P197-Q198*P198-Q199*P199 -> 444.472 | Y40: 磅 | Z40: 65.71
A41: =C41&F41&G41&J41 -> 加拿大七店903001978645半份 | B41: 加拿大 | C41: 加拿大七店 | D41: 荤菜 | E41: 河/海鲜类 | F41: 9030019 | G41: 78645 | H41: 冰鲜白虾(半） | I41: 冻虾 | J41: 半份 | K41: 4.95 | L41: 份 | M41: =IFERROR(VLOOKUP(A41,Sheet3!$A:$B,2,0),0) -> 156 | N41: 0.14 | O41: 1 | P41: 2.2 | Q41: =M41*N41*O41 -> 21.84 | R41: 1500703 | S41: =VLOOKUP(R41,'CA07-本月-盘点结果'!$B:$C,2,0) -> 带头南美白虾（30-40，4LB*6包/箱 ） | Y41: 磅 | Z41: 0
A42: =C42&F42&G42&J42 -> 加拿大七店903002932029整份 | B42: 加拿大 | C42: 加拿大七店 | D42: 荤菜 | E42: 河/海鲜类 | F42: 9030029 | G42: 32029 | H42: 冰鲜墨鱼仔 | I42: 精品墨鱼仔 | J42: 整份 | K42: 13.95 | L42: 份 | M42: =IFERROR(VLOOKUP(A42,Sheet3!$A:$B,2,0),0) -> 51 | N42: 0.28 | O42: 1.1 | Q42: =M42*N42*O42 -> 15.708 | R42: 4519171 | S42: =VLOOKUP(R42,'CA07-本月-盘点结果'!$B:$C,2,0) -> 墨鱼仔（340G*20包/箱） | T42: =VLOOKUP(R42,'CA07-本月-盘点结果'!B:I,8,0) -> 13.6 | U42: =T42-Q42-Q43-W43*O42 -> -23.822 | Y42: 公斤 | Z42: 5.71
A43: =C43&F43&G43&J43 -> 加拿大七店903002932030半份 | B43: 加拿大 | C43: 加拿大七店 | D43: 荤菜 | E43: 河/海鲜类 | F43: 9030029 | G43: 32030 | H43: 冰鲜墨鱼仔(半) | I43: 精品墨鱼仔 | J43: 半份 | K43: 6.95 | L43: 份 | M43: =IFERROR(VLOOKUP(A43,Sheet3!$A:$B,2,0),0) -> 141 | N43: 0.14 | O43: 1.1 | Q43: =M43*N43*O43 -> 21.714 | R43: 4519171 | S43: =VLOOKUP(R43,'CA07-本月-盘点结果'!$B:$C,2,0) -> 墨鱼仔（340G*20包/箱） | Y43: 公斤 | Z43: 0
A44: =C44&F44&G44&J44 -> 加拿大七店903005732057整份 | B44: 加拿大 | C44: 加拿大七店 | D44: 荤菜 | E44: 河/海鲜类 | F44: 9030057 | G44: 32057 | H44: 扇贝 | I44: 扇贝（个） | J44: 整份 | K44: 26.95 | L44: 份 | M44: =IFERROR(VLOOKUP(A44,Sheet3!$A:$B,2,0),0) -> 40 | N44: 0.44 | O44: 1.1 | P44: 2.2 | Q44: =M44*N44*O44 -> 19.36 | R44: 4515468 | S44: =VLOOKUP(R44,'CA07-本月-盘点结果'!$B:$C,2,0) -> 扇贝（3LB*4包/箱） | T44: =VLOOKUP(R44,'CA07-本月-盘点结果'!B:I,8,0) -> 141 | U44: =(T44/P44-Q44-Q45-W44*O44)*P44 -> 38.2468 | Y44: 磅 | Z44: 63.83
A45: =C45&F45&G45&J45 -> 加拿大七店903005732058半份 | B45: 加拿大 | C45: 加拿大七店 | D45: 荤菜 | E45: 河/海鲜类 | F45: 9030057 | G45: 32058 | H45: 扇贝(半) | I45: 扇贝（个） | J45: 半份 | K45: 13.95 | L45: 份 | M45: =IFERROR(VLOOKUP(A45,Sheet3!$A:$B,2,0),0) -> 113 | N45: 0.22 | O45: 1.1 | P45: 2.2 | Q45: =M45*N45*O45 -> 27.346 | R45: 4515468 | S45: =VLOOKUP(R45,'CA07-本月-盘点结果'!$B:$C,2,0) -> 扇贝（3LB*4包/箱） | Y45: 磅 | Z45: 0
A46: =C46&F46&G46&J46 -> 加拿大七店903033032331整份 | B46: 加拿大 | C46: 加拿大七店 | D46: 荤菜 | E46: 河/海鲜类 | F46: 9030330 | G46: 32331 | H46: 脆皖鱼 | I46: 脆皖鱼 | J46: 整份 | K46: 19.95 | L46: 份 | M46: =IFERROR(VLOOKUP(A46,Sheet3!$A:$B,2,0),0) -> 178 | N46: 0.2 | O46: 1 | Q46: =M46*N46*O46 -> 35.6 | R46: 4510656 | S46: =VLOOKUP(R46,'CA07-本月-盘点结果'!$B:$C,2,0) -> #N/A | T46: =VLOOKUP(R46,'CA07-本月-盘点结果'!B:I,8,0) -> #N/A | U46: =T46-Q46-Q47 -> #N/A | Y46: 公斤 | Z46: 6.04
A47: =C47&F47&G47&J47 -> 加拿大七店903033032332半份 | B47: 加拿大 | C47: 加拿大七店 | D47: 荤菜 | E47: 河/海鲜类 | F47: 9030330 | G47: 32332 | H47: 脆皖鱼(半) | I47: 脆皖鱼 | J47: 半份 | K47: 9.95 | L47: 份 | M47: =IFERROR(VLOOKUP(A47,Sheet3!$A:$B,2,0),0) -> 305 | N47: 0.1 | O47: 1.06 | Q47: =M47*N47*O47 -> 32.33 | R47: 4510656 | S47: =VLOOKUP(R47,'CA07-本月-盘点结果'!$B:$C,2,0) -> #N/A | Y47: 公斤 | Z47: 0
A48: =C48&F48&G48&J48 -> 加拿大七店903033432337整份 | B48: 加拿大 | C48: 加拿大七店 | D48: 荤菜 | E48: 河/海鲜类 | F48: 9030334 | G48: 32337 | H48: 生蚝 | I48: 精品生蚝 | J48: 整份 | K48: 12.95 | L48: 份 | M48: =IFERROR(VLOOKUP(A48,Sheet3!$A:$B,2,0),0) -> 0 | N48: 0.11 | O48: 1 | Q48: =M48*N48*O48 -> 0 | R48: 4516993 | S48: =VLOOKUP(R48,'CA07-本月-盘点结果'!$B:$C,2,0) -> #N/A | Y48: #N/A | Z48: 0
A49: =C49&F49&G49&J49 -> 加拿大七店903040732439整份 | B49: 加拿大 | C49: 加拿大七店 | D49: 荤菜 | E49: 河/海鲜类 | F49: 9030407 | G49: 32439 | H49: 冰鲜桂花蚌 | I49: 桂花蚌 | J49: 整份 | K49: 33.95 | L49: 份 | M49: =IFERROR(VLOOKUP(A49,Sheet3!$A:$B,2,0),0) -> 59 | N49: 0.2 | O49: 1 | P49: 2.2 | Q49: =M49*N49*O49 -> 11.8 | R49: 4523956 | S49: =VLOOKUP(R49,'CA07-本月-盘点结果'!$B:$C,2,0) -> 桂花蚌（LB） | T49: =VLOOKUP(R49,'CA07-本月-盘点结果'!B:I,8,0) -> 96 | U49: =T49-Q50*P50-Q49*P49 -> 22.08 | X49: 多使用22磅 | Y49: 磅 | Z49: 16.48
A50: =C50&F50&G50&J50 -> 加拿大七店903040732440半份 | B50: 加拿大 | C50: 加拿大七店 | D50: 荤菜 | E50: 河/海鲜类 | F50: 9030407 | G50: 32440 | H50: 冰鲜桂花蚌(半) | I50: 桂花蚌 | J50: 半份 | K50: 16.95 | L50: 份 | M50: =IFERROR(VLOOKUP(A50,Sheet3!$A:$B,2,0),0) -> 218 | N50: 0.1 | O50: 1 | P50: 2.2 | Q50: =M50*N50*O50 -> 21.8 | R50: 4523956 | S50: =VLOOKUP(R50,'CA07-本月-盘点结果'!$B:$C,2,0) -> 桂花蚌（LB） | Y50: 磅 | Z50: 0
A51: =C51&F51&G51&J51 -> 加拿大七店7000050957036整份 | B51: 加拿大 | C51: 加拿大七店 | D51: 荤菜 | E51: 河/海鲜类 | F51: 70000509 | G51: 57036 | H51: 鱿鱼卷(花) | I51: 鱿鱼卷(花) | J51: 整份 | K51: 8.95 | L51: 份 | M51: =IFERROR(VLOOKUP(A51,Sheet3!$A:$B,2,0),0) -> 182 | N51: 0.15 | O51: 1.07 | Q51: =M51*N51*O51 -> 29.211 | R51: 1501628 | S51: =VLOOKUP(R51,'CA07-本月-盘点结果'!$B:$C,2,0) -> 鱿鱼花（280G*12包/箱） | T51: =VLOOKUP(R51,'CA07-本月-盘点结果'!B:I,8,0) -> 47.04 | U51: =T51-Q51 -> 17.829 | Y51: 公斤 | Z51: 25.24
A52: =C52&F52&G52&J52 -> 加拿大七店7000064877308整份 | B52: 加拿大 | C52: 加拿大七店 | D52: 荤菜 | E52: 河/海鲜类 | F52: 70000648 | G52: 77308 | H52: 澳洲青边鲍 | I52: 鲍鱼 | J52: 整份 | K52: 18.95 | L52: 份 | M52: =IFERROR(VLOOKUP(A52,Sheet3!$A:$B,2,0),0) -> 39 | N52: 0.08 | O52: 1 | Q52: =M52*N52*O52 -> 3.12 | R52: 4516992 | S52: =VLOOKUP(R52,'CA07-本月-盘点结果'!$B:$C,2,0) -> 澳洲青边鲍鱼（1KG/盒） | T52: =VLOOKUP(R52,'CA07-本月-盘点结果'!B:I,8,0) -> 34 | U52: =T52-Q52-W52 -> 30.88 | Y52: 公斤 | Z52: 16.5
A53: =C53&F53&G53&J53 -> 加拿大七店7000147679074整份 | B53: 加拿大 | C53: 加拿大七店 | D53: 荤菜 | E53: 河/海鲜类 | F53: 70001476 | G53: 79074 | H53: 黑鱼片 | I53: 黑鱼片 | J53: 整份 | K53: 17.95 | L53: 份 | M53: =IFERROR(VLOOKUP(A53,Sheet3!$A:$B,2,0),0) -> 170 | N53: 0.2 | O53: 1.06 | Q53: =M53*N53*O53 -> 36.04 | R53: 4018965 | S53: =VLOOKUP(R53,'CA07-本月-盘点结果'!$B:$C,2,0) -> 黑鱼片（1KG*10包/箱） | T53: =VLOOKUP(R53,'CA07-本月-盘点结果'!B:I,8,0) -> 74 | U53: =T53-Q53-Q54 -> 5.312 | Y53: 公斤 | Z53: 14.37
A54: =C54&F54&G54&J54 -> 加拿大七店7000147679075半份 | B54: 加拿大 | C54: 加拿大七店 | D54: 荤菜 | E54: 河/海鲜类 | F54: 70001476 | G54: 79075 | H54: 黑鱼片(半） | I54: 黑鱼片 | J54: 半份 | K54: 8.95 | L54: 份 | M54: =IFERROR(VLOOKUP(A54,Sheet3!$A:$B,2,0),0) -> 308 | N54: 0.1 | O54: 1.06 | Q54: =M54*N54*O54 -> 32.648 | R54: 4018965 | S54: =VLOOKUP(R54,'CA07-本月-盘点结果'!$B:$C,2,0) -> 黑鱼片（1KG*10包/箱） | Y54: 公斤 | Z54: 0
A55: =C55&F55&G55&J55 -> 加拿大七店901000930009整份 | B55: 加拿大 | C55: 加拿大七店 | D55: 荤菜 | E55: 牛/羊肉 | F55: 9010009 | G55: 30009 | H55: 特选羊肉 | I55: 草原羔羊肉卷 | J55: 整份 | K55: 13.95 | L55: 份 | M55: =IFERROR(VLOOKUP(A55,Sheet3!$A:$B,2,0),0) -> 1939 | N55: 0.15 | O55: 1.1 | P55: 2.2 | Q55: =M55*N55*O55*P55 -> 703.857 | R55: 1500679 | S55: =VLOOKUP(R55,'CA07-本月-盘点结果'!$B:$C,2,0) -> 羊肉卷（LB） | T55: =VLOOKUP(R55,'CA07-本月-盘点结果'!B:I,8,0) -> 2495.42 | U55: =T55-Q55-W55-Q56 -> 1013.654 | X55: 多使用1013磅请核实原因 | Y55: 磅 | Z55: 27.4
A56: =C56&F56&G56&J56 -> 加拿大七店900016901003544半份 | B56: 加拿大 | C56: 加拿大七店 | D56: 荤菜 | E56: 牛/羊肉 | F56: 90001690 | G56: 1003544 | H56: 特选羊肉（赠送） | J56: 半份 | K56: 13.95 | L56: 份 | M56: =IFERROR(VLOOKUP(A56,Sheet3!$A:$B,2,0),0) -> 2143 | N56: 0.15 | O56: 1.1 | P56: 2.2 | Q56: =M56*N56*O56*P56 -> 777.909 | Y56: 磅 | Z56: 27.4
A57: =C57&F57&G57&J57 -> 加拿大七店901001930019整份 | B57: 加拿大 | C57: 加拿大七店 | D57: 荤菜 | E57: 牛/羊肉 | F57: 9010019 | G57: 30019 | H57: 精品肥牛 | I57: 精品肥牛 | J57: 整份 | K57: 10.95 | L57: 份 | M57: =IFERROR(VLOOKUP(A57,Sheet3!$A:$B,2,0),0) -> 4550 | N57: 0.16 | O57: 1.2 | P57: 2.2 | Q57: =M57*N57*O57 -> 873.6 | R57: 1500677 | S57: =VLOOKUP(R57,'CA07-本月-盘点结果'!$B:$C,2,0) -> 牛腩肉（LB） | T57: =VLOOKUP(R57,'CA07-本月-盘点结果'!B:I,8,0) -> 5629.53 | U57: =(T57/P57-Q57-Q58-Q64-Q163-Q211-W57*O57)*P57 -> 2176.41 | X57: 多使用2176磅 | Y57: 磅 | Z57: 206.07
A58: =C58&F58&G58&J58 -> 加拿大七店900020671004336整份 | B58: 加拿大 | C58: 加拿大七店 | D58: 荤菜 | E58: 牛/羊肉 | F58: 90002067 | G58: 1004336 | H58: 精品肥牛（饭团） | I58: 精品肥牛 | J58: 整份 | K58: 0 | L58: 份 | M58: =IFERROR(VLOOKUP(A58,Sheet3!$A:$B,2,0),0) -> 3624 | N58: 0.16 | O58: 1.2 | P58: 2.2 | Q58: =M58*N58*O58 -> 695.808 | R58: 1500677 | S58: =VLOOKUP(R58,'CA07-本月-盘点结果'!$B:$C,2,0) -> 牛腩肉（LB） | Y58: 磅 | Z58: 0
A59: =C59&F59&G59&J59 -> 加拿大七店901005130053整份 | B59: 加拿大 | C59: 加拿大七店 | D59: 荤菜 | E59: 牛/羊肉 | F59: 9010051 | G59: 30053 | H59: 雪花和牛 | I59: 澳洲肥牛(和牛) | J59: 整份 | K59: 49.95 | L59: 份 | M59: =IFERROR(VLOOKUP(A59,Sheet3!$A:$B,2,0),0) -> 270 | N59: 0.16 | O59: 1.1 | Q59: =M59*N59*O59 -> 47.52 | R59: 4500067 | S59: =VLOOKUP(R59,'CA07-本月-盘点结果'!$B:$C,2,0) -> 美国和牛 | T59: =VLOOKUP(R59,'CA07-本月-盘点结果'!B:I,8,0) -> 71.787 | U59: =T59-Q59 -> 24.267 | Y59: 公斤 | Z59: 2.06
A60: =C60&F60&G60&J60 -> 加拿大七店901018530219整份 | B60: 加拿大 | C60: 加拿大七店 | D60: 荤菜 | E60: 牛/羊肉 | F60: 9010185 | G60: 30219 | H60: AAA级西冷牛肉 | I60: 美国特选肥牛 | J60: 整份 | K60: 19.95 | L60: 份 | M60: =IFERROR(VLOOKUP(A60,Sheet3!$A:$B,2,0),0) -> 1190 | N60: 0.16 | O60: 1.1 | P60: 2.2 | Q60: =M60*N60*O60 -> 209.44 | R60: 1501275 | S60: =VLOOKUP(R60,'CA07-本月-盘点结果'!$B:$C,2,0) -> 西冷牛肉（LB） | T60: =VLOOKUP(R60,'CA07-本月-盘点结果'!B:I,8,0) -> 485.19 | U60: =T60-Q60*P60 -> 24.422 | Y60: 磅 | Z60: 2.32
A61: =C61&F61&G61&J61 -> 加拿大七店901029830355整份 | B61: 加拿大 | C61: 加拿大七店 | D61: 荤菜 | E61: 牛/羊肉 | F61: 9010298 | G61: 30355 | H61: 和牛牛舌 | I61: 薄切牛舌 | J61: 整份 | K61: 12.95 | L61: 份 | M61: =IFERROR(VLOOKUP(A61,Sheet3!$A:$B,2,0),0) -> 838 | N61: 0.12 | O61: 1.15 | P61: 2.2 | Q61: =M61*N61*O61 -> 115.644 | R61: 1500686 | S61: =VLOOKUP(R61,'CA07-本月-盘点结果'!$B:$C,2,0) -> 牛舌（LB） | T61: =VLOOKUP(R61,'CA07-本月-盘点结果'!B:I,8,0) -> 382.79 | U61: =T61-Q61*P61 -> 128.3732 | X61: 多使用128磅 | Y61: 磅 | Z61: 49.74
A62: =C62&F62&G62&J62 -> 加拿大七店901032530395整份 | B62: 加拿大 | C62: 加拿大七店 | D62: 荤菜 | E62: 牛/羊肉 | F62: 9010325 | G62: 30395 | H62: 精品牛板腱肉 | I62: 手切牛板腱 | J62: 整份 | K62: 12.95 | L62: 份 | M62: =IFERROR(VLOOKUP(A62,Sheet3!$A:$B,2,0),0) -> 2010 | N62: 0.16 | O62: 1.1 | P62: 2.2 | Q62: =M62*N62*O62 -> 353.76 | R62: 1501159 | S62: =VLOOKUP(R62,'CA07-本月-盘点结果'!$B:$C,2,0) -> 牛板腱（LB） | T62: =VLOOKUP(R62,'CA07-本月-盘点结果'!B:I,8,0) -> 769.36 | U62: =T62-Q62*P62 -> -8.912 | Y62: 磅 | Z62: 11.66
A63: =C63&F63&G63&J63 -> 加拿大七店907002447025整份 | B63: 加拿大 | C63: 加拿大七店 | D63: 荤菜 | E63: 牛/羊肉 | F63: 9070024 | G63: 47025 | H63: 猪颈肉 | I63: 猪颈肉 | J63: 整份 | K63: 11.95 | L63: 份 | M63: =IFERROR(VLOOKUP(A63,Sheet3!$A:$B,2,0),0) -> 368 | N63: 0.16 | O63: 1 | P63: 2.2 | Q63: =M63*N63*O63 -> 58.88 | R63: 4516994 | S63: =VLOOKUP(R63,'CA07-本月-盘点结果'!$B:$C,2,0) -> 猪颈肉（LB） | T63: =VLOOKUP(R63,'CA07-本月-盘点结果'!B:I,8,0) -> 93.49 | U63: =T63-Q63*P63 -> -36.046 | Y63: 磅 | Z63: 11.87
A64: =C64&F64&G64&J64 -> 加拿大七店7000069377384整份 | B64: 加拿大 | C64: 加拿大七店 | D64: 荤菜 | E64: 牛/羊肉 | F64: 70000693 | G64: 77384 | H64: 精品肥牛（每日特惠） | I64: 优选肥牛 | J64: 整份 | K64: 1.95 | L64: 份 | M64: =IFERROR(VLOOKUP(A64,Sheet3!$A:$B,2,0),0) -> 0 | N64: 0.16 | O64: 1.2 | P64: 2.2 | Q64: =M64*N64*O64 -> 0 | R64: 1500677 | S64: =VLOOKUP(R64,'CA07-本月-盘点结果'!$B:$C,2,0) -> 牛腩肉（LB） | Y64: 磅 | Z64: 0
A65: =C65&F65&G65&J65 -> 加拿大七店7000118278433整份 | B65: 加拿大 | C65: 加拿大七店 | D65: 荤菜 | E65: 牛/羊肉 | F65: 70001182 | G65: 78433 | H65: Prime级去骨牛小排 | I65: 雪花牛小排 | J65: 整份 | K65: 29.95 | L65: 份 | M65: =IFERROR(VLOOKUP(A65,Sheet3!$A:$B,2,0),0) -> 1306 | N65: 0.16 | O65: 1.1 | P65: 2.2 | Q65: =M65*N65*O65 -> 229.856 | R65: 4522918 | S65: =VLOOKUP(R65,'CA07-本月-盘点结果'!$B:$C,2,0) -> 去骨牛小排（LB） | T65: =VLOOKUP(R65,'CA07-本月-盘点结果'!B:I,8,0) -> 610.74 | U65: =T65-Q65*P65-W65*P65 -> 105.0568 | X65: 多使用105磅 | Y65: 磅 | Z65: 50.25
A66: =C66&F66&G66&J66 -> 加拿大七店301002320023整份 | B66: 加拿大 | C66: 加拿大七店 | D66: 荤菜 | E66: 经典火锅菜 | F66: 3010023 | G66: 20023 | H66: 猪血 | I66: 猪血 | J66: 整份 | K66: 11.95 | L66: 份 | M66: =IFERROR(VLOOKUP(A66,Sheet3!$A:$B,2,0),0) -> 190 | N66: 0.48 | O66: 1.2 | P66: 2.2 | Q66: =M66*N66*O66 -> 109.44 | R66: 1501589 | S66: =VLOOKUP(R66,'CA07-本月-盘点结果'!$B:$C,2,0) -> 猪血（20LB/桶） | T66: =VLOOKUP(R66,'CA07-本月-盘点结果'!B:I,8,0) -> 580 | U66: =T66-Q67*P66-Q66*P67 -> -9.248 | Y66: 磅（美国） | Z66: 1.54
A67: =C67&F67&G67&J67 -> 加拿大七店301002320024半份 | B67: 加拿大 | C67: 加拿大七店 | D67: 荤菜 | E67: 经典火锅菜 | F67: 3010023 | G67: 20024 | H67: 猪血(半) | I67: 血旺 | J67: 半份 | K67: 5.95 | L67: 份 | M67: =IFERROR(VLOOKUP(A67,Sheet3!$A:$B,2,0),0) -> 550 | N67: 0.24 | O67: 1.2 | P67: 2.2 | Q67: =M67*N67*O67 -> 158.4 | R67: 1501589 | S67: =VLOOKUP(R67,'CA07-本月-盘点结果'!$B:$C,2,0) -> 猪血（20LB/桶） | Y67: 磅（美国） | Z67: 0
A68: =C68&F68&G68&J68 -> 加拿大七店904004133041整份 | B68: 加拿大 | C68: 加拿大七店 | D68: 荤菜 | E68: 经典火锅菜 | F68: 9040041 | G68: 33041 | H68: 卤肥肠 | I68: 肥肠 | J68: 整份 | K68: 7.95 | L68: 份 | M68: =IFERROR(VLOOKUP(A68,Sheet3!$A:$B,2,0),0) -> 276 | N68: 0.1 | O68: 1.43 | Q68: =M68*N68*O68 -> 39.468 | R68: 1501253 | S68: =VLOOKUP(R68,'CA07-本月-盘点结果'!$B:$C,2,0) -> 猪大肠 （KG） | T68: =VLOOKUP(R68,'CA07-本月-盘点结果'!B:I,8,0)+44.09/2.2 -> 95.410909 | U68: =T68-Q68 -> 55.942909 | Y68: 公斤 | Z68: 53.54
A69: =C69&F69&G69&J69 -> 加拿大七店904005533055整份 | B69: 加拿大 | C69: 加拿大七店 | D69: 荤菜 | E69: 经典火锅菜 | F69: 9040055 | G69: 33055 | H69: 午餐肉 | I69: 午餐肉 | J69: 整份 | K69: 13.95 | L69: 份 | M69: =IFERROR(VLOOKUP(A69,Sheet3!$A:$B,2,0),0) -> 127 | N69: 0.2 | O69: 1 | P69: 0.34 | Q69: =M69*N69*O69 -> 25.4 | R69: 1500860 | S69: =VLOOKUP(R69,'CA07-本月-盘点结果'!$B:$C,2,0) -> 午餐肉（NONGSHIM， 340G*24盒/箱） | T69: =VLOOKUP(R69,'CA07-本月-盘点结果'!B:I,8,0) -> 329 | U69: =(T69*P69-Q69-Q70-W69)/P69 -> 154.29412 | Y69: 盒 | Z69: 464.35
A70: =C70&F70&G70&J70 -> 加拿大七店904005533056半份 | B70: 加拿大 | C70: 加拿大七店 | D70: 荤菜 | E70: 经典火锅菜 | F70: 9040055 | G70: 33056 | H70: 午餐肉(半) | I70: 午餐肉 | J70: 半份 | K70: 6.95 | L70: 份 | M70: =IFERROR(VLOOKUP(A70,Sheet3!$A:$B,2,0),0) -> 340 | N70: 0.1 | O70: 1 | P70: 0.34 | Q70: =M70*N70*O70 -> 34 | R70: 1500860 | S70: =VLOOKUP(R70,'CA07-本月-盘点结果'!$B:$C,2,0) -> 午餐肉（NONGSHIM， 340G*24盒/箱） | Y70: 盒 | Z70: 0
A71: =C71&F71&G71&J71 -> 加拿大七店904006333063整份 | B71: 加拿大 | C71: 加拿大七店 | D71: 荤菜 | E71: 经典火锅菜 | F71: 9040063 | G71: 33063 | H71: 鹌鹑蛋 | I71: 鹌鹑蛋 | J71: 整份 | K71: 5.95 | L71: 份 | M71: =IFERROR(VLOOKUP(A71,Sheet3!$A:$B,2,0),0) -> 804 | N71: 0.14 | O71: 1.1 | P71: 0.85 | Q71: =M71*N71*O71 -> 123.816 | R71: 1500861 | S71: =VLOOKUP(R71,'CA07-本月-盘点结果'!$B:$C,2,0) -> 鹌鹑蛋（850G*12桶/箱） | T71: =VLOOKUP(R71,'CA07-本月-盘点结果'!B:I,8,0) -> 768 | U71: =(T71*P71-Q71-W71)/P71 -> 622.33412 | Y71: 桶 | Z71: 469.91
A72: =C72&F72&G72&J72 -> 加拿大七店904006333064半份 | B72: 加拿大 | C72: 加拿大七店 | D72: 荤菜 | E72: 经典火锅菜 | F72: 9040063 | G72: 33064 | H72: 鹌鹑蛋(半) | I72: 鹌鹑蛋 | J72: 半份 | K72: 2.95 | L72: 份 | M72: =IFERROR(VLOOKUP(A72,Sheet3!$A:$B,2,0),0) -> 0 | N72: 0.07 | O72: 1.1 | P72: 0.85 | Q72: =M72*N72*O72 -> 0 | R72: 1500861 | S72: =VLOOKUP(R72,'CA07-本月-盘点结果'!$B:$C,2,0) -> 鹌鹑蛋（850G*12桶/箱） | Y72: 桶 | Z72: 0
A73: =C73&F73&G73&J73 -> 加拿大七店904006533065整份 | B73: 加拿大 | C73: 加拿大七店 | D73: 荤菜 | E73: 经典火锅菜 | F73: 9040065 | G73: 33065 | H73: 蟹味棒 | I73: 蟹味棒 | J73: 整份 | K73: 9.95 | L73: 份 | M73: =IFERROR(VLOOKUP(A73,Sheet3!$A:$B,2,0),0) -> 121 | N73: 0.1 | O73: 1 | P73: 0.5 | Q73: =M73*N73*O73 -> 12.1 | R73: 1500704 | S73: =VLOOKUP(R73,'CA07-本月-盘点结果'!$B:$C,2,0) -> 蟹肉棒（巴芬湾，500G*20包/箱） | T73: =VLOOKUP(R73,'CA07-本月-盘点结果'!B:I,8,0) -> 430 | U73: =(T73*P73-Q73-Q74-W73)/P73 -> 370.9 | Y73: 包 | Z73: 169.78
A74: =C74&F74&G74&J74 -> 加拿大七店904006533066半份 | B74: 加拿大 | C74: 加拿大七店 | D74: 荤菜 | E74: 经典火锅菜 | F74: 9040065 | G74: 33066 | H74: 蟹味棒(半) | I74: 蟹味棒 | J74: 半份 | K74: 4.95 | L74: 份 | M74: =IFERROR(VLOOKUP(A74,Sheet3!$A:$B,2,0),0) -> 349 | N74: 0.05 | O74: 1 | P74: 0.5 | Q74: =M74*N74*O74 -> 17.45 | R74: 1500704 | S74: =VLOOKUP(R74,'CA07-本月-盘点结果'!$B:$C,2,0) -> 蟹肉棒（巴芬湾，500G*20包/箱） | Y74: 包 | Z74: 0
A75: =C75&F75&G75&J75 -> 加拿大七店904033633395整份 | B75: 加拿大 | C75: 加拿大七店 | D75: 荤菜 | E75: 经典火锅菜 | F75: 9040336 | G75: 33395 | H75: 鱼豆腐 | I75: 鱼豆腐(黄的) | J75: 整份 | K75: 5.95 | L75: 份 | M75: =IFERROR(VLOOKUP(A75,Sheet3!$A:$B,2,0),0) -> 413 | N75: 0.06 | O75: 1 | Q75: =M75*N75*O75 -> 24.78 | R75: 1500730 | S75: =VLOOKUP(R75,'CA07-本月-盘点结果'!$B:$C,2,0) -> 鱼豆腐（华生，2.5KG*4包/箱） | T75: =VLOOKUP(R75,'CA07-本月-盘点结果'!B:I,8,0) -> 45 | U75: =T75-Q75 -> 20.22 | Y75: 公斤 | Z75: 88
A76: =C76&F76&G76&J76 -> 加拿大七店301001320013整份 | B76: 加拿大 | C76: 加拿大七店 | D76: 特色菜 | E76: 特色菜类 | F76: 3010013 | G76: 20013 | H76: 捞派滑牛肉 | I76: 捞派麻辣滑牛肉 | J76: 整份 | K76: 16.95 | L76: 份 | M76: =IFERROR(VLOOKUP(A76,Sheet3!$A:$B,2,0),0) -> 484 | N76: 0.3 | O76: 0.65 | P76: 2.2 | Q76: =M76*N76*O76 -> 94.38 | R76: 4515419 | S76: =VLOOKUP(R76,'CA07-本月-盘点结果'!$B:$C,2,0) -> 去肥黄瓜条（LB） | T76: =VLOOKUP(R76,'CA07-本月-盘点结果'!B:I,8,0) -> 319.82 | U76: =T76-Q76*P76-Q77*P77-Q192*P192-Q221*P221 -> -134.3425 | Y76: 磅 | Z76: 37.09
A77: =C77&F77&G77&J77 -> 加拿大七店301001320014半份 | B77: 加拿大 | C77: 加拿大七店 | D77: 特色菜 | E77: 特色菜类 | F77: 3010013 | G77: 20014 | H77: 捞派滑牛肉(半) | I77: 捞派麻辣滑牛肉 | J77: 半份 | K77: 8.95 | L77: 份 | M77: =IFERROR(VLOOKUP(A77,Sheet3!$A:$B,2,0),0) -> 657 | N77: 0.15 | O77: 0.65 | P77: 2.2 | Q77: =M77*N77*O77 -> 64.0575 | R77: 4515419 | S77: =VLOOKUP(R77,'CA07-本月-盘点结果'!$B:$C,2,0) -> 去肥黄瓜条（LB） | Y77: 磅 | Z77: 0
A78: =C78&F78&G78&J78 -> 加拿大七店301001520015整份 | B78: 加拿大 | C78: 加拿大七店 | D78: 特色菜 | E78: 特色菜类 | F78: 3010015 | G78: 20015 | H78: 捞派鲜毛肚 | I78: 捞派毛肚 | J78: 整份 | K78: 19.95 | L78: 份 | M78: =IFERROR(VLOOKUP(A78,Sheet3!$A:$B,2,0),0) -> 115 | N78: 0.2 | O78: 1.5 | Q78: =M78*N78*O78 -> 34.5 | R78: 4522462 | S78: =VLOOKUP(R78,'CA07-本月-盘点结果'!$B:$C,2,0) -> 毛肚（7KG/箱） | T78: =VLOOKUP(R78,'CA07-本月-盘点结果'!B:I,8,0) -> 90.19 | U78: =T78-Q78-Q79-Q80-Q81 -> -39.68 | Y78: 公斤 | Z78: 11.13
A79: =C79&F79&G79&J79 -> 加拿大七店301001520016半份 | B79: 加拿大 | C79: 加拿大七店 | D79: 特色菜 | E79: 特色菜类 | F79: 3010015 | G79: 20016 | H79: 捞派鲜毛肚(半) | I79: 捞派毛肚 | J79: 半份 | K79: 12.95 | L79: 份 | M79: =IFERROR(VLOOKUP(A79,Sheet3!$A:$B,2,0),0) -> 395 | N79: 0.1 | O79: 1.5 | Q79: =M79*N79*O79 -> 59.25 | R79: 4522462 | S79: =VLOOKUP(R79,'CA07-本月-盘点结果'!$B:$C,2,0) -> 毛肚（7KG/箱） | Y79: 公斤 | Z79: 0
A80: =C80&F80&G80&J80 -> 加拿大七店301001720017整份 | B80: 加拿大 | C80: 加拿大七店 | D80: 特色菜 | E80: 特色菜类 | F80: 3010017 | G80: 20017 | H80: 捞派千层牛百叶 | I80: 捞派千层毛肚 | J80: 整份 | K80: 19.95 | L80: 份 | M80: =IFERROR(VLOOKUP(A80,Sheet3!$A:$B,2,0),0) -> 54 | N80: 0.2 | O80: 1.2 | Q80: =M80*N80*O80 -> 12.96 | R80: 4522462 | S80: =VLOOKUP(R80,'CA07-本月-盘点结果'!$B:$C,2,0) -> 毛肚（7KG/箱） | Y80: 公斤 | Z80: 0
A81: =C81&F81&G81&J81 -> 加拿大七店301001720018半份 | B81: 加拿大 | C81: 加拿大七店 | D81: 特色菜 | E81: 特色菜类 | F81: 3010017 | G81: 20018 | H81: 捞派千层牛百叶(半) | I81: 捞派千层毛肚 | J81: 半份 | K81: 10.95 | L81: 份 | M81: =IFERROR(VLOOKUP(A81,Sheet3!$A:$B,2,0),0) -> 193 | N81: 0.1 | O81: 1.2 | Q81: =M81*N81*O81 -> 23.16 | R81: 4522462 | S81: =VLOOKUP(R81,'CA07-本月-盘点结果'!$B:$C,2,0) -> 毛肚（7KG/箱） | Y81: 公斤 | Z81: 0
A82: =C82&F82&G82&J82 -> 加拿大七店301001920019整份 | B82: 加拿大 | C82: 加拿大七店 | D82: 特色菜 | E82: 特色菜类 | F82: 3010019 | G82: 20019 | H82: 捞派黄喉 | I82: 捞派黄喉 | J82: 整份 | K82: 13.95 | L82: 份 | M82: =IFERROR(VLOOKUP(A82,Sheet3!$A:$B,2,0),0) -> 86 | N82: 0.2 | O82: 1.12 | P82: 2.2 | Q82: =M82*N82*O82 -> 19.264 | R82: 1500685 | S82: =VLOOKUP(R82,'CA07-本月-盘点结果'!$B:$C,2,0) -> 牛黄喉（LB） | T82: =VLOOKUP(R82,'CA07-本月-盘点结果'!B:I,8,0) -> 262.41 | U82: =(T82/P82-Q82-Q83)*P82 -> 151.2836 | Y82: 磅 | Z82: 106.91
A83: =C83&F83&G83&J83 -> 加拿大七店301001920020半份 | B83: 加拿大 | C83: 加拿大七店 | D83: 特色菜 | E83: 特色菜类 | F83: 3010019 | G83: 20020 | H83: 捞派黄喉(半) | I83: 捞派黄喉 | J83: 半份 | K83: 7.95 | L83: 份 | M83: =IFERROR(VLOOKUP(A83,Sheet3!$A:$B,2,0),0) -> 279 | N83: 0.1 | O83: 1.12 | P83: 2.2 | Q83: =M83*N83*O83 -> 31.248 | R83: 1500685 | S83: =VLOOKUP(R83,'CA07-本月-盘点结果'!$B:$C,2,0) -> 牛黄喉（LB） | Y83: 磅 | Z83: 0
A84: =C84&F84&G84&J84 -> 加拿大七店901002130021整份 | B84: 加拿大 | C84: 加拿大七店 | D84: 特色菜 | E84: 特色菜类 | F84: 9010021 | G84: 30021 | H84: 捞派羊肉 | I84: 捞派羊肉 | J84: 整份 | K84: 16.95 | L84: 份 | M84: =IFERROR(VLOOKUP(A84,Sheet3!$A:$B,2,0),0) -> 192 | N84: 0.17 | O84: 1 | Q84: =M84*N84*O84 -> 32.64 | R84: 1500996 | S84: =VLOOKUP(R84,'CA07-本月-盘点结果'!$B:$C,2,0) -> 羊腿肉（去骨，KG） | T84: =VLOOKUP(R84,'CA07-本月-盘点结果'!B:I,8,0) -> 38.47 | U84: =T84-Q84-Q85-W85 -> -14.4 | Y84: 公斤 | Z84: 3.19
A85: =C85&F85&G85&J85 -> 加拿大七店901002130022半份 | B85: 加拿大 | C85: 加拿大七店 | D85: 特色菜 | E85: 特色菜类 | F85: 9010021 | G85: 30022 | H85: 捞派羊肉(半) | I85: 捞派羊肉 | J85: 半份 | K85: 8.95 | L85: 份 | M85: =IFERROR(VLOOKUP(A85,Sheet3!$A:$B,2,0),0) -> 238 | N85: 0.085 | O85: 1 | Q85: =M85*N85*O85 -> 20.23 | R85: 1500996 | S85: =VLOOKUP(R85,'CA07-本月-盘点结果'!$B:$C,2,0) -> 羊腿肉（去骨，KG） | Y85: 公斤 | Z85: 0
A86: =C86&F86&G86&J86 -> 加拿大七店902006331063整份 | B86: 加拿大 | C86: 加拿大七店 | D86: 特色菜 | E86: 特色菜类 | F86: 9020063 | G86: 31063 | H86: 捞派虾滑 | I86: 招牌虾滑 | J86: 整份 | K86: 14.95 | L86: 份 | M86: =IFERROR(VLOOKUP(A86,Sheet3!$A:$B,2,0),0) -> 1655 | N86: 0.15 | O86: 1 | Q86: =M86*N86*O86 -> 248.25 | R86: 4020091 | S86: =VLOOKUP(R86,'CA07-本月-盘点结果'!$B:$C,2,0) -> 速冻虾滑（越南，DL443厂，1.6KG*6包/件） | T86: =VLOOKUP(R86,'CA07-本月-盘点结果'!B:I,8,0)+216 -> 628.8 | U86: =T86-V86-Q86-Q196 -> 375.98 | Y86: 公斤 | Z86: 157.4
A87: =C87&F87&G87&J87 -> 加拿大七店902050331839整份 | B87: 加拿大 | C87: 加拿大七店 | D87: 特色菜 | E87: 特色菜类 | F87: 9020503 | G87: 31839 | H87: 捞派麻辣鸡膝 | I87: 麻辣掌中宝 | J87: 整份 | K87: 13.95 | L87: 份 | M87: =IFERROR(VLOOKUP(A87,Sheet3!$A:$B,2,0),0) -> 0 | N87: 0.3 | O87: 1.1 | P87: 2.2 | Q87: =M87*N87*O87 -> 0 | R87: 4516995 | S87: =VLOOKUP(R87,'CA07-本月-盘点结果'!$B:$C,2,0) -> #N/A | U87: =T87-Q87-Q88 -> 0 | Y87: #N/A | Z87: 0
A88: =C88&F88&G88&J88 -> 加拿大七店902050331840半份 | B88: 加拿大 | C88: 加拿大七店 | D88: 特色菜 | E88: 特色菜类 | F88: 9020503 | G88: 31840 | H88: 捞派麻辣鸡膝（半） | I88: 麻辣掌中宝 | J88: 半份 | K88: 6.95 | L88: 份 | M88: =IFERROR(VLOOKUP(A88,Sheet3!$A:$B,2,0),0) -> 0 | N88: 0.15 | O88: 1.1 | P88: 2.2 | Q88: =M88*N88*O88 -> 0 | R88: 4516995 | S88: =VLOOKUP(R88,'CA07-本月-盘点结果'!$B:$C,2,0) -> #N/A | T88: =VLOOKUP(R88,'CA07-本月-盘点结果'!B:I,8,0) -> #N/A | Y88: #N/A | Z88: 0
A89: =C89&F89&G89&J89 -> 加拿大七店903011932119整份 | B89: 加拿大 | C89: 加拿大七店 | D89: 特色菜 | E89: 特色菜类 | F89: 9030119 | G89: 32119 | H89: 捞派巴沙鱼片 | I89: 捞派巴沙鱼片 | J89: 整份 | K89: 13.95 | L89: 份 | M89: =IFERROR(VLOOKUP(A89,Sheet3!$A:$B,2,0),0) -> 318 | N89: 0.3 | O89: 1.1 | Q89: =M89*N89*O89 -> 104.94 | R89: 1500700 | S89: =VLOOKUP(R89,'CA07-本月-盘点结果'!$B:$C,2,0) -> 冷冻巴沙鱼（12-14 ，10KG/箱） | T89: =VLOOKUP(R89,'CA07-本月-盘点结果'!B:I,8,0) -> 325.82 | U89: =T89-Q89-Q90-W89*O89-W90*O90 -> 136.73 | Y89: 公斤 | Z89: 188.67
A90: =C90&F90&G90&J90 -> 加拿大七店903011932120半份 | B90: 加拿大 | C90: 加拿大七店 | D90: 特色菜 | E90: 特色菜类 | F90: 9030119 | G90: 32120 | H90: 捞派巴沙鱼片(半) | I90: 捞派巴沙鱼片 | J90: 半份 | K90: 6.95 | L90: 份 | M90: =IFERROR(VLOOKUP(A90,Sheet3!$A:$B,2,0),0) -> 510 | N90: 0.15 | O90: 1.1 | Q90: =M90*N90*O90 -> 84.15 | R90: 1500700 | S90: =VLOOKUP(R90,'CA07-本月-盘点结果'!$B:$C,2,0) -> 冷冻巴沙鱼（12-14 ，10KG/箱） | Y90: 公斤 | Z90: 0
A91: =C91&F91&G91&J91 -> 加拿大七店1101040750529整份 | B91: 加拿大 | C91: 加拿大七店 | D91: 甜品饮品 | E91: 甜品类 | F91: 11010407 | G91: 50529 | H91: 酒酿圆子（冰镇） | I91: 冰酒酿圆子 | J91: 整份 | K91: 2.95 | L91: 份 | M91: =IFERROR(VLOOKUP(A91,Sheet3!$A:$B,2,0),0) -> 219 | N91: 0.022 | O91: 1.05 | Q91: =M91*N91*O91 -> 5.0589 | R91: 4702451 | S91: =VLOOKUP(R91,'CA07-本月-盘点结果'!$B:$C,2,0) -> 醪糟（米婆婆，900G*6瓶/件） | T91: =VLOOKUP(R91,'CA07-本月-盘点结果'!B:I,8,0) -> 10.8 | U91: =T91-Q91-W91 -> 5.7411 | Y91: 公斤 | Z91: 1.92
A92: =C92&F92&G92&J92 -> 加拿大七店9000047997822个 | B92: 加拿大 | C92: 加拿大七店 | D92: 甜品饮品 | E92: 甜品类 | F92: 90000479 | G92: 97822 | H92: 桃你欢心冰慕斯 | I92: 爱的魔力一圈圈（慕斯蛋糕） | J92: 个 | K92: 3.1 | L92: 份 | M92: =IFERROR(VLOOKUP(A92,Sheet3!$A:$B,2,0),0) -> 0 | N92: 1 | O92: 1 | Q92: =M92*N92*O92 -> 0 | R92: 4032395 | S92: =VLOOKUP(R92,'CA07-本月-盘点结果'!$B:$C,2,0) -> #N/A | Y92: #N/A | Z92: 0
A93: =C93&F93&G93&J93 -> 加拿大七店900012011004228瓶 | B93: 加拿大 | C93: 加拿大七店 | D93: 饮料 | E93: 特调饮品 | F93: 90001201 | G93: 1004228 | H93: 浓浓抹茶生椰 | I93: 夏日抹茶生椰 | J93: 瓶 | K93: 5.95 | L93: 瓶 | M93: =IFERROR(VLOOKUP(A93,Sheet3!$A:$B,2,0),0) -> 282 | N93: 0.4 | O93: 1 | Q93: =M93*N93*O93 -> 112.8 | R93: 4518668 | S93: =VLOOKUP(R93,'CA07-本月-盘点结果'!$B:$C,2,0) -> 厚椰乳（菲诺，1KG*12瓶/件） | T93: =VLOOKUP(R93,'CA07-本月-盘点结果'!B:I,8,0) -> 424 | U93: =T93-Q93-Q94-Q95 -> 111.2 | Y93: 瓶 | Z93: 88.2
A94: =C94&F94&G94&J94 -> 加拿大七店900012011004229扎 | B94: 加拿大 | C94: 加拿大七店 | D94: 饮料 | E94: 特调饮品 | F94: 90001201 | G94: 1004229 | H94: 浓浓抹茶生椰 | I94: 夏日抹茶生椰 | J94: 扎 | K94: 9.95 | L94: 瓶 | M94: =IFERROR(VLOOKUP(A94,Sheet3!$A:$B,2,0),0) -> 67 | N94: 0.8 | O94: 1 | Q94: =M94*N94*O94 -> 53.6 | R94: 4518668 | S94: =VLOOKUP(R94,'CA07-本月-盘点结果'!$B:$C,2,0) -> 厚椰乳（菲诺，1KG*12瓶/件） | Y94: 瓶 | Z94: 0
A95: =C95&F95&G95&J95 -> 加拿大七店900028141109399瓶 | B95: 加拿大 | C95: 加拿大七店 | D95: 饮料 | E95: 特调饮品 | F95: 90002814 | G95: 1109399 | H95: 草莓奶盖椰椰 | I95: 草莓奶盖椰椰 | J95: 瓶 | K95: 6.95 | L95: 瓶 | M95: =IFERROR(VLOOKUP(A95,Sheet3!$A:$B,2,0),0) -> 488 | N95: 0.3 | O95: 1 | Q95: =M95*N95*O95 -> 146.4 | R95: 4518668 | S95: =VLOOKUP(R95,'CA07-本月-盘点结果'!$B:$C,2,0) -> 厚椰乳（菲诺，1KG*12瓶/件） | Y95: 瓶 | Z95: 0
A96: =C96&F96&G96&J96 -> 加拿大七店1201000260002冰镇 | B96: 加拿大 | C96: 加拿大七店 | D96: 饮料 | E96: 饮料 | F96: 12010002 | G96: 60002 | H96: 柠檬冰红茶 341ML | I96: 柠檬茶 | J96: 冰镇 | K96: 2.45 | L96: 份 | M96: =IFERROR(VLOOKUP(A96,Sheet3!$A:$B,2,0),0) -> 133 | N96: 1 | O96: 1 | Q96: =M96*N96*O96 -> 133 | R96: 1500905 | S96: =VLOOKUP(R96,'CA07-本月-盘点结果'!$B:$C,2,0) -> #N/A | T96: =VLOOKUP(R96,'CA07-本月-盘点结果'!B:I,8,0) -> #N/A | U96: =T96-Q97-Q96-W96 -> #N/A | Y96: 听 | Z96: 2
A97: =C97&F97&G97&J97 -> 加拿大七店1201000260002常温 | B97: 加拿大 | C97: 加拿大七店 | D97: 饮料 | E97: 饮料 | F97: 12010002 | G97: 60002 | H97: 柠檬冰红茶 341ML | I97: 柠檬茶 | J97: 常温 | K97: 2.45 | L97: 份 | M97: =IFERROR(VLOOKUP(A97,Sheet3!$A:$B,2,0),0) -> 10 | N97: 1 | O97: 1 | Q97: =M97*N97*O97 -> 10 | R97: 1500905 | S97: =VLOOKUP(R97,'CA07-本月-盘点结果'!$B:$C,2,0) -> #N/A | Y97: 听 | Z97: 0
A98: =C98&F98&G98&J98 -> 加拿大七店1301004070040冰镇 | B98: 加拿大 | C98: 加拿大七店 | D98: 饮料 | E98: 饮料 | F98: 13010040 | G98: 70040 | H98: 可口可乐 | I98: 听可乐 | J98: 冰镇 | K98: 2.45 | L98: 听 | M98: =IFERROR(VLOOKUP(A98,Sheet3!$A:$B,2,0),0) -> 551 | N98: 1 | O98: 1 | Q98: =M98*N98*O98 -> 551 | R98: 1500902 | S98: =VLOOKUP(R98,'CA07-本月-盘点结果'!$B:$C,2,0) -> 可口可乐（355ML*32听/箱） | T98: =VLOOKUP(R98,'CA07-本月-盘点结果'!B:I,8,0) -> 936 | U98: =T98-Q98-Q99-W98 -> 364 | Y98: 听 | Z98: 88
A99: =C99&F99&G99&J99 -> 加拿大七店1301004070040常温 | B99: 加拿大 | C99: 加拿大七店 | D99: 饮料 | E99: 饮料 | F99: 13010040 | G99: 70040 | H99: 可口可乐 | I99: 听可乐 | J99: 常温 | K99: 2.45 | L99: 听 | M99: =IFERROR(VLOOKUP(A99,Sheet3!$A:$B,2,0),0) -> 21 | N99: 1 | O99: 1 | Q99: =M99*N99*O99 -> 21 | R99: 1500902 | S99: =VLOOKUP(R99,'CA07-本月-盘点结果'!$B:$C,2,0) -> 可口可乐（355ML*32听/箱） | Y99: 听 | Z99: 0
A100: =C100&F100&G100&J100 -> 加拿大七店1301004170041冰镇 | B100: 加拿大 | C100: 加拿大七店 | D100: 饮料 | E100: 饮料 | F100: 13010041 | G100: 70041 | H100: 雪碧 | I100: 听雪碧 | J100: 冰镇 | K100: 2.45 | L100: 听 | M100: =IFERROR(VLOOKUP(A100,Sheet3!$A:$B,2,0),0) -> 192 | N100: 1 | O100: 1 | Q100: =M100*N100*O100 -> 192 | R100: 4502101 | S100: =VLOOKUP(R100,'CA07-本月-盘点结果'!$B:$C,2,0) -> #N/A | T100: =VLOOKUP(R100,'CA07-本月-盘点结果'!B:I,8,0) -> #N/A | U100: =T100-Q100-Q101-W100 -> #N/A | Y100: 瓶 | Z100: 77
...

Sheet BI套餐
A1: 月份 | B1: 国家 | C1: 门店名称 | D1: 销售模式 | E1: 大类名称 | F1: 小类名称 | G1: 套餐编码 | H1: 套餐名称 | I1: 套餐规格 | J1: 套餐单价 | K1: 菜品编码 | L1: 菜品名称 | M1: 菜品规格名称 | N1: 菜品单价 | O1: 菜品单位 | P1: 出品数量 | Q1: 出品金额 | R1: 退菜数量 | S1: 退菜金额 | T1: 应收数量 | U1: 应收金额 | V1: 套餐折扣 | W1: 实收金额 | X1: 销售产品净收入 | Y1: 税额 | Z1: 净额 | AA1: 实际出品数量（出品数量-退菜数量）
A2: 202505 | B2: 加拿大 | C2: 加拿大七店 | D2: 堂食 | E2: 套餐 | F2: 套餐类 | G2: 03010184 | H2: 儿童套餐 | I2: 整份 | J2: 10.95 | K2: 09030119 | L2: 捞派巴沙鱼片 | M2: 整份 | N2: 4.78 | O2: 克 | P2: 656 | Q2: 3138.96 | R2: 6 | S2: 28.71 | T2: 650 | U2: 3110.25 | V2: 0.60696766 | W2: 1887.8212 | X2: 1879.6015 | Y2: 89.509379 | Z2: 1790.0921
A3: 202505 | B3: 加拿大 | C3: 加拿大七店 | D3: 堂食 | E3: 套餐 | F3: 套餐类 | G3: 03010184 | H3: 儿童套餐 | I3: 整份 | J3: 10.95 | K3: 09040055 | L3: 午餐肉 | M3: 整份 | N3: 6.97 | O3: 个 | P3: 656 | Q3: 4575.6 | R3: 6 | S3: 41.85 | T3: 650 | U3: 4533.75 | V3: 0.60696766 | W3: 2751.8396 | X3: 2739.8579 | Y3: 130.47605 | Z3: 2609.3819
A4: 202505 | B4: 加拿大 | C4: 加拿大七店 | D4: 堂食 | E4: 套餐 | F4: 套餐类 | G4: 03010184 | H4: 儿童套餐 | I4: 整份 | J4: 10.95 | K4: 09040063 | L4: 鹌鹑蛋 | M4: 整份 | N4: 1.96 | O4: 个 | P4: 656 | Q4: 1288.056 | R4: 6 | S4: 11.781 | T4: 650 | U4: 1276.275 | V4: 0.60696766 | W4: 774.65765 | X4: 771.28474 | Y4: 36.729711 | Z4: 734.55503
A5: 202505 | B5: 加拿大 | C5: 加拿大七店 | D5: 堂食 | E5: 套餐 | F5: 套餐类 | G5: 03010184 | H5: 儿童套餐 | I5: 整份 | J5: 10.95 | K5: 09040065 | L5: 蟹味棒 | M5: 整份 | N5: 3.28 | O5: 个 | P5: 656 | Q5: 2153.976 | R5: 6 | S5: 19.701 | T5: 650 | U5: 2134.275 | V5: 0.60696766 | W5: 1295.4359 | X5: 1289.7955 | Y5: 61.421953 | Z5: 1228.3735
A6: 202505 | B6: 加拿大 | C6: 加拿大七店 | D6: 堂食 | E6: 套餐 | F6: 套餐类 | G6: 03010184 | H6: 儿童套餐 | I6: 整份 | J6: 10.95 | K6: 10020069 | L6: 菠菜 | M6: 整份 | N6: 1.03 | O6: 克 | P6: 656 | Q6: 677.976 | R6: 6 | S6: 6.201 | T6: 650 | U6: 671.775 | V6: 0.60696766 | W6: 407.7457 | X6: 405.97035 | Y6: 19.332903 | Z6: 386.63745
A7: 202505 | B7: 加拿大 | C7: 加拿大七店 | D7: 堂食 | E7: 套餐 | F7: 套餐类 | G7: 03010184 | H7: 儿童套餐 | I7: 整份 | J7: 10.95 | K7: 11010086 | L7: 生面条 | M7: 整份 | N7: - | O7: 克 | P7: 656 | Q7: - | R7: 6 | S7: - | T7: 650 | U7: - | V7: 0.60696766 | W7: - | X7: 0 | Y7: 0 | Z7: 0
A8: 202505 | B8: 加拿大 | C8: 加拿大七店 | D8: 堂食 | E8: 套餐 | F8: 套餐类 | G8: 1000000303 | H8: 超值单人套餐（2人份） | I8: 套餐 | J8: 33.9 | K8: 01010106 | L8: 清水火锅 | M8: 四宫格 | N8: 0 | O8: 锅 | P8: 348 | Q8: 0 | R8: 6 | S8: 0 | T8: 342 | U8: 0 | V8: 1.0713018 | W8: 0 | X8: 0 | Y8: 0 | Z8: 0
A9: 202505 | B9: 加拿大 | C9: 加拿大七店 | D9: 堂食 | E9: 套餐 | F9: 套餐类 | G9: 1000000303 | H9: 超值单人套餐（2人份） | I9: 套餐 | J9: 33.9 | K9: 01060061 | L9: 清油麻辣火锅 | M9: 四宫格 | N9: 7.95 | O9: 锅 | P9: 73 | Q9: 580.35 | R9: 2 | S9: 15.9 | T9: 71 | U9: 564.45 | V9: 1.0713018 | W9: 604.69633 | X9: 631.14 | Y9: 30.02 | Z9: 601.12
A10: 202505 | B10: 加拿大 | C10: 加拿大七店 | D10: 堂食 | E10: 套餐 | F10: 套餐类 | G10: 1000000303 | H10: 超值单人套餐（2人份） | I10: 套餐 | J10: 33.9 | K10: 01060062 | L10: 三鲜猪骨火锅 | M10: 四宫格 | N10: 6.95 | O10: 锅 | P10: 105 | Q10: 729.75 | R10: 1 | S10: 6.95 | T10: 104 | U10: 722.8 | V10: 1.0713018 | W10: 774.33698 | X10: 820.09 | Y10: 39.1 | Z10: 780.99
A11: 202505 | B11: 加拿大 | C11: 加拿大七店 | D11: 堂食 | E11: 套餐 | F11: 套餐类 | G11: 1000000303 | H11: 超值单人套餐（2人份） | I11: 套餐 | J11: 33.9 | K11: 01060063 | L11: 菌汤火锅 | M11: 四宫格 | N11: 6.95 | O11: 锅 | P11: 62 | Q11: 430.9 | R11: 0 | S11: 0 | T11: 62 | U11: 430.9 | V11: 1.0713018 | W11: 461.62397 | X11: 489.25 | Y11: 23.29 | Z11: 465.96
A12: 202505 | B12: 加拿大 | C12: 加拿大七店 | D12: 堂食 | E12: 套餐 | F12: 套餐类 | G12: 1000000303 | H12: 超值单人套餐（2人份） | I12: 套餐 | J12: 33.9 | K12: 01060066 | L12: 番茄火锅 | M12: 四宫格 | N12: 6.95 | O12: 锅 | P12: 108 | Q12: 750.6 | R12: 3 | S12: 20.85 | T12: 105 | U12: 729.75 | V12: 1.0713018 | W12: 781.78252 | X12: 826.89 | Y12: 39.42 | Z12: 787.47
A13: 202505 | B13: 加拿大 | C13: 加拿大七店 | D13: 堂食 | E13: 套餐 | F13: 套餐类 | G13: 1000000303 | H13: 超值单人套餐（2人份） | I13: 套餐 | J13: 33.9 | K13: 10020113 | L13: 粉丝 | M13: 整份 | N13: 5.95 | O13: 份 | P13: 94 | Q13: 559.3 | R13: 2 | S13: 11.9 | T13: 92 | U13: 547.4 | V13: 1.0713018 | W13: 586.43063 | X13: 591.98 | Y13: 28.3 | Z13: 563.68
A14: 202505 | B14: 加拿大 | C14: 加拿大七店 | D14: 堂食 | E14: 套餐 | F14: 套餐类 | G14: 1000000303 | H14: 超值单人套餐（2人份） | I14: 套餐 | J14: 33.9 | K14: 11010262 | L14: 白米饭 | M14: 整份 | N14: 1.5 | O14: 碗 | P14: 54 | Q14: 81 | R14: 0 | S14: 0 | T14: 54 | U14: 81 | V14: 1.0713018 | W14: 86.77545 | X14: 102.63 | Y14: 4.93 | Z14: 97.7
A15: 202505 | B15: 加拿大 | C15: 加拿大七店 | D15: 堂食 | E15: 套餐 | F15: 套餐类 | G15: 1000000303 | H15: 超值单人套餐（2人份） | I15: 套餐 | J15: 33.9 | K15: 12010006 | L15: 自选饮料 | M15: 位 | N15: 3.99 | O15: 位 | P15: 348 | Q15: 1388.52 | R15: 6 | S15: 23.94 | T15: 342 | U15: 1364.58 | V15: 1.0713018 | W15: 1461.8771 | X15: 1541.1 | Y15: 73.33 | Z15: 1467.77
A16: 202505 | B16: 加拿大 | C16: 加拿大七店 | D16: 堂食 | E16: 套餐 | F16: 套餐类 | G16: 1000000303 | H16: 超值单人套餐（2人份） | I16: 套餐 | J16: 33.9 | K16: 26010234 | L16: 套餐拼盘 | M16: 整份 | N16: 0 | O16: 份 | P16: 348 | Q16: 0 | R16: 6 | S16: 0 | T16: 342 | U16: 0 | V16: 1.0713018 | W16: 0 | X16: 0 | Y16: 0 | Z16: 0
A17: 202505 | B17: 加拿大 | C17: 加拿大七店 | D17: 堂食 | E17: 套餐 | F17: 套餐类 | G17: 1000000303 | H17: 超值单人套餐（2人份） | I17: 套餐 | J17: 33.9 | K17: 91003653 | L17: 双色营养面 | M17: 整份 | N17: 4.95 | O17: 份 | P17: 200 | Q17: 990 | R17: 4 | S17: 19.8 | T17: 196 | U17: 970.2 | V17: 1.0713018 | W17: 1039.3771 | X17: 1080.54 | Y17: 51.77 | Z17: 1028.77
A18: 202505 | B18: 加拿大 | C18: 加拿大七店 | D18: 堂食 | E18: 套餐 | F18: 套餐类 | G18: 1000000304 | H18: 超值单人套餐（3人份） | I18: 套餐 | J18: 50.85 | K18: 01010106 | L18: 清水火锅 | M18: 四宫格 | N18: 0 | O18: 锅 | P18: 36 | Q18: 0 | R18: 1 | S18: 0 | T18: 35 | U18: 0 | V18: 1.0631403 | W18: 0 | X18: 0 | Y18: 0 | Z18: 0
A19: 202505 | B19: 加拿大 | C19: 加拿大七店 | D19: 堂食 | E19: 套餐 | F19: 套餐类 | G19: 1000000304 | H19: 超值单人套餐（3人份） | I19: 套餐 | J19: 50.85 | K19: 01060061 | L19: 清油麻辣火锅 | M19: 四宫格 | N19: 7.95 | O19: 锅 | P19: 19 | Q19: 151.05 | R19: 0 | S19: 0 | T19: 19 | U19: 151.05 | V19: 1.0631403 | W19: 160.58734 | X19: 166.42 | Y19: 7.96 | Z19: 158.46
... A47: 202505 | B47: 加拿大 | C47: 加拿大七店 | D47: 堂食 | E47: 套餐 | F47: 套餐类 | G47: 2601037008 | H47: 超值单人套餐 | I47: 套餐 | J47: 16.95 | K47: 91003653 | L47: 双色营养面 | M47: 整份 | N47: 4.95 | O47: 份 | P47: 567 | Q47: 2806.65 | R47: 13 | S47: 64.35 | T47: 554 | U47: 2742.3 | V47: 1.0748414 | W47: 2947.5376 | X47: 3025.39 | Y47: 142.62 | Z47: 2882.77
AA85: =P85-R85 -> 0
AA86: =P86-R86 -> 0
AA87: =P87-R87 -> 0
AA88: =P88-R88 -> 0
AA89: =P89-R89 -> 0
AA90: =P90-R90 -> 0
AA91: =P91-R91 -> 0
AA92: =P92-R92 -> 0
AA93: =P93-R93 -> 0
AA94: =P94-R94 -> 0
AA95: =P95-R95 -> 0
AA96: =P96-R96 -> 0
... AA164: =P164-R164 -> 0

Sheet 物料分类
A1: 国家/地区代码 | B1: 物料 | C1: 门店标识 | D1: 物料描述 | E1: 物料分类 | F1: 一级分类 | G1: 二级分类 | H1: 标记 | I1: 备注
A2: CA | B2: 1000049 | D2: 金标生抽（海天，4.9L*2桶/件） | E2: 1 | F2: 成本-小料台类 | H2: 6月新增
A3: CA | B3: 1000052 | D3: 韩式辣椒酱（14KG/件） | E3: 1 | F3: 成本-小料台类 | G3: 小料台类 | H3: 2309新增
A4: CA | B4: 1000063 | D4: 滑类挤袋（280*165MM，200根*50把/件） | E4: 2 | F4: 物料消耗 | G4: 其他类
A5: CA | B5: 1000096 | D5: 辣椒酱（辣妹子，920G*12瓶/件） | E5: 1 | F5: 成本-小料台类
A6: CA | B6: 1000098 | D6: 老抽（海天，4.9L*2桶/件） | E6: 1 | F6: 成本-小料台类 | H6: 6月新增
A7: CA | B7: 1000103 | D7: 大块腐乳（王致和，340G*15瓶/件） | E7: 1 | F7: 成本-小料台类 | G7: 小料台 | H7: 10月新增
A8: CA | B8: 1000106 | D8: 毛肚/牛百叶（冻，黄牛） | E8: 1 | F8: 成本-荤菜类
A9: CA | B9: 1000132 | D9: 沙茶酱（牛头，3KG*6瓶/件） | E9: 1 | F9: 成本-小料台类 | H9: 6月新增
A10: CA | B10: 1000233 | D10: 甜面酱（散装，4KG*4包/件） | E10: 1 | F10: 成本-小料台类 | H10: 6月新增
A11: CA | B11: 1000529 | D11: 去皮五花肉 | E11: 1 | F11: 成本-小吃类 | H11: 6月新增 | I11: 240911更新
A12: CA | B12: 1001049 | D12: 甜面酱（六月香，800G*12瓶/件） | E12: 1 | F12: 成本-小料台类 | H12: 7月新增
A13: CA | B13: 1001170 | D13: 墨鱼仔（越南，12KG/件） | E13: 1 | F13: 成本-荤菜类
A14: CA | B14: 1001268 | D14: 辣椒酱（辣妹子，248G*24瓶/件） | E14: 1 | F14: 成本-小料台类
A15: CA | B15: 1001413 | D15: 卤水汁（李锦记，410ML*12瓶/件） | E15: 1 | F15: 成本-荤菜类
A16: CA | B16: 1003028 | D16: 牛油（20KG/件） | E16: 1 | F16: 成本-锅底类 | H16: 6月新增
A17: CA | B17: 1004576 | D17: 虎牙脆（20G*230包/件） | E17: 1 | F17: 成本-小料台类 | H17: 6月新增
A18: CA | B18: 1012802 | D18: 去皮花生米（2KG/包） | E18: 1 | F18: 成本-小料台类 | G18: 小料台类 | H18: 2309新增
A19: CA | B19: 1500009 | D19: 蚝油（李锦记，2.2KG*6桶/件） | E19: 1 | F19: 成本-小料台类
A20: CA | B20: 1500032 | D20: 韭菜花（六必居，300G*20瓶/件） | E20: 1 | F20: 成本-小料台类
A21: CA | B21: 1500058 | D21: 菌粉TLTF-19（10KG*2包/件） | E21: 1 | F21: 成本-锅底类
A22: CA | B22: 1500059 | D22: 三鲜粉TLTF-20（10KG*2包/件） | E22: 1 | F22: 成本-锅底类
A23: CA | B23: 1500091 | D23: 带皮猪五花肉（冻，加拿大） | E23: 2 | F23: 员工餐
A24: CA | B24: 1500352 | D24: 金标生抽（海天，1.75L*6桶/件） | E24: 1 | F24: 成本-小料台类
A25: CA | B25: 1500381 | D25: 金针菇（200G*30袋/件） | E25: 1 | F25: 成本-素菜类 | G25: 素菜 | H25: 10月新增
A26: CA | B26: 1500383 | D26: 土豆（10KG/件） | E26: 1 | F26: 成本-素菜类 | G26: 素菜 | H26: 9月新增
A27: CA | B27: 1500387 | D27: 香菇（5KG/件） | E27: 1 | F27: 成本-素菜类 | G27: 素菜 | H27: 10月新增
A28: CA | B28: 1500529 | D28: 果糖（环泰，5KG*4桶/件） | E28: 1 | F28: 成本-酒水类 | G28: 饮料
A29: CA | B29: 1500612 | D29: 花椒油（川老汇，1.8L*6包/件） | E29: 1 | F29: 成本-小料台类
A30: CA | B30: 1500674 | D30: 无骨牛小排（A5和牛） | E30: 1 | F30: 成本-荤菜类
A31: CA | B31: 1500675 | D31: 西冷牛肉（带肥） | E31: 1 | F31: 成本-荤菜类
A32: CA | B32: 1500676 | D32: 牛仔骨肉（去骨） | E32: 1 | F32: 成本-荤菜类
A33: CA | B33: 1500677 | D33: 牛腩肉（LB） | E33: 1 | F33: 成本-荤菜类
A34: CA | B34: 1500678 | D34: 牛霖肉（LB） | E34: 1 | F34: 成本-小料台类 | I34: 2501更新
A35: CA | B35: 1500679 | D35: 羊肉卷（LB） | E35: 1 | F35: 成本-荤菜类
A36: CA | B36: 1500680 | D36: 带皮去骨鸡腿肉（LB） | E36: 1 | F36: 成本-荤菜类
A37: CA | B37: 1500681 | D37: 去皮五花肉（LB） | E37: 1 | F37: 成本-小吃类 | I37: 240911更新
A38: CA | B38: 1500682 | D38: 梅花猪肉（LB） | E38: 1 | F38: 成本-荤菜类
A39: CA | B39: 1500683 | D39: 猪脑（澳洲，个） | E39: 1 | F39: 成本-荤菜类
A40: CA | B40: 1500684 | D40: 毛肚（LB） | E40: 1 | F40: 成本-荤菜类
A41: CA | B41: 1500685 | D41: 牛黄喉（LB） | E41: 1 | F41: 成本-荤菜类
A42: CA | B42: 1500686 | D42: 牛舌（LB） | E42: 1 | F42: 成本-荤菜类
A43: CA | B43: 1500687 | D43: 猪棒骨（LB） | E43: 1 | F43: 成本-锅底类
A44: CA | B44: 1500688 | D44: 带皮带骨鸡腿（冻） | E44: 1 | F44: 成本-荤菜类
A45: CA | B45: 1500689 | D45: 走地鸡（冻） | E45: 2 | F45: 员工餐
A46: CA | B46: 1500690 | D46: 走地鸡（鲜） | E46: 2 | F46: 员工餐
A47: CA | B47: 1500691 | D47: 鸭血（华生，300G*16盒/箱） | E47: 1 | F47: 成本-荤菜类
A48: CA | B48: 1500692 | D48: 滑嫩血豆腐（300G*20盒/箱） | E48: 1 | F48: 成本-荤菜类
A49: CA | B49: 1500694 | D49: 猪排骨（员工餐， LB） | E49: 2 | F49: 员工餐
... A77: CA | B77: 1500722 | D77: 海带丝（454G*24包/箱） | E77: 1 | F77: 成本-小料台类
A78: CA | B78: 1500723 | D78: 干豆腐丝（227G*20包/箱） | E78: 1 | F78: 成本-素菜类 | G78: 素菜
A79: CA | B79: 1500724 | D79: 豆皮（227G*36包/箱） | E79: 1 | F79: 成本-素菜类 | G79: 素菜
A80: CA | B80: 1500725 | D80: 豆皮（丰业，KG） | E80: 1 | F80: 成本-素菜类
A81: CA | B81: 1500726 | D81: 豆腐丝（丰业，KG） | E81: 1 | F81: 成本-素菜类
A82: CA | B82: 1500727 | D82: 毛豆荚（六福，400G*20包/件） | E82: 1 | F82: 成本-小料台类
A83: CA | B83: 1500728 | D83: 毛豆荚（六福，454G*20包/件） | E83: 1 | F83: 成本-小料台类 | G83: 小料台
A84: CA | B84: 1500729 | D84: 小圆子（华生，300G*32包/箱） | E84: 1 | F84: 成本-小吃类
A85: CA | B85: 1500730 | D85: 鱼豆腐（华生，2.5KG*4包/箱） | E85: 1 | F85: 成本-荤菜类
A86: CA | B86: 1500731 | D86: 蟹籽鱼包蛋（华生，2.5KG*4包/箱） | E86: 1 | F86: 成本-荤菜类
A87: CA | B87: 1500732 | D87: 韭菜鸡蛋水饺（思念，500G*20包/箱） | E87: 1 | F87: 成本-小吃类
A88: CA | B88: 1500733 | D88: 豆腐（30块/桶） | E88: 1 | F88: 成本-素菜类
A89: CA | B89: 1500734 | D89: 鲜腐竹（LB） | E89: 1 | F89: 成本-素菜类
A90: CA | B90: 1500735 | D90: 豆干（LB） | E90: 1 | F90: 成本-素菜类
A91: CA | B91: 1500736 | D91: 滑豆腐（700G*12盒/箱） | E91: 1 | F91: 成本-素菜类
A92: CA | B92: 1500737 | D92: 甜豆浆（3.95L*4桶/箱） | E92: 1 | F92: 成本-酒水类
A93: CA | B93: 1500738 | D93: 迷你菊（紫色，5支/把） | E93: 1 | F93: 成本-荤菜类 | G93: 荤菜
A94: CA | B94: 1500739 | D94: 兰花（鲜，6支/把） | E94: 1 | F94: 成本-荤菜类 | G94: 荤菜
A95: CA | B95: 1500740 | D95: 汕尾叶（鲜， 10支/把） | E95: 1 | F95: 成本-荤菜类 | G95: 荤菜
A96: CA | B96: 1500741 | D96: 玫瑰花（20支/把） | E96: 1 | F96: 成本-荤菜类 | G96: 荤菜
A97: CA | B97: 1500742 | D97: 苏子叶（20片*20包/袋） | E97: 1 | F97: 成本-荤菜类 | G97: 荤菜
A98: CA | B98: 1500743 | D98: 白萝卜（20KG/箱） | E98: 1 | F98: 成本-素菜类
A99: CA | B99: 1500744 | D99: 红萝卜（10KG/箱） | E99: 2 | F99: 员工餐
A100: CA | B100: 1500745 | D100: 菠菜（24把/箱） | E100: 1 | F100: 成本-素菜类
A101: CA | B101: 1500746 | D101: 红彩椒（11LB/箱） | E101: 2 | F101: 员工餐
A102: CA | B102: 1500747 | D102: 青彩椒（25LB/箱） | E102: 2 | F102: 员工餐
A103: CA | B103: 1500748 | D103: 番茄（LB） | E103: 1 | F103: 成本-锅底类
A104: CA | B104: 1500749 | D104: 鲜冬菇（5LB/箱） | E104: 1 | F104: 成本-素菜类
A105: CA | B105: 1500750 | D105: 鲜冬菇（LB） | E105: 1 | F105: 成本-素菜类
A106: CA | B106: 1500751 | D106: 蠔菇（5LB/箱） | E106: 1 | F106: 成本-素菜类
A107: CA | B107: 1500752 | D107: 杏鲍菇（300G*14包/箱） | E107: 1 | F107: 成本-素菜类
A108: CA | B108: 1500753 | D108: 中葱（5KG/箱） | E108: 1 | F108: 成本-小料台类
A109: CA | B109: 1500754 | D109: 青葱（48把/箱） | E109: 1 | F109: 成本-小料台类
... A121: CA | B121: 1500766 | D121: 西芹（24颗/箱） | E121: 1 | F121: 成本-小料台类
A122: CA | B122: 1500768 | D122: 圆白菜/高丽菜（LB） | E122: 2 | F122: 员工餐 | G122: 员工餐 | H122: 2309新增
A123: CA | B123: 1500769 | D123: 白洋葱（50LB/箱） | E123: 1 | F123: 成本-锅底类 | I123: 2501更新
A124: CA | B124: 1500770 | D124: 老姜（30LB/箱） | E124: 1 | F124: 成本-小料台类 | G124: 小料台
A125: CA | B125: 1500771 | D125: 蕃茜（把） | E125: 1 | F125: 成本-小料台类 | G125: 小料台
A126: CA | B126: 1500772 | D126: 蒜肉（5LB*6包/箱） | E126: 1 | F126: 成本-小料台类
A127: CA | B127: 1500773 | D127: 朝天椒（10KG/箱） | E127: 1 | F127: 成本-小料台类
A128: CA | B128: 1500774 | D128: 朝天椒（11LB/箱） | E128: 1 | F128: 成本-小料台类
A129: CA | B129: 1500775 | D129: 日本小黄瓜（20LB/箱） | E129: 1 | F129: 成本-小料台类
A130: CA | B130: 1500776 | D130: 橙子（40LB/箱） | E130: 1 | F130: 成本-小料台类
A131: CA | B131: 1500777 | D131: 香瓜（12个/箱） | E131: 1 | F131: 成本-小料台类
A132: CA | B132: 1500778 | D132: 柠檬（115-140个/箱） | E132: 1 | F132: 成本-小料台类 | G132: 小料台
A133: CA | B133: 1500779 | D133: 提子（18LB/箱） | E133: 1 | F133: 成本-小料台类
A134: CA | B134: 1500780 | D134: 苹果（40LB/箱） | E134: 1 | F134: 成本-小料台类
A135: CA | B135: 1500781 | D135: 咖色鸡蛋（30颗*6板/箱） | E135: 1 | F135: 成本-荤菜类 | G135: 荤菜
A136: CA | B136: 1500782 | D136: 白色鸡蛋（30颗*6板/箱） | E136: 2 | F136: 员工餐
A137: CA | B137: 1500783 | D137: 茄子（30LB/箱） | E137: 2 | F137: 员工餐
A138: CA | B138: 1500784 | D138: 西瓜（LB） | E138: 1 | F138: 成本-酒水类
...

Sheet 折算数量
A1: 规格 | B1: 数量
A2: 套餐 | B2: 1
A3: 整份 | B3: 1
A4: 整份 | B4: 1
A5: 杯 | B5: 1
A6: 壶 | B6: 1
A7: 杯 | B7: 1
A8: 整份 | B8: 1
A9: 冰镇 | B9: 1
A10: 整份 | B10: 1
A11: 冰镇 | B11: 1
A12: 半份 | B12: 0.5
A13: 整份 | B13: 1
... A4318: 整份 | B4318: 1

Sheet 对照表
A1: 区域 | B1: 门店 | C1: 物料号码 | D1: 物料描述 | E1: 大类 | F1: 分类 | G1: 物料描述（通用） | H1: 一级分类 | I1: 二级分类 | J1: 对应菜品编码 | K1: 对应菜品名称 | L1: 备注
A2: CA | C2: 1000049 | D2: 金标生抽（海天，4.9L*2桶/件） | E2: 成本类 | F2: 成本-其他类 | G2: 其他 | J2: 12010001 | K2: 自选小料
A3: CA | C3: 1000096 | D3: 辣椒酱（辣妹子，920G*12瓶/件） | E3: 成本类 | F3: 成本-其他类 | G3: 小料台 | J3: 12010001 | K3: 自选小料
A4: CA | C4: 1000132 | D4: 沙茶酱（牛头，3KG*6瓶/件） | E4: 成本类 | F4: 成本-其他类 | G4: 小料台 | J4: 12010001 | K4: 自选小料
A5: CA | C5: 1001268 | D5: 辣椒酱（辣妹子，248G*24瓶/件） | E5: 成本类 | F5: 成本-其他类 | G5: 小料台 | J5: 12010001 | K5: 自选小料
A6: CA | C6: 1001413 | D6: 卤水汁（李锦记，410ML*12瓶/件） | E6: 成本类 | F6: 成本-其他类 | G6: 其他 | J6: 12010001 | K6: 自选小料
A7: CA | C7: 1004576 | D7: 虎牙脆（20G*230包/件） | E7: 成本类 | F7: 成本-其他类 | G7: 小吃 | J7: 12010001 | K7: 自选小料
A8: CA | C8: 1500009 | D8: 蚝油（李锦记，2.2KG*6桶/件） | E8: 成本类 | F8: 成本-其他类 | G8: 小料台 | J8: 12010001 | K8: 自选小料
A9: CA | C9: 1500032 | D9: 韭菜花（六必居，300G*20瓶/件） | E9: 成本类 | F9: 成本-其他类 | G9: 小料台 | J9: 12010001 | K9: 自选小料
A10: CA | C10: 1500058 | D10: 菌粉TLTF-19（10KG*2包/件） | E10: 成本类 | F10: 成本-锅底类 | G10: 锅底 | J10: 12010001 | K10: 自选小料
A11: CA | C11: 1500059 | D11: 三鲜粉TLTF-20（10KG*2包/件） | E11: 成本类 | F11: 成本-锅底类 | G11: 锅底 | J11: 12010001 | K11: 自选小料
A12: CA | C12: 1500352 | D12: 金标生抽（海天，1.75L*6桶/件） | E12: 成本类 | F12: 成本-其他类 | G12: 其他 | J12: 12010001 | K12: 自选小料
A13: CA | C13: 1500612 | D13: 花椒油（川老汇，1.8L*6包/件） | E13: 成本类 | F13: 成本-其他类 | G13: 小料台 | J13: 12010001 | K13: 自选小料
... A460: CA | C460: 4509690 | D460: 荞麦面（720G*8包/箱） | E460: 成本类 | F460: 成本-其他类 | G460: 其他 | J460: 11010030 | K460: 长寿面
